Workbook

Sheet Database
A1: Giornata | B1: Squadra | C1: Modulo | D1: Giocatore | E1: Ruolo | F1: Voto | G1: Fantavoto | H1: BonusMalus | I1: Titolare | J1: VotoUtile | K1: Sostituisce | L1: VdM (mln €)
A2: 1 | B2: Incontro al capitano | C2: 3-5-2 | D2: Maignan | E2: P | F2: 6 | G2: 5 | H2: -1 | I2: SI | J2: SI | L2: 20
A3: 1 | B3: Incontro al capitano | C3: 3-5-2 | D3: Bremer | E3: D | F3: 7 | G3: 10 | H3: 3 | I3: SI | J3: SI | L3: 35
A4: 1 | B4: Incontro al capitano | C4: 3-5-2 | D4: Stones | E4: D | F4: 6 | G4: 6 | H4: 0 | I4: SI | J4: SI | L4: 12
A5: 1 | B5: Incontro al capitano | C5: 3-5-2 | D5: Molina N. | E5: D | I5: SI | J5: NO | L5: 15
A6: 1 | B6: Incontro al capitano | C6: 3-5-2 | D6: Dominguez B. | E6: C | F6: 6 | G6: 6 | H6: 0 | I6: SI | J6: SI | L6: 9
A7: 1 | B7: Incontro al capitano | C7: 3-5-2 | D7: Casadei | E7: C | F7: 5 | G7: 5 | H7: 0 | I7: SI | J7: SI | L7: 15
A8: 1 | B8: Incontro al capitano | C8: 3-5-2 | D8: Modric | E8: C | F8: 6.5 | G8: 6.5 | H8: 0 | I8: SI | J8: SI | L8: 3.5
A9: 1 | B9: Incontro al capitano | C9: 3-5-2 | D9: Taylor K. | E9: C | F9: 6.5 | G9: 6.5 | H9: 0 | I9: SI | J9: SI | L9: 25
A10: 1 | B10: Incontro al capitano | C10: 3-5-2 | D10: Paz N. | E10: C | F10: 5.5 | G10: 5.5 | H10: 0 | I10: SI | J10: SI | L10: 80
A11: 1 | B11: Incontro al capitano | C11: 3-5-2 | D11: Boga | E11: A | F11: 5.5 | G11: 5.5 | H11: 0 | I11: SI | J11: SI | L11: 8
A12: 1 | B12: Incontro al capitano | C12: 3-5-2 | D12: Dybala | E12: A | F12: 8 | G12: 11 | H12: 3 | I12: SI | J12: SI | L12: 5
A13: 1 | B13: Incontro al capitano | C13: 3-5-2 | D13: Terracciano | E13: P | I13: NO | J13: NO | L13: 0.9
A14: 1 | B14: Incontro al capitano | C14: 3-5-2 | D14: Bartesaghi | E14: D | F14: 6 | G14: 6 | H14: 0 | I14: NO | J14: SI | K14: Molina N. | L14: 22
A15: 1 | B15: Incontro al capitano | C15: 3-5-2 | D15: Obrador | E15: D | I15: NO | J15: NO | L15: 5
A16: 1 | B16: Incontro al capitano | C16: 3-5-2 | D16: Gabbia | E16: D | F16: 6 | G16: 6 | H16: 0 | I16: NO | J16: NO | L16: 17
A17: 1 | B17: Incontro al capitano | C17: 3-5-2 | D17: Kolasinac | E17: D | F17: 6 | G17: 6 | H17: 0 | I17: NO | J17: NO | L17: 4
A18: 1 | B18: Incontro al capitano | C18: 3-5-2 | D18: Locatelli | E18: C | F18: 6 | G18: 6 | H18: 0 | I18: NO | J18: NO | L18: 25
A19: 1 | B19: Incontro al capitano | C19: 3-5-2 | D19: Fagioli | E19: C | F19: 5 | G19: 4.5 | H19: -0.5 | I19: NO | J19: NO | L19: 16
A20: 1 | B20: Incontro al capitano | C20: 3-5-2 | D20: Oulai | E20: C | F20: 6 | G20: 6 | H20: 0 | I20: NO | J20: NO | L20: 28
A21: 1 | B21: Incontro al capitano | C21: 3-5-2 | D21: Mkhitaryan | E21: C | I21: NO | J21: NO | L21: 3
A22: 1 | B22: Incontro al capitano | C22: 3-5-2 | D22: Vitinha O. | E22: A | F22: 5.5 | G22: 5.5 | H22: 0 | I22: NO | J22: NO | L22: 8
A23: 1 | B23: Incontro al capitano | C23: 3-5-2 | D23: Cutrone | E23: A | F23: 6 | G23: 6 | H23: 0 | I23: NO | J23: NO | L23: 4
A24: 1 | B24: Incontro al capitano | C24: 3-5-2 | D24: Camarda | E24: A | I24: NO | J24: NO | L24: 15
A25: 1 | B25: I Bamboli | C25: 3-5-2 | D25: De Gea | E25: P | F25: 5 | G25: 1 | H25: -4 | I25: SI | J25: SI | L25: 3.5
A26: 1 | B26: I Bamboli | C26: 3-5-2 | D26: Carlos Augusto | E26: D | I26: SI | J26: NO | L26: 23
A27: 1 | B27: I Bamboli | C27: 3-5-2 | D27: Solet | E27: D | F27: 6 | G27: 6 | H27: 0 | I27: SI | J27: SI | L27: 23
A28: 1 | B28: I Bamboli | C28: 3-5-2 | D28: Di Lorenzo | E28: D | F28: 6.5 | G28: 6.5 | H28: 0 | I28: SI | J28: SI | L28: 7.5
A29: 1 | B29: I Bamboli | C29: 3-5-2 | D29: Calò | E29: C | F29: 6 | G29: 6 | H29: 0 | I29: SI | J29: SI | L29: 2.5
A30: 1 | B30: I Bamboli | C30: 3-5-2 | D30: Gaetano | E30: C | F30: 6.5 | G30: 7.5 | H30: 1 | I30: SI | J30: SI | L30: 6.5
A31: 1 | B31: I Bamboli | C31: 3-5-2 | D31: Rabiot | E31: C | F31: 7.5 | G31: 11.5 | H31: 4 | I31: SI | J31: SI | L31: 18
A32: 1 | B32: I Bamboli | C32: 3-5-2 | D32: Calhanoglu | E32: C | F32: 7 | G32: 9.5 | H32: 2.5 | I32: SI | J32: SI | L32: 16
A33: 1 | B33: I Bamboli | C33: 3-5-2 | D33: Pellegrini Lo. | E33: C | I33: SI | J33: NO | L33: 8
A34: 1 | B34: I Bamboli | C34: 3-5-2 | D34: Dia | E34: A | F34: 6.5 | G34: 7 | H34: 0.5 | I34: SI | J34: SI | L34: 5
A35: 1 | B35: I Bamboli | C35: 3-5-2 | D35: Hojlund | E35: A | F35: 5.5 | G35: 5.5 | H35: 0 | I35: SI | J35: SI | L35: 60
A36: 1 | B36: I Bamboli | C36: 3-5-2 | D36: Christensen O. | E36: P | I36: NO | J36: NO | L36: 1.4
A37: 1 | B37: I Bamboli | C37: 3-5-2 | D37: Valeri | E37: D | F37: 6 | G37: 6 | H37: 0 | I37: NO | J37: SI | K37: Carlos Augusto | L37: 3
A38: 1 | B38: I Bamboli | C38: 3-5-2 | D38: Celik | E38: D | F38: 6 | G38: 5.5 | H38: -0.5 | I38: NO | J38: NO | L38: 14
A39: 1 | B39: I Bamboli | C39: 3-5-2 | D39: Gaspar K. | E39: D | F39: 7 | G39: 6.5 | H39: -0.5 | I39: NO | J39: NO | L39: 3
A40: 1 | B40: I Bamboli | C40: 3-5-2 | D40: Obert | E40: D | F40: 6 | G40: 6 | H40: 0 | I40: NO | J40: NO | L40: 7
A41: 1 | B41: I Bamboli | C41: 3-5-2 | D41: Ndour | E41: C | F41: 5 | G41: 5 | H41: 0 | I41: NO | J41: SI | K41: Pellegrini Lo. | L41: 20
A42: 1 | B42: I Bamboli | C42: 3-5-2 | D42: Lobotka | E42: C | F42: 6.5 | G42: 6.5 | H42: 0 | I42: NO | J42: NO | L42: 10
A43: 1 | B43: I Bamboli | C43: 3-5-2 | D43: Frendrup | E43: C | F43: 6 | G43: 6 | H43: 0 | I43: NO | J43: NO | L43: 15
A44: 1 | B44: I Bamboli | C44: 3-5-2 | D44: Stankovic A. | E44: C | F44: s.v. | G44: s.v. | I44: NO | J44: NO | L44: 32
A45: 1 | B45: I Bamboli | C45: 3-5-2 | D45: Noslin | E45: A | F45: s.v. | G45: s.v. | I45: NO | J45: NO | L45: 8
A46: 1 | B46: I Bamboli | C46: 3-5-2 | D46: Ghedjemis | E46: A | I46: NO | J46: NO | L46: 7.5
A47: 1 | B47: I Bamboli | C47: 3-5-2 | D47: Varela G. | E47: A | F47: 7 | G47: 10 | H47: 3 | I47: NO | J47: NO | L47: 3
A48: 1 | B48: Schalke 104 | C48: 3-4-3 | D48: Meret | E48: P | F48: 6 | G48: 6.5 | H48: 0.5 | I48: SI | J48: SI | L48: 8
A49: 1 | B49: Schalke 104 | C49: 3-4-3 | D49: Wesley | E49: D | F49: 6.5 | G49: 6.5 | H49: 0 | I49: SI | J49: SI | L49: 40
A50: 1 | B50: Schalke 104 | C50: 3-4-3 | D50: Spinazzola | E50: D | F50: 5.5 | G50: 5.5 | H50: 0 | I50: SI | J50: SI | L50: 3.5
A51: 1 | B51: Schalke 104 | C51: 3-4-3 | D51: Pavlovic | E51: D | F51: 6.5 | G51: 6.5 | H51: 0 | I51: SI | J51: SI | L51: 40
A52: 1 | B52: Schalke 104 | C52: 3-4-3 | D52: Zambo Anguissa | E52: C | F52: 5.5 | G52: 5.5 | H52: 0 | I52: SI | J52: SI | L52: 15
A53: 1 | B53: Schalke 104 | C53: 3-4-3 | D53: Fazzini | E53: C | F53: 6 | G53: 5.5 | H53: -0.5 | I53: SI | J53: SI | L53: 8.5
A54: 1 | B54: Schalke 104 | C54: 3-4-3 | D54: Samardzic | E54: C | F54: 6 | G54: 6 | H54: 0 | I54: SI | J54: SI | L54: 16
A55: 1 | B55: Schalke 104 | C55: 3-4-3 | D55: Chukwueze | E55: C | F55: 7 | G55: 8 | H55: 1 | I55: SI | J55: SI | L55: 18
A56: 1 | B56: Schalke 104 | C56: 3-4-3 | D56: Dovbyk | E56: A | F56: 5 | G56: 5 | H56: 0 | I56: SI | J56: SI | L56: 15
A57: 1 | B57: Schalke 104 | C57: 3-4-3 | D57: Ramos G. | E57: A | F57: 6 | G57: 6 | H57: 0 | I57: SI | J57: SI | L57: 50
A58: 1 | B58: Schalke 104 | C58: 3-4-3 | D58: Adams A. | E58: A | F58: 5.5 | G58: 5.5 | H58: 0 | I58: SI | J58: SI | L58: 15
... A69: 1 | B69: Schalke 104 | C69: 3-4-3 | D69: Kvernadze | E69: A | F69: 6 | G69: 6 | H69: 0 | I69: NO | J69: NO | L69: 4
A70: 1 | B70: Schalke 104 | C70: 3-4-3 | D70: Rrahmani Al. | E70: A | F70: s.v. | G70: s.v. | I70: NO | J70: NO | L70: 7
A71: 1 | B71: Outletico Palermo | C71: 3-4-3 | D71: Svilar | E71: P | F71: 6 | G71: 6.5 | H71: 0.5 | I71: SI | J71: SI | L71: 35
A72: 1 | B72: Outletico Palermo | C72: 3-4-3 | D72: Hermoso | E72: D | F72: 6.5 | G72: 6 | H72: -0.5 | I72: SI | J72: SI | L72: 7
A73: 1 | B73: Outletico Palermo | C73: 3-4-3 | D73: Kalulu | E73: D | F73: 6.5 | G73: 6.5 | H73: 0 | I73: SI | J73: SI | L73: 32
A74: 1 | B74: Outletico Palermo | C74: 3-4-3 | D74: N'Dicka | E74: D | F74: 6.5 | G74: 6.5 | H74: 0 | I74: SI | J74: SI | L74: 35
A75: 1 | B75: Outletico Palermo | C75: 3-4-3 | D75: Vlasic | E75: C | F75: 5.5 | G75: 5.5 | H75: 0 | I75: SI | J75: SI | L75: 10
A76: 1 | B76: Outletico Palermo | C76: 3-4-3 | D76: De Bruyne | E76: C | F76: 7.5 | G76: 11.5 | H76: 4 | I76: SI | J76: SI | L76: 8
A77: 1 | B77: Outletico Palermo | C77: 3-4-3 | D77: Pasalic | E77: C | F77: 5.5 | G77: 5.5 | H77: 0 | I77: SI | J77: SI | L77: 6
A78: 1 | B78: Outletico Palermo | C78: 3-4-3 | D78: Barella | E78: C | F78: 6 | G78: 6 | H78: 0 | I78: SI | J78: SI | L78: 50
A79: 1 | B79: Outletico Palermo | C79: 3-4-3 | D79: Simeone | E79: A | F79: 5.5 | G79: 5.5 | H79: 0 | I79: SI | J79: SI | L79: 7
A80: 1 | B80: Outletico Palermo | C80: 3-4-3 | D80: Martinez L. | E80: A | F80: 5.5 | G80: 5 | H80: -0.5 | I80: SI | J80: SI | L80: 85
A81: 1 | B81: Outletico Palermo | C81: 3-4-3 | D81: Diao | E81: A | F81: 6 | G81: 6 | H81: 0 | I81: SI | J81: SI | L81: 30
A82: 1 | B82: Outletico Palermo | C82: 3-4-3 | D82: Gollini | E82: P | I82: NO | J82: NO | L82: 0.8
A83: 1 | B83: Outletico Palermo | C83: 3-4-3 | D83: Pedersen | E83: D | F83: 6 | G83: 6 | H83: 0 | I83: NO | J83: NO | L83: 3.5
A84: 1 | B84: Outletico Palermo | C84: 3-4-3 | D84: Delprato | E84: D | F84: 6 | G84: 6 | H84: 0 | I84: NO | J84: NO | L84: 6
A85: 1 | B85: Outletico Palermo | C85: 3-4-3 | D85: Ostigard | E85: D | F85: 6.5 | G85: 6.5 | H85: 0 | I85: NO | J85: NO | L85: 13
A86: 1 | B86: Outletico Palermo | C86: 3-4-3 | D86: Mina | E86: D | I86: NO | J86: NO | L86: 2.5
A87: 1 | B87: Outletico Palermo | C87: 3-4-3 | D87: Saelemaekers | E87: C | F87: 6 | G87: 6 | H87: 0 | I87: NO | J87: NO | L87: 20
A88: 1 | B88: Outletico Palermo | C88: 3-4-3 | D88: Busio | E88: C | F88: 6.5 | G88: 6.5 | H88: 0 | I88: NO | J88: NO | L88: 8
A89: 1 | B89: Outletico Palermo | C89: 3-4-3 | D89: Pierotti | E89: C | F89: 6 | G89: 6 | H89: 0 | I89: NO | J89: NO | L89: 4
A90: 1 | B90: Outletico Palermo | C90: 3-4-3 | D90: Unai Gomez | E90: C | F90: s.v. | G90: s.v. | I90: NO | J90: NO | L90: 5
A91: 1 | B91: Outletico Palermo | C91: 3-4-3 | D91: Laurientè | E91: A | F91: 6 | G91: 6 | H91: 0 | I91: NO | J91: NO | L91: 19
A92: 1 | B92: Outletico Palermo | C92: 3-4-3 | D92: Stulic | E92: A | F92: 5 | G92: 5 | H92: 0 | I92: NO | J92: NO | L92: 3.5
A93: 1 | B93: Outletico Palermo | C93: 3-4-3 | D93: Elphege | E93: A | F93: s.v. | G93: s.v. | I93: NO | J93: NO | L93: 4
A94: 1 | B94: GC21 | C94: 3-4-3 | D94: Palmisani | E94: P | F94: 6.5 | G94: 5.5 | H94: -1 | I94: SI | J94: SI | L94: 4
A95: 1 | B95: GC21 | C95: 3-4-3 | D95: Bisseck | E95: D | F95: 7 | G95: 10 | H95: 3 | I95: SI | J95: SI | L95: 50
A96: 1 | B96: GC21 | C96: 3-4-3 | D96: Mancini | E96: D | F96: 6.5 | G96: 6.5 | H96: 0 | I96: SI | J96: SI | L96: 15
A97: 1 | B97: GC21 | C97: 3-4-3 | D97: Cambiaso | E97: D | F97: 5.5 | G97: 5 | H97: -0.5 | I97: SI | J97: SI | L97: 20
A98: 1 | B98: GC21 | C98: 3-4-3 | D98: Ferguson | E98: C | F98: 6 | G98: 6 | H98: 0 | I98: SI | J98: SI | L98: 14
A99: 1 | B99: GC21 | C99: 3-4-3 | D99: Ederson D.S. | E99: C | F99: 6 | G99: 6 | H99: 0 | I99: SI | J99: SI | L99: 45
A100: 1 | B100: GC21 | C100: 3-4-3 | D100: McTominay | E100: C | F100: 6 | G100: 6 | H100: 0 | I100: SI | J100: SI | L100: 40
A101: 1 | B101: GC21 | C101: 3-4-3 | D101: Mastantuono | E101: C | F101: 5.5 | G101: 5.5 | H101: 0 | I101: SI | J101: SI | L101: 45
A102: 1 | B102: GC21 | C102: 3-4-3 | D102: Krstovic | E102: A | F102: 7 | G102: 10 | H102: 3 | I102: SI | J102: SI | L102: 30
A103: 1 | B103: GC21 | C103: 3-4-3 | D103: Esposito F.P. | E103: A | F103: 7.5 | G103: 11.5 | H103: 4 | I103: SI | J103: SI | L103: 45
A104: 1 | B104: GC21 | C104: 3-4-3 | D104: Yildiz | E104: A | F104: 5.5 | G104: 5.5 | H104: 0 | I104: SI | J104: SI | L104: 75
A105: 1 | B105: GC21 | C105: 3-4-3 | D105: Muric | E105: P | F105: 6 | G105: 4 | H105: -2 | I105: NO | J105: NO | L105: 7.5
... A115: 1 | B115: GC21 | C115: 3-4-3 | D115: Pellegrino M. | E115: A | F115: 5 | G115: 4.5 | H115: -0.5 | I115: NO | J115: NO | L115: 15
A116: 1 | B116: GC21 | C116: 3-4-3 | D116: Robinson J. | E116: A | F116: s.v. | G116: s.v. | I116: NO | J116: NO | L116: 8
A117: 1 | B117: Masterchef FC | C117: 3-4-3 | D117: Skorupski | E117: P | F117: 6 | G117: 5 | H117: -1 | I117: SI | J117: SI | L117: 2
A118: 1 | B118: Masterchef FC | C118: 3-4-3 | D118: Norton-Cuffy | E118: D | F118: 6 | G118: 6 | H118: 0 | I118: SI | J118: SI | L118: 15
A119: 1 | B119: Masterchef FC | C119: 3-4-3 | D119: Tiago Gabriel | E119: D | F119: 7 | G119: 10 | H119: 3 | I119: SI | J119: SI | L119: 15
...

Sheet Analisi Bonus
A1: Analisi BonusMalus per Squadra
A2: Dati cumulati su tutte le giornate presenti nel foglio Database
A4: Squadra | B4: Portieri (VU) | C4: Difensori (VU) | D4: Centrocampisti (VU) | E4: Attaccanti (VU) | F4: Totale Voti Utili | G4: Subentrati | H4: Panchinari (no P)
A5: {=_xlfn._xlws.SORT(_xlfn.UNIQUE(Fantacalcio[Squadra]))} -> Evacuo Kaka Toni | B5: =IF($A5="","",SUMIFS(Fantacalcio[BonusMalus],Fantacalcio[Squadra],$A5,Fantacalcio[VotoUtile],"SI",Fantacalcio[Ruolo],"P")) -> -7 | C5: =IF($A5="","",SUMIFS(Fantacalcio[BonusMalus],Fantacalcio[Squadra],$A5,Fantacalcio[VotoUtile],"SI",Fantacalcio[Ruolo],"D")) -> 10 | D5: =IF($A5="","",SUMIFS(Fantacalcio[BonusMalus],Fantacalcio[Squadra],$A5,Fantacalcio[VotoUtile],"SI",Fantacalcio[Ruolo],"C")) -> 8 | E5: =IF($A5="","",SUMIFS(Fantacalcio[BonusMalus],Fantacalcio[Squadra],$A5,Fantacalcio[VotoUtile],"SI",Fantacalcio[Ruolo],"A")) -> 3.5 | F5: =IF($A5="","",SUMIFS(Fantacalcio[BonusMalus],Fantacalcio[Squadra],$A5,Fantacalcio[VotoUtile],"SI")) -> 14.5 | G5: =IF($A5="","",SUMIFS(Fantacalcio[BonusMalus],Fantacalcio[Squadra],$A5,Fantacalcio[Titolare],"NO",Fantacalcio[VotoUtile],"SI")) -> 1.5 | H5: =IF($A5="","",SUMIFS(Fantacalcio[BonusMalus],Fantacalcio[Squadra],$A5,Fantacalcio[Titolare],"NO",Fantacalcio[VotoUtile],"NO",Fantacalcio[Ruolo],"<>P")) -> 1.5
A6: GC21 | B6: =IF($A6="","",SUMIFS(Fantacalcio[BonusMalus],Fantacalcio[Squadra],$A6,Fantacalcio[VotoUtile],"SI",Fantacalcio[Ruolo],"P")) -> -9 | C6: =IF($A6="","",SUMIFS(Fantacalcio[BonusMalus],Fantacalcio[Squadra],$A6,Fantacalcio[VotoUtile],"SI",Fantacalcio[Ruolo],"D")) -> 7.5 | D6: =IF($A6="","",SUMIFS(Fantacalcio[BonusMalus],Fantacalcio[Squadra],$A6,Fantacalcio[VotoUtile],"SI",Fantacalcio[Ruolo],"C")) -> 11.5 | E6: =IF($A6="","",SUMIFS(Fantacalcio[BonusMalus],Fantacalcio[Squadra],$A6,Fantacalcio[VotoUtile],"SI",Fantacalcio[Ruolo],"A")) -> 16.5 | F6: =IF($A6="","",SUMIFS(Fantacalcio[BonusMalus],Fantacalcio[Squadra],$A6,Fantacalcio[VotoUtile],"SI")) -> 26.5 | G6: =IF($A6="","",SUMIFS(Fantacalcio[BonusMalus],Fantacalcio[Squadra],$A6,Fantacalcio[Titolare],"NO",Fantacalcio[VotoUtile],"SI")) -> 2 | H6: =IF($A6="","",SUMIFS(Fantacalcio[BonusMalus],Fantacalcio[Squadra],$A6,Fantacalcio[Titolare],"NO",Fantacalcio[VotoUtile],"NO",Fantacalcio[Ruolo],"<>P")) -> 12
A7: I Bamboli | B7: =IF($A7="","",SUMIFS(Fantacalcio[BonusMalus],Fantacalcio[Squadra],$A7,Fantacalcio[VotoUtile],"SI",Fantacalcio[Ruolo],"P")) -> -11.5 | C7: =IF($A7="","",SUMIFS(Fantacalcio[BonusMalus],Fantacalcio[Squadra],$A7,Fantacalcio[VotoUtile],"SI",Fantacalcio[Ruolo],"D")) -> 4.5 | D7: =IF($A7="","",SUMIFS(Fantacalcio[BonusMalus],Fantacalcio[Squadra],$A7,Fantacalcio[VotoUtile],"SI",Fantacalcio[Ruolo],"C")) -> 23.5 | E7: =IF($A7="","",SUMIFS(Fantacalcio[BonusMalus],Fantacalcio[Squadra],$A7,Fantacalcio[VotoUtile],"SI",Fantacalcio[Ruolo],"A")) -> 13.5 | F7: =IF($A7="","",SUMIFS(Fantacalcio[BonusMalus],Fantacalcio[Squadra],$A7,Fantacalcio[VotoUtile],"SI")) -> 30 | G7: =IF($A7="","",SUMIFS(Fantacalcio[BonusMalus],Fantacalcio[Squadra],$A7,Fantacalcio[Titolare],"NO",Fantacalcio[VotoUtile],"SI")) -> -2 | H7: =IF($A7="","",SUMIFS(Fantacalcio[BonusMalus],Fantacalcio[Squadra],$A7,Fantacalcio[Titolare],"NO",Fantacalcio[VotoUtile],"NO",Fantacalcio[Ruolo],"<>P")) -> 20
A8: Incontro al capitano | B8: =IF($A8="","",SUMIFS(Fantacalcio[BonusMalus],Fantacalcio[Squadra],$A8,Fantacalcio[VotoUtile],"SI",Fantacalcio[Ruolo],"P")) -> -4 | C8: =IF($A8="","",SUMIFS(Fantacalcio[BonusMalus],Fantacalcio[Squadra],$A8,Fantacalcio[VotoUtile],"SI",Fantacalcio[Ruolo],"D")) -> 7 | D8: =IF($A8="","",SUMIFS(Fantacalcio[BonusMalus],Fantacalcio[Squadra],$A8,Fantacalcio[VotoUtile],"SI",Fantacalcio[Ruolo],"C")) -> 6 | E8: =IF($A8="","",SUMIFS(Fantacalcio[BonusMalus],Fantacalcio[Squadra],$A8,Fantacalcio[VotoUtile],"SI",Fantacalcio[Ruolo],"A")) -> 3 | F8: =IF($A8="","",SUMIFS(Fantacalcio[BonusMalus],Fantacalcio[Squadra],$A8,Fantacalcio[VotoUtile],"SI")) -> 12 | G8: =IF($A8="","",SUMIFS(Fantacalcio[BonusMalus],Fantacalcio[Squadra],$A8,Fantacalcio[Titolare],"NO",Fantacalcio[VotoUtile],"SI")) -> -2.5 | H8: =IF($A8="","",SUMIFS(Fantacalcio[BonusMalus],Fantacalcio[Squadra],$A8,Fantacalcio[Titolare],"NO",Fantacalcio[VotoUtile],"NO",Fantacalcio[Ruolo],"<>P")) -> 3
A9: Mancinix | B9: =IF($A9="","",SUMIFS(Fantacalcio[BonusMalus],Fantacalcio[Squadra],$A9,Fantacalcio[VotoUtile],"SI",Fantacalcio[Ruolo],"P")) -> -6.5 | C9: =IF($A9="","",SUMIFS(Fantacalcio[BonusMalus],Fantacalcio[Squadra],$A9,Fantacalcio[VotoUtile],"SI",Fantacalcio[Ruolo],"D")) -> -0.5 | D9: =IF($A9="","",SUMIFS(Fantacalcio[BonusMalus],Fantacalcio[Squadra],$A9,Fantacalcio[VotoUtile],"SI",Fantacalcio[Ruolo],"C")) -> 8.5 | E9: =IF($A9="","",SUMIFS(Fantacalcio[BonusMalus],Fantacalcio[Squadra],$A9,Fantacalcio[VotoUtile],"SI",Fantacalcio[Ruolo],"A")) -> 19.5 | F9: =IF($A9="","",SUMIFS(Fantacalcio[BonusMalus],Fantacalcio[Squadra],$A9,Fantacalcio[VotoUtile],"SI")) -> 21 | G9: =IF($A9="","",SUMIFS(Fantacalcio[BonusMalus],Fantacalcio[Squadra],$A9,Fantacalcio[Titolare],"NO",Fantacalcio[VotoUtile],"SI")) -> -0.5 | H9: =IF($A9="","",SUMIFS(Fantacalcio[BonusMalus],Fantacalcio[Squadra],$A9,Fantacalcio[Titolare],"NO",Fantacalcio[VotoUtile],"NO",Fantacalcio[Ruolo],"<>P")) -> 15
A10: Masterchef FC | B10: =IF($A10="","",SUMIFS(Fantacalcio[BonusMalus],Fantacalcio[Squadra],$A10,Fantacalcio[VotoUtile],"SI",Fantacalcio[Ruolo],"P")) -> -7 | C10: =IF($A10="","",SUMIFS(Fantacalcio[BonusMalus],Fantacalcio[Squadra],$A10,Fantacalcio[VotoUtile],"SI",Fantacalcio[Ruolo],"D")) -> 8 | D10: =IF($A10="","",SUMIFS(Fantacalcio[BonusMalus],Fantacalcio[Squadra],$A10,Fantacalcio[VotoUtile],"SI",Fantacalcio[Ruolo],"C")) -> 14.5 | E10: =IF($A10="","",SUMIFS(Fantacalcio[BonusMalus],Fantacalcio[Squadra],$A10,Fantacalcio[VotoUtile],"SI",Fantacalcio[Ruolo],"A")) -> 14 | F10: =IF($A10="","",SUMIFS(Fantacalcio[BonusMalus],Fantacalcio[Squadra],$A10,Fantacalcio[VotoUtile],"SI")) -> 29.5 | G10: =IF($A10="","",SUMIFS(Fantacalcio[BonusMalus],Fantacalcio[Squadra],$A10,Fantacalcio[Titolare],"NO",Fantacalcio[VotoUtile],"SI")) -> 6 | H10: =IF($A10="","",SUMIFS(Fantacalcio[BonusMalus],Fantacalcio[Squadra],$A10,Fantacalcio[Titolare],"NO",Fantacalcio[VotoUtile],"NO",Fantacalcio[Ruolo],"<>P")) -> 16
A11: Outletico Palermo | B11: =IF($A11="","",SUMIFS(Fantacalcio[BonusMalus],Fantacalcio[Squadra],$A11,Fantacalcio[VotoUtile],"SI",Fantacalcio[Ruolo],"P")) -> -1 | C11: =IF($A11="","",SUMIFS(Fantacalcio[BonusMalus],Fantacalcio[Squadra],$A11,Fantacalcio[VotoUtile],"SI",Fantacalcio[Ruolo],"D")) -> 1 | D11: =IF($A11="","",SUMIFS(Fantacalcio[BonusMalus],Fantacalcio[Squadra],$A11,Fantacalcio[VotoUtile],"SI",Fantacalcio[Ruolo],"C")) -> 16 | E11: =IF($A11="","",SUMIFS(Fantacalcio[BonusMalus],Fantacalcio[Squadra],$A11,Fantacalcio[VotoUtile],"SI",Fantacalcio[Ruolo],"A")) -> 16.5 | F11: =IF($A11="","",SUMIFS(Fantacalcio[BonusMalus],Fantacalcio[Squadra],$A11,Fantacalcio[VotoUtile],"SI")) -> 32.5 | G11: =IF($A11="","",SUMIFS(Fantacalcio[BonusMalus],Fantacalcio[Squadra],$A11,Fantacalcio[Titolare],"NO",Fantacalcio[VotoUtile],"SI")) -> -0.5 | H11: =IF($A11="","",SUMIFS(Fantacalcio[BonusMalus],Fantacalcio[Squadra],$A11,Fantacalcio[Titolare],"NO",Fantacalcio[VotoUtile],"NO",Fantacalcio[Ruolo],"<>P")) -> 4
A12: Paris Saint-Gervasoni | B12: =IF($A12="","",SUMIFS(Fantacalcio[BonusMalus],Fantacalcio[Squadra],$A12,Fantacalcio[VotoUtile],"SI",Fantacalcio[Ruolo],"P")) -> -4 | C12: =IF($A12="","",SUMIFS(Fantacalcio[BonusMalus],Fantacalcio[Squadra],$A12,Fantacalcio[VotoUtile],"SI",Fantacalcio[Ruolo],"D")) -> 10.5 | D12: =IF($A12="","",SUMIFS(Fantacalcio[BonusMalus],Fantacalcio[Squadra],$A12,Fantacalcio[VotoUtile],"SI",Fantacalcio[Ruolo],"C")) -> 16 | E12: =IF($A12="","",SUMIFS(Fantacalcio[BonusMalus],Fantacalcio[Squadra],$A12,Fantacalcio[VotoUtile],"SI",Fantacalcio[Ruolo],"A")) -> 17.5 | F12: =IF($A12="","",SUMIFS(Fantacalcio[BonusMalus],Fantacalcio[Squadra],$A12,Fantacalcio[VotoUtile],"SI")) -> 40 | G12: =IF($A12="","",SUMIFS(Fantacalcio[BonusMalus],Fantacalcio[Squadra],$A12,Fantacalcio[Titolare],"NO",Fantacalcio[VotoUtile],"SI")) -> 3 | H12: =IF($A12="","",SUMIFS(Fantacalcio[BonusMalus],Fantacalcio[Squadra],$A12,Fantacalcio[Titolare],"NO",Fantacalcio[VotoUtile],"NO",Fantacalcio[Ruolo],"<>P")) -> 18.5
A13: Schalke 104 | B13: =IF($A13="","",SUMIFS(Fantacalcio[BonusMalus],Fantacalcio[Squadra],$A13,Fantacalcio[VotoUtile],"SI",Fantacalcio[Ruolo],"P")) -> -4.5 | C13: =IF($A13="","",SUMIFS(Fantacalcio[BonusMalus],Fantacalcio[Squadra],$A13,Fantacalcio[VotoUtile],"SI",Fantacalcio[Ruolo],"D")) -> 0.5 | D13: =IF($A13="","",SUMIFS(Fantacalcio[BonusMalus],Fantacalcio[Squadra],$A13,Fantacalcio[VotoUtile],"SI",Fantacalcio[Ruolo],"C")) -> 11.5 | E13: =IF($A13="","",SUMIFS(Fantacalcio[BonusMalus],Fantacalcio[Squadra],$A13,Fantacalcio[VotoUtile],"SI",Fantacalcio[Ruolo],"A")) -> 15 | F13: =IF($A13="","",SUMIFS(Fantacalcio[BonusMalus],Fantacalcio[Squadra],$A13,Fantacalcio[VotoUtile],"SI")) -> 22.5 | G13: =IF($A13="","",SUMIFS(Fantacalcio[BonusMalus],Fantacalcio[Squadra],$A13,Fantacalcio[Titolare],"NO",Fantacalcio[VotoUtile],"SI")) -> 0 | H13: =IF($A13="","",SUMIFS(Fantacalcio[BonusMalus],Fantacalcio[Squadra],$A13,Fantacalcio[Titolare],"NO",Fantacalcio[VotoUtile],"NO",Fantacalcio[Ruolo],"<>P")) -> 26
A14: SuperGregariana | B14: =IF($A14="","",SUMIFS(Fantacalcio[BonusMalus],Fantacalcio[Squadra],$A14,Fantacalcio[VotoUtile],"SI",Fantacalcio[Ruolo],"P")) -> -8.5 | C14: =IF($A14="","",SUMIFS(Fantacalcio[BonusMalus],Fantacalcio[Squadra],$A14,Fantacalcio[VotoUtile],"SI",Fantacalcio[Ruolo],"D")) -> -1 | D14: =IF($A14="","",SUMIFS(Fantacalcio[BonusMalus],Fantacalcio[Squadra],$A14,Fantacalcio[VotoUtile],"SI",Fantacalcio[Ruolo],"C")) -> 8.5 | E14: =IF($A14="","",SUMIFS(Fantacalcio[BonusMalus],Fantacalcio[Squadra],$A14,Fantacalcio[VotoUtile],"SI",Fantacalcio[Ruolo],"A")) -> 18 | F14: =IF($A14="","",SUMIFS(Fantacalcio[BonusMalus],Fantacalcio[Squadra],$A14,Fantacalcio[VotoUtile],"SI")) -> 17 | G14: =IF($A14="","",SUMIFS(Fantacalcio[BonusMalus],Fantacalcio[Squadra],$A14,Fantacalcio[Titolare],"NO",Fantacalcio[VotoUtile],"SI")) -> -5 | H14: =IF($A14="","",SUMIFS(Fantacalcio[BonusMalus],Fantacalcio[Squadra],$A14,Fantacalcio[Titolare],"NO",Fantacalcio[VotoUtile],"NO",Fantacalcio[Ruolo],"<>P")) -> 8.5
B15: =IF($A15="","",SUMIFS(Fantacalcio[BonusMalus],Fantacalcio[Squadra],$A15,Fantacalcio[VotoUtile],"SI",Fantacalcio[Ruolo],"P")) | C15: =IF($A15="","",SUMIFS(Fantacalcio[BonusMalus],Fantacalcio[Squadra],$A15,Fantacalcio[VotoUtile],"SI",Fantacalcio[Ruolo],"D")) | D15: =IF($A15="","",SUMIFS(Fantacalcio[BonusMalus],Fantacalcio[Squadra],$A15,Fantacalcio[VotoUtile],"SI",Fantacalcio[Ruolo],"C")) | E15: =IF($A15="","",SUMIFS(Fantacalcio[BonusMalus],Fantacalcio[Squadra],$A15,Fantacalcio[VotoUtile],"SI",Fantacalcio[Ruolo],"A")) | F15: =IF($A15="","",SUMIFS(Fantacalcio[BonusMalus],Fantacalcio[Squadra],$A15,Fantacalcio[VotoUtile],"SI")) | G15: =IF($A15="","",SUMIFS(Fantacalcio[BonusMalus],Fantacalcio[Squadra],$A15,Fantacalcio[Titolare],"NO",Fantacalcio[VotoUtile],"SI")) | H15: =IF($A15="","",SUMIFS(Fantacalcio[BonusMalus],Fantacalcio[Squadra],$A15,Fantacalcio[Titolare],"NO",Fantacalcio[VotoUtile],"NO",Fantacalcio[Ruolo],"<>P"))
B16: =IF($A16="","",SUMIFS(Fantacalcio[BonusMalus],Fantacalcio[Squadra],$A16,Fantacalcio[VotoUtile],"SI",Fantacalcio[Ruolo],"P")) | C16: =IF($A16="","",SUMIFS(Fantacalcio[BonusMalus],Fantacalcio[Squadra],$A16,Fantacalcio[VotoUtile],"SI",Fantacalcio[Ruolo],"D")) | D16: =IF($A16="","",SUMIFS(Fantacalcio[BonusMalus],Fantacalcio[Squadra],$A16,Fantacalcio[VotoUtile],"SI",Fantacalcio[Ruolo],"C")) | E16: =IF($A16="","",SUMIFS(Fantacalcio[BonusMalus],Fantacalcio[Squadra],$A16,Fantacalcio[VotoUtile],"SI",Fantacalcio[Ruolo],"A")) | F16: =IF($A16="","",SUMIFS(Fantacalcio[BonusMalus],Fantacalcio[Squadra],$A16,Fantacalcio[VotoUtile],"SI")) | G16: =IF($A16="","",SUMIFS(Fantacalcio[BonusMalus],Fantacalcio[Squadra],$A16,Fantacalcio[Titolare],"NO",Fantacalcio[VotoUtile],"SI")) | H16: =IF($A16="","",SUMIFS(Fantacalcio[BonusMalus],Fantacalcio[Squadra],$A16,Fantacalcio[Titolare],"NO",Fantacalcio[VotoUtile],"NO",Fantacalcio[Ruolo],"<>P"))
B17: =IF($A17="","",SUMIFS(Fantacalcio[BonusMalus],Fantacalcio[Squadra],$A17,Fantacalcio[VotoUtile],"SI",Fantacalcio[Ruolo],"P")) | C17: =IF($A17="","",SUMIFS(Fantacalcio[BonusMalus],Fantacalcio[Squadra],$A17,Fantacalcio[VotoUtile],"SI",Fantacalcio[Ruolo],"D")) | D17: =IF($A17="","",SUMIFS(Fantacalcio[BonusMalus],Fantacalcio[Squadra],$A17,Fantacalcio[VotoUtile],"SI",Fantacalcio[Ruolo],"C")) | E17: =IF($A17="","",SUMIFS(Fantacalcio[BonusMalus],Fantacalcio[Squadra],$A17,Fantacalcio[VotoUtile],"SI",Fantacalcio[Ruolo],"A")) | F17: =IF($A17="","",SUMIFS(Fantacalcio[BonusMalus],Fantacalcio[Squadra],$A17,Fantacalcio[VotoUtile],"SI")) | G17: =IF($A17="","",SUMIFS(Fantacalcio[BonusMalus],Fantacalcio[Squadra],$A17,Fantacalcio[Titolare],"NO",Fantacalcio[VotoUtile],"SI")) | H17: =IF($A17="","",SUMIFS(Fantacalcio[BonusMalus],Fantacalcio[Squadra],$A17,Fantacalcio[Titolare],"NO",Fantacalcio[VotoUtile],"NO",Fantacalcio[Ruolo],"<>P"))
B18: =IF($A18="","",SUMIFS(Fantacalcio[BonusMalus],Fantacalcio[Squadra],$A18,Fantacalcio[VotoUtile],"SI",Fantacalcio[Ruolo],"P")) | C18: =IF($A18="","",SUMIFS(Fantacalcio[BonusMalus],Fantacalcio[Squadra],$A18,Fantacalcio[VotoUtile],"SI",Fantacalcio[Ruolo],"D")) | D18: =IF($A18="","",SUMIFS(Fantacalcio[BonusMalus],Fantacalcio[Squadra],$A18,Fantacalcio[VotoUtile],"SI",Fantacalcio[Ruolo],"C")) | E18: =IF($A18="","",SUMIFS(Fantacalcio[BonusMalus],Fantacalcio[Squadra],$A18,Fantacalcio[VotoUtile],"SI",Fantacalcio[Ruolo],"A")) | F18: =IF($A18="","",SUMIFS(Fantacalcio[BonusMalus],Fantacalcio[Squadra],$A18,Fantacalcio[VotoUtile],"SI")) | G18: =IF($A18="","",SUMIFS(Fantacalcio[BonusMalus],Fantacalcio[Squadra],$A18,Fantacalcio[Titolare],"NO",Fantacalcio[VotoUtile],"SI")) | H18: =IF($A18="","",SUMIFS(Fantacalcio[BonusMalus],Fantacalcio[Squadra],$A18,Fantacalcio[Titolare],"NO",Fantacalcio[VotoUtile],"NO",Fantacalcio[Ruolo],"<>P"))
B19: =IF($A19="","",SUMIFS(Fantacalcio[BonusMalus],Fantacalcio[Squadra],$A19,Fantacalcio[VotoUtile],"SI",Fantacalcio[Ruolo],"P")) | C19: =IF($A19="","",SUMIFS(Fantacalcio[BonusMalus],Fantacalcio[Squadra],$A19,Fantacalcio[VotoUtile],"SI",Fantacalcio[Ruolo],"D")) | D19: =IF($A19="","",SUMIFS(Fantacalcio[BonusMalus],Fantacalcio[Squadra],$A19,Fantacalcio[VotoUtile],"SI",Fantacalcio[Ruolo],"C")) | E19: =IF($A19="","",SUMIFS(Fantacalcio[BonusMalus],Fantacalcio[Squadra],$A19,Fantacalcio[VotoUtile],"SI",Fantacalcio[Ruolo],"A")) | F19: =IF($A19="","",SUMIFS(Fantacalcio[BonusMalus],Fantacalcio[Squadra],$A19,Fantacalcio[VotoUtile],"SI")) | G19: =IF($A19="","",SUMIFS(Fantacalcio[BonusMalus],Fantacalcio[Squadra],$A19,Fantacalcio[Titolare],"NO",Fantacalcio[VotoUtile],"SI")) | H19: =IF($A19="","",SUMIFS(Fantacalcio[BonusMalus],Fantacalcio[Squadra],$A19,Fantacalcio[Titolare],"NO",Fantacalcio[VotoUtile],"NO",Fantacalcio[Ruolo],"<>P"))
B20: =IF($A20="","",SUMIFS(Fantacalcio[BonusMalus],Fantacalcio[Squadra],$A20,Fantacalcio[VotoUtile],"SI",Fantacalcio[Ruolo],"P")) | C20: =IF($A20="","",SUMIFS(Fantacalcio[BonusMalus],Fantacalcio[Squadra],$A20,Fantacalcio[VotoUtile],"SI",Fantacalcio[Ruolo],"D")) | D20: =IF($A20="","",SUMIFS(Fantacalcio[BonusMalus],Fantacalcio[Squadra],$A20,Fantacalcio[VotoUtile],"SI",Fantacalcio[Ruolo],"C")) | E20: =IF($A20="","",SUMIFS(Fantacalcio[BonusMalus],Fantacalcio[Squadra],$A20,Fantacalcio[VotoUtile],"SI",Fantacalcio[Ruolo],"A")) | F20: =IF($A20="","",SUMIFS(Fantacalcio[BonusMalus],Fantacalcio[Squadra],$A20,Fantacalcio[VotoUtile],"SI")) | G20: =IF($A20="","",SUMIFS(Fantacalcio[BonusMalus],Fantacalcio[Squadra],$A20,Fantacalcio[Titolare],"NO",Fantacalcio[VotoUtile],"SI")) | H20: =IF($A20="","",SUMIFS(Fantacalcio[BonusMalus],Fantacalcio[Squadra],$A20,Fantacalcio[Titolare],"NO",Fantacalcio[VotoUtile],"NO",Fantacalcio[Ruolo],"<>P"))
B21: =IF($A21="","",SUMIFS(Fantacalcio[BonusMalus],Fantacalcio[Squadra],$A21,Fantacalcio[VotoUtile],"SI",Fantacalcio[Ruolo],"P")) | C21: =IF($A21="","",SUMIFS(Fantacalcio[BonusMalus],Fantacalcio[Squadra],$A21,Fantacalcio[VotoUtile],"SI",Fantacalcio[Ruolo],"D")) | D21: =IF($A21="","",SUMIFS(Fantacalcio[BonusMalus],Fantacalcio[Squadra],$A21,Fantacalcio[VotoUtile],"SI",Fantacalcio[Ruolo],"C")) | E21: =IF($A21="","",SUMIFS(Fantacalcio[BonusMalus],Fantacalcio[Squadra],$A21,Fantacalcio[VotoUtile],"SI",Fantacalcio[Ruolo],"A")) | F21: =IF($A21="","",SUMIFS(Fantacalcio[BonusMalus],Fantacalcio[Squadra],$A21,Fantacalcio[VotoUtile],"SI")) | G21: =IF($A21="","",SUMIFS(Fantacalcio[BonusMalus],Fantacalcio[Squadra],$A21,Fantacalcio[Titolare],"NO",Fantacalcio[VotoUtile],"SI")) | H21: =IF($A21="","",SUMIFS(Fantacalcio[BonusMalus],Fantacalcio[Squadra],$A21,Fantacalcio[Titolare],"NO",Fantacalcio[VotoUtile],"NO",Fantacalcio[Ruolo],"<>P"))
B22: =IF($A22="","",SUMIFS(Fantacalcio[BonusMalus],Fantacalcio[Squadra],$A22,Fantacalcio[VotoUtile],"SI",Fantacalcio[Ruolo],"P")) | C22: =IF($A22="","",SUMIFS(Fantacalcio[BonusMalus],Fantacalcio[Squadra],$A22,Fantacalcio[VotoUtile],"SI",Fantacalcio[Ruolo],"D")) | D22: =IF($A22="","",SUMIFS(Fantacalcio[BonusMalus],Fantacalcio[Squadra],$A22,Fantacalcio[VotoUtile],"SI",Fantacalcio[Ruolo],"C")) | E22: =IF($A22="","",SUMIFS(Fantacalcio[BonusMalus],Fantacalcio[Squadra],$A22,Fantacalcio[VotoUtile],"SI",Fantacalcio[Ruolo],"A")) | F22: =IF($A22="","",SUMIFS(Fantacalcio[BonusMalus],Fantacalcio[Squadra],$A22,Fantacalcio[VotoUtile],"SI")) | G22: =IF($A22="","",SUMIFS(Fantacalcio[BonusMalus],Fantacalcio[Squadra],$A22,Fantacalcio[Titolare],"NO",Fantacalcio[VotoUtile],"SI")) | H22: =IF($A22="","",SUMIFS(Fantacalcio[BonusMalus],Fantacalcio[Squadra],$A22,Fantacalcio[Titolare],"NO",Fantacalcio[VotoUtile],"NO",Fantacalcio[Ruolo],"<>P"))
B23: =IF($A23="","",SUMIFS(Fantacalcio[BonusMalus],Fantacalcio[Squadra],$A23,Fantacalcio[VotoUtile],"SI",Fantacalcio[Ruolo],"P")) | C23: =IF($A23="","",SUMIFS(Fantacalcio[BonusMalus],Fantacalcio[Squadra],$A23,Fantacalcio[VotoUtile],"SI",Fantacalcio[Ruolo],"D")) | D23: =IF($A23="","",SUMIFS(Fantacalcio[BonusMalus],Fantacalcio[Squadra],$A23,Fantacalcio[VotoUtile],"SI",Fantacalcio[Ruolo],"C")) | E23: =IF($A23="","",SUMIFS(Fantacalcio[BonusMalus],Fantacalcio[Squadra],$A23,Fantacalcio[VotoUtile],"SI",Fantacalcio[Ruolo],"A")) | F23: =IF($A23="","",SUMIFS(Fantacalcio[BonusMalus],Fantacalcio[Squadra],$A23,Fantacalcio[VotoUtile],"SI")) | G23: =IF($A23="","",SUMIFS(Fantacalcio[BonusMalus],Fantacalcio[Squadra],$A23,Fantacalcio[Titolare],"NO",Fantacalcio[VotoUtile],"SI")) | H23: =IF($A23="","",SUMIFS(Fantacalcio[BonusMalus],Fantacalcio[Squadra],$A23,Fantacalcio[Titolare],"NO",Fantacalcio[VotoUtile],"NO",Fantacalcio[Ruolo],"<>P"))
B24: =IF($A24="","",SUMIFS(Fantacalcio[BonusMalus],Fantacalcio[Squadra],$A24,Fantacalcio[VotoUtile],"SI",Fantacalcio[Ruolo],"P")) | C24: =IF($A24="","",SUMIFS(Fantacalcio[BonusMalus],Fantacalcio[Squadra],$A24,Fantacalcio[VotoUtile],"SI",Fantacalcio[Ruolo],"D")) | D24: =IF($A24="","",SUMIFS(Fantacalcio[BonusMalus],Fantacalcio[Squadra],$A24,Fantacalcio[VotoUtile],"SI",Fantacalcio[Ruolo],"C")) | E24: =IF($A24="","",SUMIFS(Fantacalcio[BonusMalus],Fantacalcio[Squadra],$A24,Fantacalcio[VotoUtile],"SI",Fantacalcio[Ruolo],"A")) | F24: =IF($A24="","",SUMIFS(Fantacalcio[BonusMalus],Fantacalcio[Squadra],$A24,Fantacalcio[VotoUtile],"SI")) | G24: =IF($A24="","",SUMIFS(Fantacalcio[BonusMalus],Fantacalcio[Squadra],$A24,Fantacalcio[Titolare],"NO",Fantacalcio[VotoUtile],"SI")) | H24: =IF($A24="","",SUMIFS(Fantacalcio[BonusMalus],Fantacalcio[Squadra],$A24,Fantacalcio[Titolare],"NO",Fantacalcio[VotoUtile],"NO",Fantacalcio[Ruolo],"<>P"))
A26: Legenda
A27: VU = Voto Utile (colonna VotoUtile = SI)
A28: Portieri/Difensori/Centrocampisti/Attaccanti: BonusMalus dei soli giocatori con Voto Utile, divisi per ruolo
A29: Totale Voti Utili: BonusMalus di tutti i giocatori con Voto Utile (somma delle 4 colonne per ruolo)
A30: Subentrati: Titolare = NO e Voto Utile = SI
A31: Panchinari (no P): Titolare = NO e Voto Utile = NO, portieri esclusi

Sheet Analisi Voto
A1: Analisi Media Voto per Squadra
A2: Dati cumulati su tutte le giornate presenti nel foglio Database
A4: Squadra | B4: Portieri (VU) | C4: Difensori (VU) | D4: Centrocampisti (VU) | E4: Attaccanti (VU) | F4: Media Voti Utili | G4: Subentrati | H4: Panchinari (no P)
A5: {=_xlfn._xlws.SORT(_xlfn.UNIQUE(Fantacalcio[Squadra]))} -> Evacuo Kaka Toni | B5: =IF($A5="","",IFERROR(AVERAGEIFS(Fantacalcio[Voto],Fantacalcio[Squadra],$A5,Fantacalcio[VotoUtile],"SI",Fantacalcio[Ruolo],"P"),"")) -> 6 | C5: =IF($A5="","",IFERROR(AVERAGEIFS(Fantacalcio[Voto],Fantacalcio[Squadra],$A5,Fantacalcio[VotoUtile],"SI",Fantacalcio[Ruolo],"D"),"")) -> 6.0833333 | D5: =IF($A5="","",IFERROR(AVERAGEIFS(Fantacalcio[Voto],Fantacalcio[Squadra],$A5,Fantacalcio[VotoUtile],"SI",Fantacalcio[Ruolo],"C"),"")) -> 6.2 | E5: =IF($A5="","",IFERROR(AVERAGEIFS(Fantacalcio[Voto],Fantacalcio[Squadra],$A5,Fantacalcio[VotoUtile],"SI",Fantacalcio[Ruolo],"A"),"")) -> 5.8888889 | F5: =IF($A5="","",IFERROR(AVERAGEIFS(Fantacalcio[Voto],Fantacalcio[Squadra],$A5,Fantacalcio[VotoUtile],"SI"),"")) -> 6.047619 | G5: =IF($A5="","",IFERROR(AVERAGEIFS(Fantacalcio[Voto],Fantacalcio[Squadra],$A5,Fantacalcio[Titolare],"NO",Fantacalcio[VotoUtile],"SI"),"")) -> 5.9166667 | H5: =IF($A5="","",IFERROR(AVERAGEIFS(Fantacalcio[Voto],Fantacalcio[Squadra],$A5,Fantacalcio[Titolare],"NO",Fantacalcio[VotoUtile],"NO",Fantacalcio[Ruolo],"<>P"),"")) -> 5.8913043
A6: GC21 | B6: =IF($A6="","",IFERROR(AVERAGEIFS(Fantacalcio[Voto],Fantacalcio[Squadra],$A6,Fantacalcio[VotoUtile],"SI",Fantacalcio[Ruolo],"P"),"")) -> 5.8333333 | C6: =IF($A6="","",IFERROR(AVERAGEIFS(Fantacalcio[Voto],Fantacalcio[Squadra],$A6,Fantacalcio[VotoUtile],"SI",Fantacalcio[Ruolo],"D"),"")) -> 6.2142857 | D6: =IF($A6="","",IFERROR(AVERAGEIFS(Fantacalcio[Voto],Fantacalcio[Squadra],$A6,Fantacalcio[VotoUtile],"SI",Fantacalcio[Ruolo],"C"),"")) -> 6.0217391 | E6: =IF($A6="","",IFERROR(AVERAGEIFS(Fantacalcio[Voto],Fantacalcio[Squadra],$A6,Fantacalcio[VotoUtile],"SI",Fantacalcio[Ruolo],"A"),"")) -> 6.09375 | F6: =IF($A6="","",IFERROR(AVERAGEIFS(Fantacalcio[Voto],Fantacalcio[Squadra],$A6,Fantacalcio[VotoUtile],"SI"),"")) -> 6.0833333 | G6: =IF($A6="","",IFERROR(AVERAGEIFS(Fantacalcio[Voto],Fantacalcio[Squadra],$A6,Fantacalcio[Titolare],"NO",Fantacalcio[VotoUtile],"SI"),"")) -> 6 | H6: =IF($A6="","",IFERROR(AVERAGEIFS(Fantacalcio[Voto],Fantacalcio[Squadra],$A6,Fantacalcio[Titolare],"NO",Fantacalcio[VotoUtile],"NO",Fantacalcio[Ruolo],"<>P"),"")) -> 6.0729167
A7: I Bamboli | B7: =IF($A7="","",IFERROR(AVERAGEIFS(Fantacalcio[Voto],Fantacalcio[Squadra],$A7,Fantacalcio[VotoUtile],"SI",Fantacalcio[Ruolo],"P"),"")) -> 5.75 | C7: =IF($A7="","",IFERROR(AVERAGEIFS(Fantacalcio[Voto],Fantacalcio[Squadra],$A7,Fantacalcio[VotoUtile],"SI",Fantacalcio[Ruolo],"D"),"")) -> 6.2222222 | D7: =IF($A7="","",IFERROR(AVERAGEIFS(Fantacalcio[Voto],Fantacalcio[Squadra],$A7,Fantacalcio[VotoUtile],"SI",Fantacalcio[Ruolo],"C"),"")) -> 6.28 | E7: =IF($A7="","",IFERROR(AVERAGEIFS(Fantacalcio[Voto],Fantacalcio[Squadra],$A7,Fantacalcio[VotoUtile],"SI",Fantacalcio[Ruolo],"A"),"")) -> 6.2647059 | F7: =IF($A7="","",IFERROR(AVERAGEIFS(Fantacalcio[Voto],Fantacalcio[Squadra],$A7,Fantacalcio[VotoUtile],"SI"),"")) -> 6.2121212 | G7: =IF($A7="","",IFERROR(AVERAGEIFS(Fantacalcio[Voto],Fantacalcio[Squadra],$A7,Fantacalcio[Titolare],"NO",Fantacalcio[VotoUtile],"SI"),"")) -> 5.5 | H7: =IF($A7="","",IFERROR(AVERAGEIFS(Fantacalcio[Voto],Fantacalcio[Squadra],$A7,Fantacalcio[Titolare],"NO",Fantacalcio[VotoUtile],"NO",Fantacalcio[Ruolo],"<>P"),"")) -> 6.076087
A8: Incontro al capitano | B8: =IF($A8="","",IFERROR(AVERAGEIFS(Fantacalcio[Voto],Fantacalcio[Squadra],$A8,Fantacalcio[VotoUtile],"SI",Fantacalcio[Ruolo],"P"),"")) -> 6.1666667 | C8: =IF($A8="","",IFERROR(AVERAGEIFS(Fantacalcio[Voto],Fantacalcio[Squadra],$A8,Fantacalcio[VotoUtile],"SI",Fantacalcio[Ruolo],"D"),"")) -> 6 | D8: =IF($A8="","",IFERROR(AVERAGEIFS(Fantacalcio[Voto],Fantacalcio[Squadra],$A8,Fantacalcio[VotoUtile],"SI",Fantacalcio[Ruolo],"C"),"")) -> 6.0769231 | E8: =IF($A8="","",IFERROR(AVERAGEIFS(Fantacalcio[Voto],Fantacalcio[Squadra],$A8,Fantacalcio[VotoUtile],"SI",Fantacalcio[Ruolo],"A"),"")) -> 6.2 | F8: =IF($A8="","",IFERROR(AVERAGEIFS(Fantacalcio[Voto],Fantacalcio[Squadra],$A8,Fantacalcio[VotoUtile],"SI"),"")) -> 6.0909091 | G8: =IF($A8="","",IFERROR(AVERAGEIFS(Fantacalcio[Voto],Fantacalcio[Squadra],$A8,Fantacalcio[Titolare],"NO",Fantacalcio[VotoUtile],"SI"),"")) -> 6 | H8: =IF($A8="","",IFERROR(AVERAGEIFS(Fantacalcio[Voto],Fantacalcio[Squadra],$A8,Fantacalcio[Titolare],"NO",Fantacalcio[VotoUtile],"NO",Fantacalcio[Ruolo],"<>P"),"")) -> 5.8636364
A9: Mancinix | B9: =IF($A9="","",IFERROR(AVERAGEIFS(Fantacalcio[Voto],Fantacalcio[Squadra],$A9,Fantacalcio[VotoUtile],"SI",Fantacalcio[Ruolo],"P"),"")) -> 6.5 | C9: =IF($A9="","",IFERROR(AVERAGEIFS(Fantacalcio[Voto],Fantacalcio[Squadra],$A9,Fantacalcio[VotoUtile],"SI",Fantacalcio[Ruolo],"D"),"")) -> 6.0277778 | D9: =IF($A9="","",IFERROR(AVERAGEIFS(Fantacalcio[Voto],Fantacalcio[Squadra],$A9,Fantacalcio[VotoUtile],"SI",Fantacalcio[Ruolo],"C"),"")) -> 6.1153846 | E9: =IF($A9="","",IFERROR(AVERAGEIFS(Fantacalcio[Voto],Fantacalcio[Squadra],$A9,Fantacalcio[VotoUtile],"SI",Fantacalcio[Ruolo],"A"),"")) -> 6.25 | F9: =IF($A9="","",IFERROR(AVERAGEIFS(Fantacalcio[Voto],Fantacalcio[Squadra],$A9,Fantacalcio[VotoUtile],"SI"),"")) -> 6.1590909 | G9: =IF($A9="","",IFERROR(AVERAGEIFS(Fantacalcio[Voto],Fantacalcio[Squadra],$A9,Fantacalcio[Titolare],"NO",Fantacalcio[VotoUtile],"SI"),"")) -> 6.1 | H9: =IF($A9="","",IFERROR(AVERAGEIFS(Fantacalcio[Voto],Fantacalcio[Squadra],$A9,Fantacalcio[Titolare],"NO",Fantacalcio[VotoUtile],"NO",Fantacalcio[Ruolo],"<>P"),"")) -> 6.025
A10: Masterchef FC | B10: =IF($A10="","",IFERROR(AVERAGEIFS(Fantacalcio[Voto],Fantacalcio[Squadra],$A10,Fantacalcio[VotoUtile],"SI",Fantacalcio[Ruolo],"P"),"")) -> 5.5 | C10: =IF($A10="","",IFERROR(AVERAGEIFS(Fantacalcio[Voto],Fantacalcio[Squadra],$A10,Fantacalcio[VotoUtile],"SI",Fantacalcio[Ruolo],"D"),"")) -> 6 | D10: =IF($A10="","",IFERROR(AVERAGEIFS(Fantacalcio[Voto],Fantacalcio[Squadra],$A10,Fantacalcio[VotoUtile],"SI",Fantacalcio[Ruolo],"C"),"")) -> 6 | E10: =IF($A10="","",IFERROR(AVERAGEIFS(Fantacalcio[Voto],Fantacalcio[Squadra],$A10,Fantacalcio[VotoUtile],"SI",Fantacalcio[Ruolo],"A"),"")) -> 5.8611111 | F10: =IF($A10="","",IFERROR(AVERAGEIFS(Fantacalcio[Voto],Fantacalcio[Squadra],$A10,Fantacalcio[VotoUtile],"SI"),"")) -> 5.9166667 | G10: =IF($A10="","",IFERROR(AVERAGEIFS(Fantacalcio[Voto],Fantacalcio[Squadra],$A10,Fantacalcio[Titolare],"NO",Fantacalcio[VotoUtile],"SI"),"")) -> 6.0833333 | H10: =IF($A10="","",IFERROR(AVERAGEIFS(Fantacalcio[Voto],Fantacalcio[Squadra],$A10,Fantacalcio[Titolare],"NO",Fantacalcio[VotoUtile],"NO",Fantacalcio[Ruolo],"<>P"),"")) -> 5.8863636
A11: Outletico Palermo | B11: =IF($A11="","",IFERROR(AVERAGEIFS(Fantacalcio[Voto],Fantacalcio[Squadra],$A11,Fantacalcio[VotoUtile],"SI",Fantacalcio[Ruolo],"P"),"")) -> 6.4166667 | C11: =IF($A11="","",IFERROR(AVERAGEIFS(Fantacalcio[Voto],Fantacalcio[Squadra],$A11,Fantacalcio[VotoUtile],"SI",Fantacalcio[Ruolo],"D"),"")) -> 6.1111111 | D11: =IF($A11="","",IFERROR(AVERAGEIFS(Fantacalcio[Voto],Fantacalcio[Squadra],$A11,Fantacalcio[VotoUtile],"SI",Fantacalcio[Ruolo],"C"),"")) -> 6.0625 | E11: =IF($A11="","",IFERROR(AVERAGEIFS(Fantacalcio[Voto],Fantacalcio[Squadra],$A11,Fantacalcio[VotoUtile],"SI",Fantacalcio[Ruolo],"A"),"")) -> 6.3055556 | F11: =IF($A11="","",IFERROR(AVERAGEIFS(Fantacalcio[Voto],Fantacalcio[Squadra],$A11,Fantacalcio[VotoUtile],"SI"),"")) -> 6.1742424 | G11: =IF($A11="","",IFERROR(AVERAGEIFS(Fantacalcio[Voto],Fantacalcio[Squadra],$A11,Fantacalcio[Titolare],"NO",Fantacalcio[VotoUtile],"SI"),"")) -> 5.7 | H11: =IF($A11="","",IFERROR(AVERAGEIFS(Fantacalcio[Voto],Fantacalcio[Squadra],$A11,Fantacalcio[Titolare],"NO",Fantacalcio[VotoUtile],"NO",Fantacalcio[Ruolo],"<>P"),"")) -> 5.893617
A12: Paris Saint-Gervasoni | B12: =IF($A12="","",IFERROR(AVERAGEIFS(Fantacalcio[Voto],Fantacalcio[Squadra],$A12,Fantacalcio[VotoUtile],"SI",Fantacalcio[Ruolo],"P"),"")) -> 6.4166667 | C12: =IF($A12="","",IFERROR(AVERAGEIFS(Fantacalcio[Voto],Fantacalcio[Squadra],$A12,Fantacalcio[VotoUtile],"SI",Fantacalcio[Ruolo],"D"),"")) -> 6.1111111 | D12: =IF($A12="","",IFERROR(AVERAGEIFS(Fantacalcio[Voto],Fantacalcio[Squadra],$A12,Fantacalcio[VotoUtile],"SI",Fantacalcio[Ruolo],"C"),"")) -> 6.3076923 | E12: =IF($A12="","",IFERROR(AVERAGEIFS(Fantacalcio[Voto],Fantacalcio[Squadra],$A12,Fantacalcio[VotoUtile],"SI",Fantacalcio[Ruolo],"A"),"")) -> 6.09375 | F12: =IF($A12="","",IFERROR(AVERAGEIFS(Fantacalcio[Voto],Fantacalcio[Squadra],$A12,Fantacalcio[VotoUtile],"SI"),"")) -> 6.2121212 | G12: =IF($A12="","",IFERROR(AVERAGEIFS(Fantacalcio[Voto],Fantacalcio[Squadra],$A12,Fantacalcio[Titolare],"NO",Fantacalcio[VotoUtile],"SI"),"")) -> 6.1875 | H12: =IF($A12="","",IFERROR(AVERAGEIFS(Fantacalcio[Voto],Fantacalcio[Squadra],$A12,Fantacalcio[Titolare],"NO",Fantacalcio[VotoUtile],"NO",Fantacalcio[Ruolo],"<>P"),"")) -> 6.0675676
A13: Schalke 104 | B13: =IF($A13="","",IFERROR(AVERAGEIFS(Fantacalcio[Voto],Fantacalcio[Squadra],$A13,Fantacalcio[VotoUtile],"SI",Fantacalcio[Ruolo],"P"),"")) -> 6.1666667 | C13: =IF($A13="","",IFERROR(AVERAGEIFS(Fantacalcio[Voto],Fantacalcio[Squadra],$A13,Fantacalcio[VotoUtile],"SI",Fantacalcio[Ruolo],"D"),"")) -> 6.1388889 | D13: =IF($A13="","",IFERROR(AVERAGEIFS(Fantacalcio[Voto],Fantacalcio[Squadra],$A13,Fantacalcio[VotoUtile],"SI",Fantacalcio[Ruolo],"C"),"")) -> 6.0416667 | E13: =IF($A13="","",IFERROR(AVERAGEIFS(Fantacalcio[Voto],Fantacalcio[Squadra],$A13,Fantacalcio[VotoUtile],"SI",Fantacalcio[Ruolo],"A"),"")) -> 5.9722222 | F13: =IF($A13="","",IFERROR(AVERAGEIFS(Fantacalcio[Voto],Fantacalcio[Squadra],$A13,Fantacalcio[VotoUtile],"SI"),"")) -> 6.0606061 | G13: =IF($A13="","",IFERROR(AVERAGEIFS(Fantacalcio[Voto],Fantacalcio[Squadra],$A13,Fantacalcio[Titolare],"NO",Fantacalcio[VotoUtile],"SI"),"")) -> 6 | H13: =IF($A13="","",IFERROR(AVERAGEIFS(Fantacalcio[Voto],Fantacalcio[Squadra],$A13,Fantacalcio[Titolare],"NO",Fantacalcio[VotoUtile],"NO",Fantacalcio[Ruolo],"<>P"),"")) -> 5.9673913
A14: SuperGregariana | B14: =IF($A14="","",IFERROR(AVERAGEIFS(Fantacalcio[Voto],Fantacalcio[Squadra],$A14,Fantacalcio[VotoUtile],"SI",Fantacalcio[Ruolo],"P"),"")) -> 6.0833333 | C14: =IF($A14="","",IFERROR(AVERAGEIFS(Fantacalcio[Voto],Fantacalcio[Squadra],$A14,Fantacalcio[VotoUtile],"SI",Fantacalcio[Ruolo],"D"),"")) -> 5.8333333 | D14: =IF($A14="","",IFERROR(AVERAGEIFS(Fantacalcio[Voto],Fantacalcio[Squadra],$A14,Fantacalcio[VotoUtile],"SI",Fantacalcio[Ruolo],"C"),"")) -> 5.9791667 | E14: =IF($A14="","",IFERROR(AVERAGEIFS(Fantacalcio[Voto],Fantacalcio[Squadra],$A14,Fantacalcio[VotoUtile],"SI",Fantacalcio[Ruolo],"A"),"")) -> 6.0833333 | F14: =IF($A14="","",IFERROR(AVERAGEIFS(Fantacalcio[Voto],Fantacalcio[Squadra],$A14,Fantacalcio[VotoUtile],"SI"),"")) -> 5.9772727 | G14: =IF($A14="","",IFERROR(AVERAGEIFS(Fantacalcio[Voto],Fantacalcio[Squadra],$A14,Fantacalcio[Titolare],"NO",Fantacalcio[VotoUtile],"SI"),"")) -> 5.7142857 | H14: =IF($A14="","",IFERROR(AVERAGEIFS(Fantacalcio[Voto],Fantacalcio[Squadra],$A14,Fantacalcio[Titolare],"NO",Fantacalcio[VotoUtile],"NO",Fantacalcio[Ruolo],"<>P"),"")) -> 5.872093
A26: Legenda
A27: VU = Voto Utile (colonna VotoUtile = SI)
A28: Portieri/Difensori/Centrocampisti/Attaccanti: media del Voto (non Fantavoto) dei soli giocatori con Voto Utile, divisi per ruolo
A29: Media Voti Utili: media del Voto di tutti i giocatori con Voto Utile
A30: Subentrati: media del Voto dei giocatori con Titolare = NO e Voto Utile = SI
A31: Panchinari (no P): media del Voto dei giocatori con Titolare = NO e Voto Utile = NO, portieri esclusi
A32: I giocatori senza voto (s.v. / non scesi in campo) sono esclusi dalle medie. Cella vuota = nessun giocatore nella categoria.

Sheet Analisi VdM
A1: Analisi Valore di Mercato per Squadra e Giornata
A2: Somma dei VdM (mln €) dei giocatori con Voto Utile = SI. Le giornate senza dati restano vuote ed escluse dalla media.
A4: Squadra | B4: Media | C4: {=_xlfn.SEQUENCE(1,38)} -> 1 | D4: 2 | E4: 3 | F4: 4 | G4: 5 | H4: 6 | I4: 7 | J4: 8 | K4: 9 | L4: 10 | M4: 11 | N4: 12 | O4: 13 | P4: 14 | Q4: 15 | R4: 16 | S4: 17 | T4: 18 | U4: 19 | V4: 20 | W4: 21 | X4: 22 | Y4: 23 | Z4: 24 | AA4: 25 | AB4: 26 | AC4: 27 | AD4: 28 | AE4: 29 | AF4: 30 | AG4: 31 | AH4: 32 | AI4: 33 | AJ4: 34 | AK4: 35 | AL4: 36 | AM4: 37 | AN4: 38
A5: {=_xlfn._xlws.SORT(_xlfn.UNIQUE(_xlfn._xlws.FILTER(Fantacalcio[Squadra],Fantacalcio[Squadra]<>"")))} -> Evacuo Kaka Toni | B5: =IF($A5="","",IF(COUNT(C5:AN5)=0,"",AVERAGE(C5:AN5))) -> 157.83333 | C5: =IF($A5="","",IF(COUNTIFS(Fantacalcio[Giornata],C$4,Fantacalcio[Squadra],$A5)=0,"",SUMIFS(Fantacalcio[VdM (mln €)],Fantacalcio[Giornata],C$4,Fantacalcio[Squadra],$A5,Fantacalcio[VotoUtile],"SI"))) -> 152 | D5: =IF($A5="","",IF(COUNTIFS(Fantacalcio[Giornata],D$4,Fantacalcio[Squadra],$A5)=0,"",SUMIFS(Fantacalcio[VdM (mln €)],Fantacalcio[Giornata],D$4,Fantacalcio[Squadra],$A5,Fantacalcio[VotoUtile],"SI"))) -> 121.4 | E5: =IF($A5="","",IF(COUNTIFS(Fantacalcio[Giornata],E$4,Fantacalcio[Squadra],$A5)=0,"",SUMIFS(Fantacalcio[VdM (mln €)],Fantacalcio[Giornata],E$4,Fantacalcio[Squadra],$A5,Fantacalcio[VotoUtile],"SI"))) -> 128.9 | F5: =IF($A5="","",IF(COUNTIFS(Fantacalcio[Giornata],F$4,Fantacalcio[Squadra],$A5)=0,"",SUMIFS(Fantacalcio[VdM (mln €)],Fantacalcio[Giornata],F$4,Fantacalcio[Squadra],$A5,Fantacalcio[VotoUtile],"SI"))) -> 177.9 | G5: =IF($A5="","",IF(COUNTIFS(Fantacalcio[Giornata],G$4,Fantacalcio[Squadra],$A5)=0,"",SUMIFS(Fantacalcio[VdM (mln €)],Fantacalcio[Giornata],G$4,Fantacalcio[Squadra],$A5,Fantacalcio[VotoUtile],"SI"))) -> 192.9 | H5: =IF($A5="","",IF(COUNTIFS(Fantacalcio[Giornata],H$4,Fantacalcio[Squadra],$A5)=0,"",SUMIFS(Fantacalcio[VdM (mln €)],Fantacalcio[Giornata],H$4,Fantacalcio[Squadra],$A5,Fantacalcio[VotoUtile],"SI"))) -> 173.9 | I5: =IF($A5="","",IF(COUNTIFS(Fantacalcio[Giornata],I$4,Fantacalcio[Squadra],$A5)=0,"",SUMIFS(Fantacalcio[VdM (mln €)],Fantacalcio[Giornata],I$4,Fantacalcio[Squadra],$A5,Fantacalcio[VotoUtile],"SI"))) | J5: =IF($A5="","",IF(COUNTIFS(Fantacalcio[Giornata],J$4,Fantacalcio[Squadra],$A5)=0,"",SUMIFS(Fantacalcio[VdM (mln €)],Fantacalcio[Giornata],J$4,Fantacalcio[Squadra],$A5,Fantacalcio[VotoUtile],"SI"))) | ... AN5: =IF($A5="","",IF(COUNTIFS(Fantacalcio[Giornata],AN$4,Fantacalcio[Squadra],$A5)=0,"",SUMIFS(Fantacalcio[VdM (mln €)],Fantacalcio[Giornata],AN$4,Fantacalcio[Squadra],$A5,Fantacalcio[VotoUtile],"SI")))
A6: GC21 | B6: =IF($A6="","",IF(COUNT(C6:AN6)=0,"",AVERAGE(C6:AN6))) -> 300.83333 | C6: =IF($A6="","",IF(COUNTIFS(Fantacalcio[Giornata],C$4,Fantacalcio[Squadra],$A6)=0,"",SUMIFS(Fantacalcio[VdM (mln €)],Fantacalcio[Giornata],C$4,Fantacalcio[Squadra],$A6,Fantacalcio[VotoUtile],"SI"))) -> 383 | D6: =IF($A6="","",IF(COUNTIFS(Fantacalcio[Giornata],D$4,Fantacalcio[Squadra],$A6)=0,"",SUMIFS(Fantacalcio[VdM (mln €)],Fantacalcio[Giornata],D$4,Fantacalcio[Squadra],$A6,Fantacalcio[VotoUtile],"SI"))) -> 306 | E6: =IF($A6="","",IF(COUNTIFS(Fantacalcio[Giornata],E$4,Fantacalcio[Squadra],$A6)=0,"",SUMIFS(Fantacalcio[VdM (mln €)],Fantacalcio[Giornata],E$4,Fantacalcio[Squadra],$A6,Fantacalcio[VotoUtile],"SI"))) -> 255 | F6: =IF($A6="","",IF(COUNTIFS(Fantacalcio[Giornata],F$4,Fantacalcio[Squadra],$A6)=0,"",SUMIFS(Fantacalcio[VdM (mln €)],Fantacalcio[Giornata],F$4,Fantacalcio[Squadra],$A6,Fantacalcio[VotoUtile],"SI"))) -> 262 | G6: =IF($A6="","",IF(COUNTIFS(Fantacalcio[Giornata],G$4,Fantacalcio[Squadra],$A6)=0,"",SUMIFS(Fantacalcio[VdM (mln €)],Fantacalcio[Giornata],G$4,Fantacalcio[Squadra],$A6,Fantacalcio[VotoUtile],"SI"))) -> 276.5 | H6: =IF($A6="","",IF(COUNTIFS(Fantacalcio[Giornata],H$4,Fantacalcio[Squadra],$A6)=0,"",SUMIFS(Fantacalcio[VdM (mln €)],Fantacalcio[Giornata],H$4,Fantacalcio[Squadra],$A6,Fantacalcio[VotoUtile],"SI"))) -> 322.5 | I6: =IF($A6="","",IF(COUNTIFS(Fantacalcio[Giornata],I$4,Fantacalcio[Squadra],$A6)=0,"",SUMIFS(Fantacalcio[VdM (mln €)],Fantacalcio[Giornata],I$4,Fantacalcio[Squadra],$A6,Fantacalcio[VotoUtile],"SI"))) | J6: =IF($A6="","",IF(COUNTIFS(Fantacalcio[Giornata],J$4,Fantacalcio[Squadra],$A6)=0,"",SUMIFS(Fantacalcio[VdM (mln €)],Fantacalcio[Giornata],J$4,Fantacalcio[Squadra],$A6,Fantacalcio[VotoUtile],"SI"))) | ... AN6: =IF($A6="","",IF(COUNTIFS(Fantacalcio[Giornata],AN$4,Fantacalcio[Squadra],$A6)=0,"",SUMIFS(Fantacalcio[VdM (mln €)],Fantacalcio[Giornata],AN$4,Fantacalcio[Squadra],$A6,Fantacalcio[VotoUtile],"SI")))
A7: I Bamboli | B7: =IF($A7="","",IF(COUNT(C7:AN7)=0,"",AVERAGE(C7:AN7))) -> 174.75 | C7: =IF($A7="","",IF(COUNTIFS(Fantacalcio[Giornata],C$4,Fantacalcio[Squadra],$A7)=0,"",SUMIFS(Fantacalcio[VdM (mln €)],Fantacalcio[Giornata],C$4,Fantacalcio[Squadra],$A7,Fantacalcio[VotoUtile],"SI"))) -> 165 | D7: =IF($A7="","",IF(COUNTIFS(Fantacalcio[Giornata],D$4,Fantacalcio[Squadra],$A7)=0,"",SUMIFS(Fantacalcio[VdM (mln €)],Fantacalcio[Giornata],D$4,Fantacalcio[Squadra],$A7,Fantacalcio[VotoUtile],"SI"))) -> 166 | E7: =IF($A7="","",IF(COUNTIFS(Fantacalcio[Giornata],E$4,Fantacalcio[Squadra],$A7)=0,"",SUMIFS(Fantacalcio[VdM (mln €)],Fantacalcio[Giornata],E$4,Fantacalcio[Squadra],$A7,Fantacalcio[VotoUtile],"SI"))) -> 157.5 | F7: =IF($A7="","",IF(COUNTIFS(Fantacalcio[Giornata],F$4,Fantacalcio[Squadra],$A7)=0,"",SUMIFS(Fantacalcio[VdM (mln €)],Fantacalcio[Giornata],F$4,Fantacalcio[Squadra],$A7,Fantacalcio[VotoUtile],"SI"))) -> 197.5 | G7: =IF($A7="","",IF(COUNTIFS(Fantacalcio[Giornata],G$4,Fantacalcio[Squadra],$A7)=0,"",SUMIFS(Fantacalcio[VdM (mln €)],Fantacalcio[Giornata],G$4,Fantacalcio[Squadra],$A7,Fantacalcio[VotoUtile],"SI"))) -> 183 | H7: =IF($A7="","",IF(COUNTIFS(Fantacalcio[Giornata],H$4,Fantacalcio[Squadra],$A7)=0,"",SUMIFS(Fantacalcio[VdM (mln €)],Fantacalcio[Giornata],H$4,Fantacalcio[Squadra],$A7,Fantacalcio[VotoUtile],"SI"))) -> 179.5 | I7: =IF($A7="","",IF(COUNTIFS(Fantacalcio[Giornata],I$4,Fantacalcio[Squadra],$A7)=0,"",SUMIFS(Fantacalcio[VdM (mln €)],Fantacalcio[Giornata],I$4,Fantacalcio[Squadra],$A7,Fantacalcio[VotoUtile],"SI"))) | J7: =IF($A7="","",IF(COUNTIFS(Fantacalcio[Giornata],J$4,Fantacalcio[Squadra],$A7)=0,"",SUMIFS(Fantacalcio[VdM (mln €)],Fantacalcio[Giornata],J$4,Fantacalcio[Squadra],$A7,Fantacalcio[VotoUtile],"SI"))) | ... AN7: =IF($A7="","",IF(COUNTIFS(Fantacalcio[Giornata],AN$4,Fantacalcio[Squadra],$A7)=0,"",SUMIFS(Fantacalcio[VdM (mln €)],Fantacalcio[Giornata],AN$4,Fantacalcio[Squadra],$A7,Fantacalcio[VotoUtile],"SI")))
A8: Incontro al capitano | B8: =IF($A8="","",IF(COUNT(C8:AN8)=0,"",AVERAGE(C8:AN8))) -> 251.83333 | C8: =IF($A8="","",IF(COUNTIFS(Fantacalcio[Giornata],C$4,Fantacalcio[Squadra],$A8)=0,"",SUMIFS(Fantacalcio[VdM (mln €)],Fantacalcio[Giornata],C$4,Fantacalcio[Squadra],$A8,Fantacalcio[VotoUtile],"SI"))) -> 234.5 | D8: =IF($A8="","",IF(COUNTIFS(Fantacalcio[Giornata],D$4,Fantacalcio[Squadra],$A8)=0,"",SUMIFS(Fantacalcio[VdM (mln €)],Fantacalcio[Giornata],D$4,Fantacalcio[Squadra],$A8,Fantacalcio[VotoUtile],"SI"))) -> 266.5 | E8: =IF($A8="","",IF(COUNTIFS(Fantacalcio[Giornata],E$4,Fantacalcio[Squadra],$A8)=0,"",SUMIFS(Fantacalcio[VdM (mln €)],Fantacalcio[Giornata],E$4,Fantacalcio[Squadra],$A8,Fantacalcio[VotoUtile],"SI"))) -> 252.5 | F8: =IF($A8="","",IF(COUNTIFS(Fantacalcio[Giornata],F$4,Fantacalcio[Squadra],$A8)=0,"",SUMIFS(Fantacalcio[VdM (mln €)],Fantacalcio[Giornata],F$4,Fantacalcio[Squadra],$A8,Fantacalcio[VotoUtile],"SI"))) -> 256.5 | G8: =IF($A8="","",IF(COUNTIFS(Fantacalcio[Giornata],G$4,Fantacalcio[Squadra],$A8)=0,"",SUMIFS(Fantacalcio[VdM (mln €)],Fantacalcio[Giornata],G$4,Fantacalcio[Squadra],$A8,Fantacalcio[VotoUtile],"SI"))) -> 248.5 | H8: =IF($A8="","",IF(COUNTIFS(Fantacalcio[Giornata],H$4,Fantacalcio[Squadra],$A8)=0,"",SUMIFS(Fantacalcio[VdM (mln €)],Fantacalcio[Giornata],H$4,Fantacalcio[Squadra],$A8,Fantacalcio[VotoUtile],"SI"))) -> 252.5 | I8: =IF($A8="","",IF(COUNTIFS(Fantacalcio[Giornata],I$4,Fantacalcio[Squadra],$A8)=0,"",SUMIFS(Fantacalcio[VdM (mln €)],Fantacalcio[Giornata],I$4,Fantacalcio[Squadra],$A8,Fantacalcio[VotoUtile],"SI"))) | J8: =IF($A8="","",IF(COUNTIFS(Fantacalcio[Giornata],J$4,Fantacalcio[Squadra],$A8)=0,"",SUMIFS(Fantacalcio[VdM (mln €)],Fantacalcio[Giornata],J$4,Fantacalcio[Squadra],$A8,Fantacalcio[VotoUtile],"SI"))) | ... AN8: =IF($A8="","",IF(COUNTIFS(Fantacalcio[Giornata],AN$4,Fantacalcio[Squadra],$A8)=0,"",SUMIFS(Fantacalcio[VdM (mln €)],Fantacalcio[Giornata],AN$4,Fantacalcio[Squadra],$A8,Fantacalcio[VotoUtile],"SI")))
A9: Mancinix | B9: =IF($A9="","",IF(COUNT(C9:AN9)=0,"",AVERAGE(C9:AN9))) -> 306.08333 | C9: =IF($A9="","",IF(COUNTIFS(Fantacalcio[Giornata],C$4,Fantacalcio[Squadra],$A9)=0,"",SUMIFS(Fantacalcio[VdM (mln €)],Fantacalcio[Giornata],C$4,Fantacalcio[Squadra],$A9,Fantacalcio[VotoUtile],"SI"))) -> 324 | D9: =IF($A9="","",IF(COUNTIFS(Fantacalcio[Giornata],D$4,Fantacalcio[Squadra],$A9)=0,"",SUMIFS(Fantacalcio[VdM (mln €)],Fantacalcio[Giornata],D$4,Fantacalcio[Squadra],$A9,Fantacalcio[VotoUtile],"SI"))) -> 297 | E9: =IF($A9="","",IF(COUNTIFS(Fantacalcio[Giornata],E$4,Fantacalcio[Squadra],$A9)=0,"",SUMIFS(Fantacalcio[VdM (mln €)],Fantacalcio[Giornata],E$4,Fantacalcio[Squadra],$A9,Fantacalcio[VotoUtile],"SI"))) -> 294 | F9: =IF($A9="","",IF(COUNTIFS(Fantacalcio[Giornata],F$4,Fantacalcio[Squadra],$A9)=0,"",SUMIFS(Fantacalcio[VdM (mln €)],Fantacalcio[Giornata],F$4,Fantacalcio[Squadra],$A9,Fantacalcio[VotoUtile],"SI"))) -> 299.5 | G9: =IF($A9="","",IF(COUNTIFS(Fantacalcio[Giornata],G$4,Fantacalcio[Squadra],$A9)=0,"",SUMIFS(Fantacalcio[VdM (mln €)],Fantacalcio[Giornata],G$4,Fantacalcio[Squadra],$A9,Fantacalcio[VotoUtile],"SI"))) -> 330 | H9: =IF($A9="","",IF(COUNTIFS(Fantacalcio[Giornata],H$4,Fantacalcio[Squadra],$A9)=0,"",SUMIFS(Fantacalcio[VdM (mln €)],Fantacalcio[Giornata],H$4,Fantacalcio[Squadra],$A9,Fantacalcio[VotoUtile],"SI"))) -> 292 | I9: =IF($A9="","",IF(COUNTIFS(Fantacalcio[Giornata],I$4,Fantacalcio[Squadra],$A9)=0,"",SUMIFS(Fantacalcio[VdM (mln €)],Fantacalcio[Giornata],I$4,Fantacalcio[Squadra],$A9,Fantacalcio[VotoUtile],"SI"))) | J9: =IF($A9="","",IF(COUNTIFS(Fantacalcio[Giornata],J$4,Fantacalcio[Squadra],$A9)=0,"",SUMIFS(Fantacalcio[VdM (mln €)],Fantacalcio[Giornata],J$4,Fantacalcio[Squadra],$A9,Fantacalcio[VotoUtile],"SI"))) | ... AN9: =IF($A9="","",IF(COUNTIFS(Fantacalcio[Giornata],AN$4,Fantacalcio[Squadra],$A9)=0,"",SUMIFS(Fantacalcio[VdM (mln €)],Fantacalcio[Giornata],AN$4,Fantacalcio[Squadra],$A9,Fantacalcio[VotoUtile],"SI")))
A10: Masterchef FC | B10: =IF($A10="","",IF(COUNT(C10:AN10)=0,"",AVERAGE(C10:AN10))) -> 203 | C10: =IF($A10="","",IF(COUNTIFS(Fantacalcio[Giornata],C$4,Fantacalcio[Squadra],$A10)=0,"",SUMIFS(Fantacalcio[VdM (mln €)],Fantacalcio[Giornata],C$4,Fantacalcio[Squadra],$A10,Fantacalcio[VotoUtile],"SI"))) -> 209.5 | D10: =IF($A10="","",IF(COUNTIFS(Fantacalcio[Giornata],D$4,Fantacalcio[Squadra],$A10)=0,"",SUMIFS(Fantacalcio[VdM (mln €)],Fantacalcio[Giornata],D$4,Fantacalcio[Squadra],$A10,Fantacalcio[VotoUtile],"SI"))) -> 182 | E10: =IF($A10="","",IF(COUNTIFS(Fantacalcio[Giornata],E$4,Fantacalcio[Squadra],$A10)=0,"",SUMIFS(Fantacalcio[VdM (mln €)],Fantacalcio[Giornata],E$4,Fantacalcio[Squadra],$A10,Fantacalcio[VotoUtile],"SI"))) -> 223.5 | F10: =IF($A10="","",IF(COUNTIFS(Fantacalcio[Giornata],F$4,Fantacalcio[Squadra],$A10)=0,"",SUMIFS(Fantacalcio[VdM (mln €)],Fantacalcio[Giornata],F$4,Fantacalcio[Squadra],$A10,Fantacalcio[VotoUtile],"SI"))) -> 154.5 | G10: =IF($A10="","",IF(COUNTIFS(Fantacalcio[Giornata],G$4,Fantacalcio[Squadra],$A10)=0,"",SUMIFS(Fantacalcio[VdM (mln €)],Fantacalcio[Giornata],G$4,Fantacalcio[Squadra],$A10,Fantacalcio[VotoUtile],"SI"))) -> 178.5 | H10: =IF($A10="","",IF(COUNTIFS(Fantacalcio[Giornata],H$4,Fantacalcio[Squadra],$A10)=0,"",SUMIFS(Fantacalcio[VdM (mln €)],Fantacalcio[Giornata],H$4,Fantacalcio[Squadra],$A10,Fantacalcio[VotoUtile],"SI"))) -> 270 | I10: =IF($A10="","",IF(COUNTIFS(Fantacalcio[Giornata],I$4,Fantacalcio[Squadra],$A10)=0,"",SUMIFS(Fantacalcio[VdM (mln €)],Fantacalcio[Giornata],I$4,Fantacalcio[Squadra],$A10,Fantacalcio[VotoUtile],"SI"))) | J10: =IF($A10="","",IF(COUNTIFS(Fantacalcio[Giornata],J$4,Fantacalcio[Squadra],$A10)=0,"",SUMIFS(Fantacalcio[VdM (mln €)],Fantacalcio[Giornata],J$4,Fantacalcio[Squadra],$A10,Fantacalcio[VotoUtile],"SI"))) | ... AN10: =IF($A10="","",IF(COUNTIFS(Fantacalcio[Giornata],AN$4,Fantacalcio[Squadra],$A10)=0,"",SUMIFS(Fantacalcio[VdM (mln €)],Fantacalcio[Giornata],AN$4,Fantacalcio[Squadra],$A10,Fantacalcio[VotoUtile],"SI")))
A11: Outletico Palermo | B11: =IF($A11="","",IF(COUNT(C11:AN11)=0,"",AVERAGE(C11:AN11))) -> 266.88333 | C11: =IF($A11="","",IF(COUNTIFS(Fantacalcio[Giornata],C$4,Fantacalcio[Squadra],$A11)=0,"",SUMIFS(Fantacalcio[VdM (mln €)],Fantacalcio[Giornata],C$4,Fantacalcio[Squadra],$A11,Fantacalcio[VotoUtile],"SI"))) -> 305 | D11: =IF($A11="","",IF(COUNTIFS(Fantacalcio[Giornata],D$4,Fantacalcio[Squadra],$A11)=0,"",SUMIFS(Fantacalcio[VdM (mln €)],Fantacalcio[Giornata],D$4,Fantacalcio[Squadra],$A11,Fantacalcio[VotoUtile],"SI"))) -> 271 | E11: =IF($A11="","",IF(COUNTIFS(Fantacalcio[Giornata],E$4,Fantacalcio[Squadra],$A11)=0,"",SUMIFS(Fantacalcio[VdM (mln €)],Fantacalcio[Giornata],E$4,Fantacalcio[Squadra],$A11,Fantacalcio[VotoUtile],"SI"))) -> 290 | F11: =IF($A11="","",IF(COUNTIFS(Fantacalcio[Giornata],F$4,Fantacalcio[Squadra],$A11)=0,"",SUMIFS(Fantacalcio[VdM (mln €)],Fantacalcio[Giornata],F$4,Fantacalcio[Squadra],$A11,Fantacalcio[VotoUtile],"SI"))) -> 256 | G11: =IF($A11="","",IF(COUNTIFS(Fantacalcio[Giornata],G$4,Fantacalcio[Squadra],$A11)=0,"",SUMIFS(Fantacalcio[VdM (mln €)],Fantacalcio[Giornata],G$4,Fantacalcio[Squadra],$A11,Fantacalcio[VotoUtile],"SI"))) -> 283 | H11: =IF($A11="","",IF(COUNTIFS(Fantacalcio[Giornata],H$4,Fantacalcio[Squadra],$A11)=0,"",SUMIFS(Fantacalcio[VdM (mln €)],Fantacalcio[Giornata],H$4,Fantacalcio[Squadra],$A11,Fantacalcio[VotoUtile],"SI"))) -> 196.3 | I11: =IF($A11="","",IF(COUNTIFS(Fantacalcio[Giornata],I$4,Fantacalcio[Squadra],$A11)=0,"",SUMIFS(Fantacalcio[VdM (mln €)],Fantacalcio[Giornata],I$4,Fantacalcio[Squadra],$A11,Fantacalcio[VotoUtile],"SI"))) | J11: =IF($A11="","",IF(COUNTIFS(Fantacalcio[Giornata],J$4,Fantacalcio[Squadra],$A11)=0,"",SUMIFS(Fantacalcio[VdM (mln €)],Fantacalcio[Giornata],J$4,Fantacalcio[Squadra],$A11,Fantacalcio[VotoUtile],"SI"))) | ... AN11: =IF($A11="","",IF(COUNTIFS(Fantacalcio[Giornata],AN$4,Fantacalcio[Squadra],$A11)=0,"",SUMIFS(Fantacalcio[VdM (mln €)],Fantacalcio[Giornata],AN$4,Fantacalcio[Squadra],$A11,Fantacalcio[VotoUtile],"SI")))
A12: Paris Saint-Gervasoni | B12: =IF($A12="","",IF(COUNT(C12:AN12)=0,"",AVERAGE(C12:AN12))) -> 190.16667 | C12: =IF($A12="","",IF(COUNTIFS(Fantacalcio[Giornata],C$4,Fantacalcio[Squadra],$A12)=0,"",SUMIFS(Fantacalcio[VdM (mln €)],Fantacalcio[Giornata],C$4,Fantacalcio[Squadra],$A12,Fantacalcio[VotoUtile],"SI"))) -> 233.5 | D12: =IF($A12="","",IF(COUNTIFS(Fantacalcio[Giornata],D$4,Fantacalcio[Squadra],$A12)=0,"",SUMIFS(Fantacalcio[VdM (mln €)],Fantacalcio[Giornata],D$4,Fantacalcio[Squadra],$A12,Fantacalcio[VotoUtile],"SI"))) -> 182 | E12: =IF($A12="","",IF(COUNTIFS(Fantacalcio[Giornata],E$4,Fantacalcio[Squadra],$A12)=0,"",SUMIFS(Fantacalcio[VdM (mln €)],Fantacalcio[Giornata],E$4,Fantacalcio[Squadra],$A12,Fantacalcio[VotoUtile],"SI"))) -> 160 | F12: =IF($A12="","",IF(COUNTIFS(Fantacalcio[Giornata],F$4,Fantacalcio[Squadra],$A12)=0,"",SUMIFS(Fantacalcio[VdM (mln €)],Fantacalcio[Giornata],F$4,Fantacalcio[Squadra],$A12,Fantacalcio[VotoUtile],"SI"))) -> 194.5 | G12: =IF($A12="","",IF(COUNTIFS(Fantacalcio[Giornata],G$4,Fantacalcio[Squadra],$A12)=0,"",SUMIFS(Fantacalcio[VdM (mln €)],Fantacalcio[Giornata],G$4,Fantacalcio[Squadra],$A12,Fantacalcio[VotoUtile],"SI"))) -> 159.5 | H12: =IF($A12="","",IF(COUNTIFS(Fantacalcio[Giornata],H$4,Fantacalcio[Squadra],$A12)=0,"",SUMIFS(Fantacalcio[VdM (mln €)],Fantacalcio[Giornata],H$4,Fantacalcio[Squadra],$A12,Fantacalcio[VotoUtile],"SI"))) -> 211.5 | I12: =IF($A12="","",IF(COUNTIFS(Fantacalcio[Giornata],I$4,Fantacalcio[Squadra],$A12)=0,"",SUMIFS(Fantacalcio[VdM (mln €)],Fantacalcio[Giornata],I$4,Fantacalcio[Squadra],$A12,Fantacalcio[VotoUtile],"SI"))) | J12: =IF($A12="","",IF(COUNTIFS(Fantacalcio[Giornata],J$4,Fantacalcio[Squadra],$A12)=0,"",SUMIFS(Fantacalcio[VdM (mln €)],Fantacalcio[Giornata],J$4,Fantacalcio[Squadra],$A12,Fantacalcio[VotoUtile],"SI"))) | ... AN12: =IF($A12="","",IF(COUNTIFS(Fantacalcio[Giornata],AN$4,Fantacalcio[Squadra],$A12)=0,"",SUMIFS(Fantacalcio[VdM (mln €)],Fantacalcio[Giornata],AN$4,Fantacalcio[Squadra],$A12,Fantacalcio[VotoUtile],"SI")))
A13: Schalke 104 | B13: =IF($A13="","",IF(COUNT(C13:AN13)=0,"",AVERAGE(C13:AN13))) -> 210.16667 | C13: =IF($A13="","",IF(COUNTIFS(Fantacalcio[Giornata],C$4,Fantacalcio[Squadra],$A13)=0,"",SUMIFS(Fantacalcio[VdM (mln €)],Fantacalcio[Giornata],C$4,Fantacalcio[Squadra],$A13,Fantacalcio[VotoUtile],"SI"))) -> 229 | D13: =IF($A13="","",IF(COUNTIFS(Fantacalcio[Giornata],D$4,Fantacalcio[Squadra],$A13)=0,"",SUMIFS(Fantacalcio[VdM (mln €)],Fantacalcio[Giornata],D$4,Fantacalcio[Squadra],$A13,Fantacalcio[VotoUtile],"SI"))) -> 217 | E13: =IF($A13="","",IF(COUNTIFS(Fantacalcio[Giornata],E$4,Fantacalcio[Squadra],$A13)=0,"",SUMIFS(Fantacalcio[VdM (mln €)],Fantacalcio[Giornata],E$4,Fantacalcio[Squadra],$A13,Fantacalcio[VotoUtile],"SI"))) -> 205.5 | F13: =IF($A13="","",IF(COUNTIFS(Fantacalcio[Giornata],F$4,Fantacalcio[Squadra],$A13)=0,"",SUMIFS(Fantacalcio[VdM (mln €)],Fantacalcio[Giornata],F$4,Fantacalcio[Squadra],$A13,Fantacalcio[VotoUtile],"SI"))) -> 171 | G13: =IF($A13="","",IF(COUNTIFS(Fantacalcio[Giornata],G$4,Fantacalcio[Squadra],$A13)=0,"",SUMIFS(Fantacalcio[VdM (mln €)],Fantacalcio[Giornata],G$4,Fantacalcio[Squadra],$A13,Fantacalcio[VotoUtile],"SI"))) -> 217 | H13: =IF($A13="","",IF(COUNTIFS(Fantacalcio[Giornata],H$4,Fantacalcio[Squadra],$A13)=0,"",SUMIFS(Fantacalcio[VdM (mln €)],Fantacalcio[Giornata],H$4,Fantacalcio[Squadra],$A13,Fantacalcio[VotoUtile],"SI"))) -> 221.5 | I13: =IF($A13="","",IF(COUNTIFS(Fantacalcio[Giornata],I$4,Fantacalcio[Squadra],$A13)=0,"",SUMIFS(Fantacalcio[VdM (mln €)],Fantacalcio[Giornata],I$4,Fantacalcio[Squadra],$A13,Fantacalcio[VotoUtile],"SI"))) | J13: =IF($A13="","",IF(COUNTIFS(Fantacalcio[Giornata],J$4,Fantacalcio[Squadra],$A13)=0,"",SUMIFS(Fantacalcio[VdM (mln €)],Fantacalcio[Giornata],J$4,Fantacalcio[Squadra],$A13,Fantacalcio[VotoUtile],"SI"))) | ... AN13: =IF($A13="","",IF(COUNTIFS(Fantacalcio[Giornata],AN$4,Fantacalcio[Squadra],$A13)=0,"",SUMIFS(Fantacalcio[VdM (mln €)],Fantacalcio[Giornata],AN$4,Fantacalcio[Squadra],$A13,Fantacalcio[VotoUtile],"SI")))
A14: SuperGregariana | B14: =IF($A14="","",IF(COUNT(C14:AN14)=0,"",AVERAGE(C14:AN14))) -> 235.33333 | C14: =IF($A14="","",IF(COUNTIFS(Fantacalcio[Giornata],C$4,Fantacalcio[Squadra],$A14)=0,"",SUMIFS(Fantacalcio[VdM (mln €)],Fantacalcio[Giornata],C$4,Fantacalcio[Squadra],$A14,Fantacalcio[VotoUtile],"SI"))) -> 238.5 | D14: =IF($A14="","",IF(COUNTIFS(Fantacalcio[Giornata],D$4,Fantacalcio[Squadra],$A14)=0,"",SUMIFS(Fantacalcio[VdM (mln €)],Fantacalcio[Giornata],D$4,Fantacalcio[Squadra],$A14,Fantacalcio[VotoUtile],"SI"))) -> 277 | E14: =IF($A14="","",IF(COUNTIFS(Fantacalcio[Giornata],E$4,Fantacalcio[Squadra],$A14)=0,"",SUMIFS(Fantacalcio[VdM (mln €)],Fantacalcio[Giornata],E$4,Fantacalcio[Squadra],$A14,Fantacalcio[VotoUtile],"SI"))) -> 227.5 | F14: =IF($A14="","",IF(COUNTIFS(Fantacalcio[Giornata],F$4,Fantacalcio[Squadra],$A14)=0,"",SUMIFS(Fantacalcio[VdM (mln €)],Fantacalcio[Giornata],F$4,Fantacalcio[Squadra],$A14,Fantacalcio[VotoUtile],"SI"))) -> 217 | G14: =IF($A14="","",IF(COUNTIFS(Fantacalcio[Giornata],G$4,Fantacalcio[Squadra],$A14)=0,"",SUMIFS(Fantacalcio[VdM (mln €)],Fantacalcio[Giornata],G$4,Fantacalcio[Squadra],$A14,Fantacalcio[VotoUtile],"SI"))) -> 217.5 | H14: =IF($A14="","",IF(COUNTIFS(Fantacalcio[Giornata],H$4,Fantacalcio[Squadra],$A14)=0,"",SUMIFS(Fantacalcio[VdM (mln €)],Fantacalcio[Giornata],H$4,Fantacalcio[Squadra],$A14,Fantacalcio[VotoUtile],"SI"))) -> 234.5 | I14: =IF($A14="","",IF(COUNTIFS(Fantacalcio[Giornata],I$4,Fantacalcio[Squadra],$A14)=0,"",SUMIFS(Fantacalcio[VdM (mln €)],Fantacalcio[Giornata],I$4,Fantacalcio[Squadra],$A14,Fantacalcio[VotoUtile],"SI"))) | J14: =IF($A14="","",IF(COUNTIFS(Fantacalcio[Giornata],J$4,Fantacalcio[Squadra],$A14)=0,"",SUMIFS(Fantacalcio[VdM (mln €)],Fantacalcio[Giornata],J$4,Fantacalcio[Squadra],$A14,Fantacalcio[VotoUtile],"SI"))) | ... AN14: =IF($A14="","",IF(COUNTIFS(Fantacalcio[Giornata],AN$4,Fantacalcio[Squadra],$A14)=0,"",SUMIFS(Fantacalcio[VdM (mln €)],Fantacalcio[Giornata],AN$4,Fantacalcio[Squadra],$A14,Fantacalcio[VotoUtile],"SI")))
A16: Legenda
A17: Ogni cella Giornata × Squadra = somma dei VdM (mln €) dei giocatori schierati con VotoUtile = SI
A18: Media = media dei soli totali di giornata già presenti nel foglio Database
A19: Le giornate non ancora inserite nel Database restano vuote e non entrano nel calcolo della media
A20: Le squadre e i valori si aggiornano automaticamente quando vengono aggiunte nuove giornate al Database
A21: Valori espressi in milioni di euro (mln €)
A25: Classifica per VdM Medio (tutte le giornate compilate)
A26: Squadra | B26: Media VdM
A27: {=IF(ROWS($A$27:A27)>SUMPRODUCT(--ISNUMBER($B$5:$B$14)),"",INDEX(_xlfn._xlws.SORT(_xlfn._xlws.FILTER($A$5:$B$14,ISNUMBER($B$5:$B$14)),2,-1),ROWS($A$27:A27),1))} -> Mancinix | B27: {=IF(ROWS($A$27:A27)>SUMPRODUCT(--ISNUMBER($B$5:$B$14)),"",INDEX(_xlfn._xlws.SORT(_xlfn._xlws.FILTER($A$5:$B$14,ISNUMBER($B$5:$B$14)),2,-1),ROWS($A$27:A27),2))} -> 306.08333
A28: {=IF(ROWS($A$27:A28)>SUMPRODUCT(--ISNUMBER($B$5:$B$14)),"",INDEX(_xlfn._xlws.SORT(_xlfn._xlws.FILTER($A$5:$B$14,ISNUMBER($B$5:$B$14)),2,-1),ROWS($A$27:A28),1))} -> GC21 | B28: {=IF(ROWS($A$27:A28)>SUMPRODUCT(--ISNUMBER($B$5:$B$14)),"",INDEX(_xlfn._xlws.SORT(_xlfn._xlws.FILTER($A$5:$B$14,ISNUMBER($B$5:$B$14)),2,-1),ROWS($A$27:A28),2))} -> 300.83333
A29: {=IF(ROWS($A$27:A29)>SUMPRODUCT(--ISNUMBER($B$5:$B$14)),"",INDEX(_xlfn._xlws.SORT(_xlfn._xlws.FILTER($A$5:$B$14,ISNUMBER($B$5:$B$14)),2,-1),ROWS($A$27:A29),1))} -> Outletico Palermo | B29: {=IF(ROWS($A$27:A29)>SUMPRODUCT(--ISNUMBER($B$5:$B$14)),"",INDEX(_xlfn._xlws.SORT(_xlfn._xlws.FILTER($A$5:$B$14,ISNUMBER($B$5:$B$14)),2,-1),ROWS($A$27:A29),2))} -> 266.88333
A30: {=IF(ROWS($A$27:A30)>SUMPRODUCT(--ISNUMBER($B$5:$B$14)),"",INDEX(_xlfn._xlws.SORT(_xlfn._xlws.FILTER($A$5:$B$14,ISNUMBER($B$5:$B$14)),2,-1),ROWS($A$27:A30),1))} -> Incontro al capitano | B30: {=IF(ROWS($A$27:A30)>SUMPRODUCT(--ISNUMBER($B$5:$B$14)),"",INDEX(_xlfn._xlws.SORT(_xlfn._xlws.FILTER($A$5:$B$14,ISNUMBER($B$5:$B$14)),2,-1),ROWS($A$27:A30),2))} -> 251.83333
A31: {=IF(ROWS($A$27:A31)>SUMPRODUCT(--ISNUMBER($B$5:$B$14)),"",INDEX(_xlfn._xlws.SORT(_xlfn._xlws.FILTER($A$5:$B$14,ISNUMBER($B$5:$B$14)),2,-1),ROWS($A$27:A31),1))} -> SuperGregariana | B31: {=IF(ROWS($A$27:A31)>SUMPRODUCT(--ISNUMBER($B$5:$B$14)),"",INDEX(_xlfn._xlws.SORT(_xlfn._xlws.FILTER($A$5:$B$14,ISNUMBER($B$5:$B$14)),2,-1),ROWS($A$27:A31),2))} -> 235.33333
A32: {=IF(ROWS($A$27:A32)>SUMPRODUCT(--ISNUMBER($B$5:$B$14)),"",INDEX(_xlfn._xlws.SORT(_xlfn._xlws.FILTER($A$5:$B$14,ISNUMBER($B$5:$B$14)),2,-1),ROWS($A$27:A32),1))} -> Schalke 104 | B32: {=IF(ROWS($A$27:A32)>SUMPRODUCT(--ISNUMBER($B$5:$B$14)),"",INDEX(_xlfn._xlws.SORT(_xlfn._xlws.FILTER($A$5:$B$14,ISNUMBER($B$5:$B$14)),2,-1),ROWS($A$27:A32),2))} -> 210.16667
A33: {=IF(ROWS($A$27:A33)>SUMPRODUCT(--ISNUMBER($B$5:$B$14)),"",INDEX(_xlfn._xlws.SORT(_xlfn._xlws.FILTER($A$5:$B$14,ISNUMBER($B$5:$B$14)),2,-1),ROWS($A$27:A33),1))} -> Masterchef FC | B33: {=IF(ROWS($A$27:A33)>SUMPRODUCT(--ISNUMBER($B$5:$B$14)),"",INDEX(_xlfn._xlws.SORT(_xlfn._xlws.FILTER($A$5:$B$14,ISNUMBER($B$5:$B$14)),2,-1),ROWS($A$27:A33),2))} -> 203
A34: {=IF(ROWS($A$27:A34)>SUMPRODUCT(--ISNUMBER($B$5:$B$14)),"",INDEX(_xlfn._xlws.SORT(_xlfn._xlws.FILTER($A$5:$B$14,ISNUMBER($B$5:$B$14)),2,-1),ROWS($A$27:A34),1))} -> Paris Saint-Gervasoni | B34: {=IF(ROWS($A$27:A34)>SUMPRODUCT(--ISNUMBER($B$5:$B$14)),"",INDEX(_xlfn._xlws.SORT(_xlfn._xlws.FILTER($A$5:$B$14,ISNUMBER($B$5:$B$14)),2,-1),ROWS($A$27:A34),2))} -> 190.16667
A35: {=IF(ROWS($A$27:A35)>SUMPRODUCT(--ISNUMBER($B$5:$B$14)),"",INDEX(_xlfn._xlws.SORT(_xlfn._xlws.FILTER($A$5:$B$14,ISNUMBER($B$5:$B$14)),2,-1),ROWS($A$27:A35),1))} -> I Bamboli | B35: {=IF(ROWS($A$27:A35)>SUMPRODUCT(--ISNUMBER($B$5:$B$14)),"",INDEX(_xlfn._xlws.SORT(_xlfn._xlws.FILTER($A$5:$B$14,ISNUMBER($B$5:$B$14)),2,-1),ROWS($A$27:A35),2))} -> 174.75
A36: {=IF(ROWS($A$27:A36)>SUMPRODUCT(--ISNUMBER($B$5:$B$14)),"",INDEX(_xlfn._xlws.SORT(_xlfn._xlws.FILTER($A$5:$B$14,ISNUMBER($B$5:$B$14)),2,-1),ROWS($A$27:A36),1))} -> Evacuo Kaka Toni | B36: {=IF(ROWS($A$27:A36)>SUMPRODUCT(--ISNUMBER($B$5:$B$14)),"",INDEX(_xlfn._xlws.SORT(_xlfn._xlws.FILTER($A$5:$B$14,ISNUMBER($B$5:$B$14)),2,-1),ROWS($A$27:A36),2))} -> 157.83333
A38: =IF(COUNT($C$5:$AN$14)=0,"Classifica ultima giornata - nessuna giornata compilata","Classifica Giornata "&MAX(_xlfn._xlws.FILTER($C$4:$AN$4,_xlfn.BYCOL($C$5:$AN$14,_xlfn.LAMBDA(_xlpm.c,COUNT(_xlpm.c)>0))))&" (ultima giornata compilata)") -> Classifica Giornata 6 (ultima giornata compilata)
A39: Squadra | B39: VdM Giornata
A40: {=IF(COUNT($C$5:$AN$14)=0,"",IF(ROWS($A$40:A40)>SUMPRODUCT(--ISNUMBER(_xlfn.CHOOSECOLS($C$5:$AN$14,MAX(_xlfn._xlws.FILTER(_xlfn.SEQUENCE(1,COLUMNS($C$4:$AN$4)),_xlfn.BYCOL($C$5:$AN$14,_xlfn.LAMBDA(_xlpm.c,COUNT(_xlpm.c)>0))))))),"",INDEX(_xlfn._xlws.SORT(_xlfn._xlws.FILTER(_xlfn.HSTACK($A$5:$A$14,_xlfn.CHOOSECOLS($C$5:$AN$14,MAX(_xlfn._xlws.FILTER(_xlfn.SEQUENCE(1,COLUMNS($C$4:$AN$4)),_xlfn.BYCOL($C$5:$AN$14,_xlfn.LAMBDA(_xlpm.c,COUNT(_xlpm.c)>0)))))),ISNUMBER(_xlfn.CHOOSECOLS($C$5:$AN$14,MAX(_xlfn._xlws.FILTER(_xlfn.SEQUENCE(1,COLUMNS($C$4:$AN$4)),_xlfn.BYCOL($C$5:$AN$14,_xlfn.LAMBDA(_xlpm.c,COUNT(_xlpm.c)>0))))))),2,-1),ROWS($A$40:A40),1)))} -> GC21 | B40: {=IF(COUNT($C$5:$AN$14)=0,"",IF(ROWS($A$40:A40)>SUMPRODUCT(--ISNUMBER(_xlfn.CHOOSECOLS($C$5:$AN$14,MAX(_xlfn._xlws.FILTER(_xlfn.SEQUENCE(1,COLUMNS($C$4:$AN$4)),_xlfn.BYCOL($C$5:$AN$14,_xlfn.LAMBDA(_xlpm.c,COUNT(_xlpm.c)>0))))))),"",INDEX(_xlfn._xlws.SORT(_xlfn._xlws.FILTER(_xlfn.HSTACK($A$5:$A$14,_xlfn.CHOOSECOLS($C$5:$AN$14,MAX(_xlfn._xlws.FILTER(_xlfn.SEQUENCE(1,COLUMNS($C$4:$AN$4)),_xlfn.BYCOL($C$5:$AN$14,_xlfn.LAMBDA(_xlpm.c,COUNT(_xlpm.c)>0)))))),ISNUMBER(_xlfn.CHOOSECOLS($C$5:$AN$14,MAX(_xlfn._xlws.FILTER(_xlfn.SEQUENCE(1,COLUMNS($C$4:$AN$4)),_xlfn.BYCOL($C$5:$AN$14,_xlfn.LAMBDA(_xlpm.c,COUNT(_xlpm.c)>0))))))),2,-1),ROWS($A$40:A40),2)))} -> 322.5
A41: {=IF(COUNT($C$5:$AN$14)=0,"",IF(ROWS($A$40:A41)>SUMPRODUCT(--ISNUMBER(_xlfn.CHOOSECOLS($C$5:$AN$14,MAX(_xlfn._xlws.FILTER(_xlfn.SEQUENCE(1,COLUMNS($C$4:$AN$4)),_xlfn.BYCOL($C$5:$AN$14,_xlfn.LAMBDA(_xlpm.c,COUNT(_xlpm.c)>0))))))),"",INDEX(_xlfn._xlws.SORT(_xlfn._xlws.FILTER(_xlfn.HSTACK($A$5:$A$14,_xlfn.CHOOSECOLS($C$5:$AN$14,MAX(_xlfn._xlws.FILTER(_xlfn.SEQUENCE(1,COLUMNS($C$4:$AN$4)),_xlfn.BYCOL($C$5:$AN$14,_xlfn.LAMBDA(_xlpm.c,COUNT(_xlpm.c)>0)))))),ISNUMBER(_xlfn.CHOOSECOLS($C$5:$AN$14,MAX(_xlfn._xlws.FILTER(_xlfn.SEQUENCE(1,COLUMNS($C$4:$AN$4)),_xlfn.BYCOL($C$5:$AN$14,_xlfn.LAMBDA(_xlpm.c,COUNT(_xlpm.c)>0))))))),2,-1),ROWS($A$40:A41),1)))} -> Mancinix | B41: {=IF(COUNT($C$5:$AN$14)=0,"",IF(ROWS($A$40:A41)>SUMPRODUCT(--ISNUMBER(_xlfn.CHOOSECOLS($C$5:$AN$14,MAX(_xlfn._xlws.FILTER(_xlfn.SEQUENCE(1,COLUMNS($C$4:$AN$4)),_xlfn.BYCOL($C$5:$AN$14,_xlfn.LAMBDA(_xlpm.c,COUNT(_xlpm.c)>0))))))),"",INDEX(_xlfn._xlws.SORT(_xlfn._xlws.FILTER(_xlfn.HSTACK($A$5:$A$14,_xlfn.CHOOSECOLS($C$5:$AN$14,MAX(_xlfn._xlws.FILTER(_xlfn.SEQUENCE(1,COLUMNS($C$4:$AN$4)),_xlfn.BYCOL($C$5:$AN$14,_xlfn.LAMBDA(_xlpm.c,COUNT(_xlpm.c)>0)))))),ISNUMBER(_xlfn.CHOOSECOLS($C$5:$AN$14,MAX(_xlfn._xlws.FILTER(_xlfn.SEQUENCE(1,COLUMNS($C$4:$AN$4)),_xlfn.BYCOL($C$5:$AN$14,_xlfn.LAMBDA(_xlpm.c,COUNT(_xlpm.c)>0))))))),2,-1),ROWS($A$40:A41),2)))} -> 292
A42: {=IF(COUNT($C$5:$AN$14)=0,"",IF(ROWS($A$40:A42)>SUMPRODUCT(--ISNUMBER(_xlfn.CHOOSECOLS($C$5:$AN$14,MAX(_xlfn._xlws.FILTER(_xlfn.SEQUENCE(1,COLUMNS($C$4:$AN$4)),_xlfn.BYCOL($C$5:$AN$14,_xlfn.LAMBDA(_xlpm.c,COUNT(_xlpm.c)>0))))))),"",INDEX(_xlfn._xlws.SORT(_xlfn._xlws.FILTER(_xlfn.HSTACK($A$5:$A$14,_xlfn.CHOOSECOLS($C$5:$AN$14,MAX(_xlfn._xlws.FILTER(_xlfn.SEQUENCE(1,COLUMNS($C$4:$AN$4)),_xlfn.BYCOL($C$5:$AN$14,_xlfn.LAMBDA(_xlpm.c,COUNT(_xlpm.c)>0)))))),ISNUMBER(_xlfn.CHOOSECOLS($C$5:$AN$14,MAX(_xlfn._xlws.FILTER(_xlfn.SEQUENCE(1,COLUMNS($C$4:$AN$4)),_xlfn.BYCOL($C$5:$AN$14,_xlfn.LAMBDA(_xlpm.c,COUNT(_xlpm.c)>0))))))),2,-1),ROWS($A$40:A42),1)))} -> Masterchef FC | B42: {=IF(COUNT($C$5:$AN$14)=0,"",IF(ROWS($A$40:A42)>SUMPRODUCT(--ISNUMBER(_xlfn.CHOOSECOLS($C$5:$AN$14,MAX(_xlfn._xlws.FILTER(_xlfn.SEQUENCE(1,COLUMNS($C$4:$AN$4)),_xlfn.BYCOL($C$5:$AN$14,_xlfn.LAMBDA(_xlpm.c,COUNT(_xlpm.c)>0))))))),"",INDEX(_xlfn._xlws.SORT(_xlfn._xlws.FILTER(_xlfn.HSTACK($A$5:$A$14,_xlfn.CHOOSECOLS($C$5:$AN$14,MAX(_xlfn._xlws.FILTER(_xlfn.SEQUENCE(1,COLUMNS($C$4:$AN$4)),_xlfn.BYCOL($C$5:$AN$14,_xlfn.LAMBDA(_xlpm.c,COUNT(_xlpm.c)>0)))))),ISNUMBER(_xlfn.CHOOSECOLS($C$5:$AN$14,MAX(_xlfn._xlws.FILTER(_xlfn.SEQUENCE(1,COLUMNS($C$4:$AN$4)),_xlfn.BYCOL($C$5:$AN$14,_xlfn.LAMBDA(_xlpm.c,COUNT(_xlpm.c)>0))))))),2,-1),ROWS($A$40:A42),2)))} -> 270
A43: {=IF(COUNT($C$5:$AN$14)=0,"",IF(ROWS($A$40:A43)>SUMPRODUCT(--ISNUMBER(_xlfn.CHOOSECOLS($C$5:$AN$14,MAX(_xlfn._xlws.FILTER(_xlfn.SEQUENCE(1,COLUMNS($C$4:$AN$4)),_xlfn.BYCOL($C$5:$AN$14,_xlfn.LAMBDA(_xlpm.c,COUNT(_xlpm.c)>0))))))),"",INDEX(_xlfn._xlws.SORT(_xlfn._xlws.FILTER(_xlfn.HSTACK($A$5:$A$14,_xlfn.CHOOSECOLS($C$5:$AN$14,MAX(_xlfn._xlws.FILTER(_xlfn.SEQUENCE(1,COLUMNS($C$4:$AN$4)),_xlfn.BYCOL($C$5:$AN$14,_xlfn.LAMBDA(_xlpm.c,COUNT(_xlpm.c)>0)))))),ISNUMBER(_xlfn.CHOOSECOLS($C$5:$AN$14,MAX(_xlfn._xlws.FILTER(_xlfn.SEQUENCE(1,COLUMNS($C$4:$AN$4)),_xlfn.BYCOL($C$5:$AN$14,_xlfn.LAMBDA(_xlpm.c,COUNT(_xlpm.c)>0))))))),2,-1),ROWS($A$40:A43),1)))} -> Incontro al capitano | B43: {=IF(COUNT($C$5:$AN$14)=0,"",IF(ROWS($A$40:A43)>SUMPRODUCT(--ISNUMBER(_xlfn.CHOOSECOLS($C$5:$AN$14,MAX(_xlfn._xlws.FILTER(_xlfn.SEQUENCE(1,COLUMNS($C$4:$AN$4)),_xlfn.BYCOL($C$5:$AN$14,_xlfn.LAMBDA(_xlpm.c,COUNT(_xlpm.c)>0))))))),"",INDEX(_xlfn._xlws.SORT(_xlfn._xlws.FILTER(_xlfn.HSTACK($A$5:$A$14,_xlfn.CHOOSECOLS($C$5:$AN$14,MAX(_xlfn._xlws.FILTER(_xlfn.SEQUENCE(1,COLUMNS($C$4:$AN$4)),_xlfn.BYCOL($C$5:$AN$14,_xlfn.LAMBDA(_xlpm.c,COUNT(_xlpm.c)>0)))))),ISNUMBER(_xlfn.CHOOSECOLS($C$5:$AN$14,MAX(_xlfn._xlws.FILTER(_xlfn.SEQUENCE(1,COLUMNS($C$4:$AN$4)),_xlfn.BYCOL($C$5:$AN$14,_xlfn.LAMBDA(_xlpm.c,COUNT(_xlpm.c)>0))))))),2,-1),ROWS($A$40:A43),2)))} -> 252.5
A44: {=IF(COUNT($C$5:$AN$14)=0,"",IF(ROWS($A$40:A44)>SUMPRODUCT(--ISNUMBER(_xlfn.CHOOSECOLS($C$5:$AN$14,MAX(_xlfn._xlws.FILTER(_xlfn.SEQUENCE(1,COLUMNS($C$4:$AN$4)),_xlfn.BYCOL($C$5:$AN$14,_xlfn.LAMBDA(_xlpm.c,COUNT(_xlpm.c)>0))))))),"",INDEX(_xlfn._xlws.SORT(_xlfn._xlws.FILTER(_xlfn.HSTACK($A$5:$A$14,_xlfn.CHOOSECOLS($C$5:$AN$14,MAX(_xlfn._xlws.FILTER(_xlfn.SEQUENCE(1,COLUMNS($C$4:$AN$4)),_xlfn.BYCOL($C$5:$AN$14,_xlfn.LAMBDA(_xlpm.c,COUNT(_xlpm.c)>0)))))),ISNUMBER(_xlfn.CHOOSECOLS($C$5:$AN$14,MAX(_xlfn._xlws.FILTER(_xlfn.SEQUENCE(1,COLUMNS($C$4:$AN$4)),_xlfn.BYCOL($C$5:$AN$14,_xlfn.LAMBDA(_xlpm.c,COUNT(_xlpm.c)>0))))))),2,-1),ROWS($A$40:A44),1)))} -> SuperGregariana | B44: {=IF(COUNT($C$5:$AN$14)=0,"",IF(ROWS($A$40:A44)>SUMPRODUCT(--ISNUMBER(_xlfn.CHOOSECOLS($C$5:$AN$14,MAX(_xlfn._xlws.FILTER(_xlfn.SEQUENCE(1,COLUMNS($C$4:$AN$4)),_xlfn.BYCOL($C$5:$AN$14,_xlfn.LAMBDA(_xlpm.c,COUNT(_xlpm.c)>0))))))),"",INDEX(_xlfn._xlws.SORT(_xlfn._xlws.FILTER(_xlfn.HSTACK($A$5:$A$14,_xlfn.CHOOSECOLS($C$5:$AN$14,MAX(_xlfn._xlws.FILTER(_xlfn.SEQUENCE(1,COLUMNS($C$4:$AN$4)),_xlfn.BYCOL($C$5:$AN$14,_xlfn.LAMBDA(_xlpm.c,COUNT(_xlpm.c)>0)))))),ISNUMBER(_xlfn.CHOOSECOLS($C$5:$AN$14,MAX(_xlfn._xlws.FILTER(_xlfn.SEQUENCE(1,COLUMNS($C$4:$AN$4)),_xlfn.BYCOL($C$5:$AN$14,_xlfn.LAMBDA(_xlpm.c,COUNT(_xlpm.c)>0))))))),2,-1),ROWS($A$40:A44),2)))} -> 234.5
A45: {=IF(COUNT($C$5:$AN$14)=0,"",IF(ROWS($A$40:A45)>SUMPRODUCT(--ISNUMBER(_xlfn.CHOOSECOLS($C$5:$AN$14,MAX(_xlfn._xlws.FILTER(_xlfn.SEQUENCE(1,COLUMNS($C$4:$AN$4)),_xlfn.BYCOL($C$5:$AN$14,_xlfn.LAMBDA(_xlpm.c,COUNT(_xlpm.c)>0))))))),"",INDEX(_xlfn._xlws.SORT(_xlfn._xlws.FILTER(_xlfn.HSTACK($A$5:$A$14,_xlfn.CHOOSECOLS($C$5:$AN$14,MAX(_xlfn._xlws.FILTER(_xlfn.SEQUENCE(1,COLUMNS($C$4:$AN$4)),_xlfn.BYCOL($C$5:$AN$14,_xlfn.LAMBDA(_xlpm.c,COUNT(_xlpm.c)>0)))))),ISNUMBER(_xlfn.CHOOSECOLS($C$5:$AN$14,MAX(_xlfn._xlws.FILTER(_xlfn.SEQUENCE(1,COLUMNS($C$4:$AN$4)),_xlfn.BYCOL($C$5:$AN$14,_xlfn.LAMBDA(_xlpm.c,COUNT(_xlpm.c)>0))))))),2,-1),ROWS($A$40:A45),1)))} -> Schalke 104 | B45: {=IF(COUNT($C$5:$AN$14)=0,"",IF(ROWS($A$40:A45)>SUMPRODUCT(--ISNUMBER(_xlfn.CHOOSECOLS($C$5:$AN$14,MAX(_xlfn._xlws.FILTER(_xlfn.SEQUENCE(1,COLUMNS($C$4:$AN$4)),_xlfn.BYCOL($C$5:$AN$14,_xlfn.LAMBDA(_xlpm.c,COUNT(_xlpm.c)>0))))))),"",INDEX(_xlfn._xlws.SORT(_xlfn._xlws.FILTER(_xlfn.HSTACK($A$5:$A$14,_xlfn.CHOOSECOLS($C$5:$AN$14,MAX(_xlfn._xlws.FILTER(_xlfn.SEQUENCE(1,COLUMNS($C$4:$AN$4)),_xlfn.BYCOL($C$5:$AN$14,_xlfn.LAMBDA(_xlpm.c,COUNT(_xlpm.c)>0)))))),ISNUMBER(_xlfn.CHOOSECOLS($C$5:$AN$14,MAX(_xlfn._xlws.FILTER(_xlfn.SEQUENCE(1,COLUMNS($C$4:$AN$4)),_xlfn.BYCOL($C$5:$AN$14,_xlfn.LAMBDA(_xlpm.c,COUNT(_xlpm.c)>0))))))),2,-1),ROWS($A$40:A45),2)))} -> 221.5
A46: {=IF(COUNT($C$5:$AN$14)=0,"",IF(ROWS($A$40:A46)>SUMPRODUCT(--ISNUMBER(_xlfn.CHOOSECOLS($C$5:$AN$14,MAX(_xlfn._xlws.FILTER(_xlfn.SEQUENCE(1,COLUMNS($C$4:$AN$4)),_xlfn.BYCOL($C$5:$AN$14,_xlfn.LAMBDA(_xlpm.c,COUNT(_xlpm.c)>0))))))),"",INDEX(_xlfn._xlws.SORT(_xlfn._xlws.FILTER(_xlfn.HSTACK($A$5:$A$14,_xlfn.CHOOSECOLS($C$5:$AN$14,MAX(_xlfn._xlws.FILTER(_xlfn.SEQUENCE(1,COLUMNS($C$4:$AN$4)),_xlfn.BYCOL($C$5:$AN$14,_xlfn.LAMBDA(_xlpm.c,COUNT(_xlpm.c)>0)))))),ISNUMBER(_xlfn.CHOOSECOLS($C$5:$AN$14,MAX(_xlfn._xlws.FILTER(_xlfn.SEQUENCE(1,COLUMNS($C$4:$AN$4)),_xlfn.BYCOL($C$5:$AN$14,_xlfn.LAMBDA(_xlpm.c,COUNT(_xlpm.c)>0))))))),2,-1),ROWS($A$40:A46),1)))} -> Paris Saint-Gervasoni | B46: {=IF(COUNT($C$5:$AN$14)=0,"",IF(ROWS($A$40:A46)>SUMPRODUCT(--ISNUMBER(_xlfn.CHOOSECOLS($C$5:$AN$14,MAX(_xlfn._xlws.FILTER(_xlfn.SEQUENCE(1,COLUMNS($C$4:$AN$4)),_xlfn.BYCOL($C$5:$AN$14,_xlfn.LAMBDA(_xlpm.c,COUNT(_xlpm.c)>0))))))),"",INDEX(_xlfn._xlws.SORT(_xlfn._xlws.FILTER(_xlfn.HSTACK($A$5:$A$14,_xlfn.CHOOSECOLS($C$5:$AN$14,MAX(_xlfn._xlws.FILTER(_xlfn.SEQUENCE(1,COLUMNS($C$4:$AN$4)),_xlfn.BYCOL($C$5:$AN$14,_xlfn.LAMBDA(_xlpm.c,COUNT(_xlpm.c)>0)))))),ISNUMBER(_xlfn.CHOOSECOLS($C$5:$AN$14,MAX(_xlfn._xlws.FILTER(_xlfn.SEQUENCE(1,COLUMNS($C$4:$AN$4)),_xlfn.BYCOL($C$5:$AN$14,_xlfn.LAMBDA(_xlpm.c,COUNT(_xlpm.c)>0))))))),2,-1),ROWS($A$40:A46),2)))} -> 211.5
A47: {=IF(COUNT($C$5:$AN$14)=0,"",IF(ROWS($A$40:A47)>SUMPRODUCT(--ISNUMBER(_xlfn.CHOOSECOLS($C$5:$AN$14,MAX(_xlfn._xlws.FILTER(_xlfn.SEQUENCE(1,COLUMNS($C$4:$AN$4)),_xlfn.BYCOL($C$5:$AN$14,_xlfn.LAMBDA(_xlpm.c,COUNT(_xlpm.c)>0))))))),"",INDEX(_xlfn._xlws.SORT(_xlfn._xlws.FILTER(_xlfn.HSTACK($A$5:$A$14,_xlfn.CHOOSECOLS($C$5:$AN$14,MAX(_xlfn._xlws.FILTER(_xlfn.SEQUENCE(1,COLUMNS($C$4:$AN$4)),_xlfn.BYCOL($C$5:$AN$14,_xlfn.LAMBDA(_xlpm.c,COUNT(_xlpm.c)>0)))))),ISNUMBER(_xlfn.CHOOSECOLS($C$5:$AN$14,MAX(_xlfn._xlws.FILTER(_xlfn.SEQUENCE(1,COLUMNS($C$4:$AN$4)),_xlfn.BYCOL($C$5:$AN$14,_xlfn.LAMBDA(_xlpm.c,COUNT(_xlpm.c)>0))))))),2,-1),ROWS($A$40:A47),1)))} -> Outletico Palermo | B47: {=IF(COUNT($C$5:$AN$14)=0,"",IF(ROWS($A$40:A47)>SUMPRODUCT(--ISNUMBER(_xlfn.CHOOSECOLS($C$5:$AN$14,MAX(_xlfn._xlws.FILTER(_xlfn.SEQUENCE(1,COLUMNS($C$4:$AN$4)),_xlfn.BYCOL($C$5:$AN$14,_xlfn.LAMBDA(_xlpm.c,COUNT(_xlpm.c)>0))))))),"",INDEX(_xlfn._xlws.SORT(_xlfn._xlws.FILTER(_xlfn.HSTACK($A$5:$A$14,_xlfn.CHOOSECOLS($C$5:$AN$14,MAX(_xlfn._xlws.FILTER(_xlfn.SEQUENCE(1,COLUMNS($C$4:$AN$4)),_xlfn.BYCOL($C$5:$AN$14,_xlfn.LAMBDA(_xlpm.c,COUNT(_xlpm.c)>0)))))),ISNUMBER(_xlfn.CHOOSECOLS($C$5:$AN$14,MAX(_xlfn._xlws.FILTER(_xlfn.SEQUENCE(1,COLUMNS($C$4:$AN$4)),_xlfn.BYCOL($C$5:$AN$14,_xlfn.LAMBDA(_xlpm.c,COUNT(_xlpm.c)>0))))))),2,-1),ROWS($A$40:A47),2)))} -> 196.3
A48: {=IF(COUNT($C$5:$AN$14)=0,"",IF(ROWS($A$40:A48)>SUMPRODUCT(--ISNUMBER(_xlfn.CHOOSECOLS($C$5:$AN$14,MAX(_xlfn._xlws.FILTER(_xlfn.SEQUENCE(1,COLUMNS($C$4:$AN$4)),_xlfn.BYCOL($C$5:$AN$14,_xlfn.LAMBDA(_xlpm.c,COUNT(_xlpm.c)>0))))))),"",INDEX(_xlfn._xlws.SORT(_xlfn._xlws.FILTER(_xlfn.HSTACK($A$5:$A$14,_xlfn.CHOOSECOLS($C$5:$AN$14,MAX(_xlfn._xlws.FILTER(_xlfn.SEQUENCE(1,COLUMNS($C$4:$AN$4)),_xlfn.BYCOL($C$5:$AN$14,_xlfn.LAMBDA(_xlpm.c,COUNT(_xlpm.c)>0)))))),ISNUMBER(_xlfn.CHOOSECOLS($C$5:$AN$14,MAX(_xlfn._xlws.FILTER(_xlfn.SEQUENCE(1,COLUMNS($C$4:$AN$4)),_xlfn.BYCOL($C$5:$AN$14,_xlfn.LAMBDA(_xlpm.c,COUNT(_xlpm.c)>0))))))),2,-1),ROWS($A$40:A48),1)))} -> I Bamboli | B48: {=IF(COUNT($C$5:$AN$14)=0,"",IF(ROWS($A$40:A48)>SUMPRODUCT(--ISNUMBER(_xlfn.CHOOSECOLS($C$5:$AN$14,MAX(_xlfn._xlws.FILTER(_xlfn.SEQUENCE(1,COLUMNS($C$4:$AN$4)),_xlfn.BYCOL($C$5:$AN$14,_xlfn.LAMBDA(_xlpm.c,COUNT(_xlpm.c)>0))))))),"",INDEX(_xlfn._xlws.SORT(_xlfn._xlws.FILTER(_xlfn.HSTACK($A$5:$A$14,_xlfn.CHOOSECOLS($C$5:$AN$14,MAX(_xlfn._xlws.FILTER(_xlfn.SEQUENCE(1,COLUMNS($C$4:$AN$4)),_xlfn.BYCOL($C$5:$AN$14,_xlfn.LAMBDA(_xlpm.c,COUNT(_xlpm.c)>0)))))),ISNUMBER(_xlfn.CHOOSECOLS($C$5:$AN$14,MAX(_xlfn._xlws.FILTER(_xlfn.SEQUENCE(1,COLUMNS($C$4:$AN$4)),_xlfn.BYCOL($C$5:$AN$14,_xlfn.LAMBDA(_xlpm.c,COUNT(_xlpm.c)>0))))))),2,-1),ROWS($A$40:A48),2)))} -> 179.5
A49: {=IF(COUNT($C$5:$AN$14)=0,"",IF(ROWS($A$40:A49)>SUMPRODUCT(--ISNUMBER(_xlfn.CHOOSECOLS($C$5:$AN$14,MAX(_xlfn._xlws.FILTER(_xlfn.SEQUENCE(1,COLUMNS($C$4:$AN$4)),_xlfn.BYCOL($C$5:$AN$14,_xlfn.LAMBDA(_xlpm.c,COUNT(_xlpm.c)>0))))))),"",INDEX(_xlfn._xlws.SORT(_xlfn._xlws.FILTER(_xlfn.HSTACK($A$5:$A$14,_xlfn.CHOOSECOLS($C$5:$AN$14,MAX(_xlfn._xlws.FILTER(_xlfn.SEQUENCE(1,COLUMNS($C$4:$AN$4)),_xlfn.BYCOL($C$5:$AN$14,_xlfn.LAMBDA(_xlpm.c,COUNT(_xlpm.c)>0)))))),ISNUMBER(_xlfn.CHOOSECOLS($C$5:$AN$14,MAX(_xlfn._xlws.FILTER(_xlfn.SEQUENCE(1,COLUMNS($C$4:$AN$4)),_xlfn.BYCOL($C$5:$AN$14,_xlfn.LAMBDA(_xlpm.c,COUNT(_xlpm.c)>0))))))),2,-1),ROWS($A$40:A49),1)))} -> Evacuo Kaka Toni | B49: {=IF(COUNT($C$5:$AN$14)=0,"",IF(ROWS($A$40:A49)>SUMPRODUCT(--ISNUMBER(_xlfn.CHOOSECOLS($C$5:$AN$14,MAX(_xlfn._xlws.FILTER(_xlfn.SEQUENCE(1,COLUMNS($C$4:$AN$4)),_xlfn.BYCOL($C$5:$AN$14,_xlfn.LAMBDA(_xlpm.c,COUNT(_xlpm.c)>0))))))),"",INDEX(_xlfn._xlws.SORT(_xlfn._xlws.FILTER(_xlfn.HSTACK($A$5:$A$14,_xlfn.CHOOSECOLS($C$5:$AN$14,MAX(_xlfn._xlws.FILTER(_xlfn.SEQUENCE(1,COLUMNS($C$4:$AN$4)),_xlfn.BYCOL($C$5:$AN$14,_xlfn.LAMBDA(_xlpm.c,COUNT(_xlpm.c)>0)))))),ISNUMBER(_xlfn.CHOOSECOLS($C$5:$AN$14,MAX(_xlfn._xlws.FILTER(_xlfn.SEQUENCE(1,COLUMNS($C$4:$AN$4)),_xlfn.BYCOL($C$5:$AN$14,_xlfn.LAMBDA(_xlpm.c,COUNT(_xlpm.c)>0))))))),2,-1),ROWS($A$40:A49),2)))} -> 173.9

Sheet Analisi FM
A1: Analisi FM - Crediti spesi per punto Bonus
A2: Rapporto tra crediti spesi all'asta (foglio Spesa Asta) e BonusMalus dei voti utili (foglio Analisi Bonus), per squadra e ruolo. Portieri: si usa il valore assoluto del BonusMalus (piu' alto = meglio). Totale: solo Difensori, Centrocampisti e Attaccanti.
A4: Squadra | B4: Portieri | C4: Difensori | D4: Centrocampisti | E4: Attaccanti | F4: Totale
A5: ='Spesa Asta'!A5 -> Evacuo Kaka Toni | B5: =IF(N('Analisi Bonus'!B5)=0,"n.d.",'Spesa Asta'!B5/ABS('Analisi Bonus'!B5)) -> 8.8571429 | C5: =IF(N('Analisi Bonus'!C5)=0,"n.d.",'Spesa Asta'!C5/'Analisi Bonus'!C5) -> 5.4 | D5: =IF(N('Analisi Bonus'!D5)=0,"n.d.",'Spesa Asta'!D5/'Analisi Bonus'!D5) -> 20 | E5: =IF(N('Analisi Bonus'!E5)=0,"n.d.",'Spesa Asta'!E5/'Analisi Bonus'!E5) -> 39.714286 | F5: =IF(N('Analisi Bonus'!C5)+N('Analisi Bonus'!D5)+N('Analisi Bonus'!E5)=0,"n.d.",('Spesa Asta'!C5+'Spesa Asta'!D5+'Spesa Asta'!E5)/('Analisi Bonus'!C5+'Analisi Bonus'!D5+'Analisi Bonus'!E5)) -> 16.418605
A6: ='Spesa Asta'!A6 -> GC21 | B6: =IF(N('Analisi Bonus'!B6)=0,"n.d.",'Spesa Asta'!B6/ABS('Analisi Bonus'!B6)) -> 1.6666667 | C6: =IF(N('Analisi Bonus'!C6)=0,"n.d.",'Spesa Asta'!C6/'Analisi Bonus'!C6) -> 9.6 | D6: =IF(N('Analisi Bonus'!D6)=0,"n.d.",'Spesa Asta'!D6/'Analisi Bonus'!D6) -> 13.913043 | E6: =IF(N('Analisi Bonus'!E6)=0,"n.d.",'Spesa Asta'!E6/'Analisi Bonus'!E6) -> 11.090909 | F6: =IF(N('Analisi Bonus'!C6)+N('Analisi Bonus'!D6)+N('Analisi Bonus'!E6)=0,"n.d.",('Spesa Asta'!C6+'Spesa Asta'!D6+'Spesa Asta'!E6)/('Analisi Bonus'!C6+'Analisi Bonus'!D6+'Analisi Bonus'!E6)) -> 11.690141
A7: ='Spesa Asta'!A7 -> I Bamboli | B7: =IF(N('Analisi Bonus'!B7)=0,"n.d.",'Spesa Asta'!B7/ABS('Analisi Bonus'!B7)) -> 3.3913043 | C7: =IF(N('Analisi Bonus'!C7)=0,"n.d.",'Spesa Asta'!C7/'Analisi Bonus'!C7) -> 14 | D7: =IF(N('Analisi Bonus'!D7)=0,"n.d.",'Spesa Asta'!D7/'Analisi Bonus'!D7) -> 5.4893617 | E7: =IF(N('Analisi Bonus'!E7)=0,"n.d.",'Spesa Asta'!E7/'Analisi Bonus'!E7) -> 13.481481 | F7: =IF(N('Analisi Bonus'!C7)+N('Analisi Bonus'!D7)+N('Analisi Bonus'!E7)=0,"n.d.",('Spesa Asta'!C7+'Spesa Asta'!D7+'Spesa Asta'!E7)/('Analisi Bonus'!C7+'Analisi Bonus'!D7+'Analisi Bonus'!E7)) -> 9.0120482
A8: ='Spesa Asta'!A8 -> Incontro al capitano | B8: =IF(N('Analisi Bonus'!B8)=0,"n.d.",'Spesa Asta'!B8/ABS('Analisi Bonus'!B8)) -> 16.25 | C8: =IF(N('Analisi Bonus'!C8)=0,"n.d.",'Spesa Asta'!C8/'Analisi Bonus'!C8) -> 14.714286 | D8: =IF(N('Analisi Bonus'!D8)=0,"n.d.",'Spesa Asta'!D8/'Analisi Bonus'!D8) -> 24 | E8: =IF(N('Analisi Bonus'!E8)=0,"n.d.",'Spesa Asta'!E8/'Analisi Bonus'!E8) -> 37.333333 | F8: =IF(N('Analisi Bonus'!C8)+N('Analisi Bonus'!D8)+N('Analisi Bonus'!E8)=0,"n.d.",('Spesa Asta'!C8+'Spesa Asta'!D8+'Spesa Asta'!E8)/('Analisi Bonus'!C8+'Analisi Bonus'!D8+'Analisi Bonus'!E8)) -> 22.4375
A9: ='Spesa Asta'!A9 -> Mancinix | B9: =IF(N('Analisi Bonus'!B9)=0,"n.d.",'Spesa Asta'!B9/ABS('Analisi Bonus'!B9)) -> 8.3076923 | C9: =IF(N('Analisi Bonus'!C9)=0,"n.d.",'Spesa Asta'!C9/'Analisi Bonus'!C9) -> -144 | D9: =IF(N('Analisi Bonus'!D9)=0,"n.d.",'Spesa Asta'!D9/'Analisi Bonus'!D9) -> 17.529412 | E9: =IF(N('Analisi Bonus'!E9)=0,"n.d.",'Spesa Asta'!E9/'Analisi Bonus'!E9) -> 7.8461538 | F9: =IF(N('Analisi Bonus'!C9)+N('Analisi Bonus'!D9)+N('Analisi Bonus'!E9)=0,"n.d.",('Spesa Asta'!C9+'Spesa Asta'!D9+'Spesa Asta'!E9)/('Analisi Bonus'!C9+'Analisi Bonus'!D9+'Analisi Bonus'!E9)) -> 13.6
A10: ='Spesa Asta'!A10 -> Masterchef FC | B10: =IF(N('Analisi Bonus'!B10)=0,"n.d.",'Spesa Asta'!B10/ABS('Analisi Bonus'!B10)) -> 2.7142857 | C10: =IF(N('Analisi Bonus'!C10)=0,"n.d.",'Spesa Asta'!C10/'Analisi Bonus'!C10) -> 6.25 | D10: =IF(N('Analisi Bonus'!D10)=0,"n.d.",'Spesa Asta'!D10/'Analisi Bonus'!D10) -> 9.2413793 | E10: =IF(N('Analisi Bonus'!E10)=0,"n.d.",'Spesa Asta'!E10/'Analisi Bonus'!E10) -> 16.214286 | F10: =IF(N('Analisi Bonus'!C10)+N('Analisi Bonus'!D10)+N('Analisi Bonus'!E10)=0,"n.d.",('Spesa Asta'!C10+'Spesa Asta'!D10+'Spesa Asta'!E10)/('Analisi Bonus'!C10+'Analisi Bonus'!D10+'Analisi Bonus'!E10)) -> 11.260274
A11: ='Spesa Asta'!A11 -> Outletico Palermo | B11: =IF(N('Analisi Bonus'!B11)=0,"n.d.",'Spesa Asta'!B11/ABS('Analisi Bonus'!B11)) -> 60 | C11: =IF(N('Analisi Bonus'!C11)=0,"n.d.",'Spesa Asta'!C11/'Analisi Bonus'!C11) -> 38 | D11: =IF(N('Analisi Bonus'!D11)=0,"n.d.",'Spesa Asta'!D11/'Analisi Bonus'!D11) -> 7.1875 | E11: =IF(N('Analisi Bonus'!E11)=0,"n.d.",'Spesa Asta'!E11/'Analisi Bonus'!E11) -> 12.848485 | F11: =IF(N('Analisi Bonus'!C11)+N('Analisi Bonus'!D11)+N('Analisi Bonus'!E11)=0,"n.d.",('Spesa Asta'!C11+'Spesa Asta'!D11+'Spesa Asta'!E11)/('Analisi Bonus'!C11+'Analisi Bonus'!D11+'Analisi Bonus'!E11)) -> 10.895522
A12: ='Spesa Asta'!A12 -> Paris Saint-Gervasoni | B12: =IF(N('Analisi Bonus'!B12)=0,"n.d.",'Spesa Asta'!B12/ABS('Analisi Bonus'!B12)) -> 8.5 | C12: =IF(N('Analisi Bonus'!C12)=0,"n.d.",'Spesa Asta'!C12/'Analisi Bonus'!C12) -> 5.4285714 | D12: =IF(N('Analisi Bonus'!D12)=0,"n.d.",'Spesa Asta'!D12/'Analisi Bonus'!D12) -> 10.375 | E12: =IF(N('Analisi Bonus'!E12)=0,"n.d.",'Spesa Asta'!E12/'Analisi Bonus'!E12) -> 9.6571429 | F12: =IF(N('Analisi Bonus'!C12)+N('Analisi Bonus'!D12)+N('Analisi Bonus'!E12)=0,"n.d.",('Spesa Asta'!C12+'Spesa Asta'!D12+'Spesa Asta'!E12)/('Analisi Bonus'!C12+'Analisi Bonus'!D12+'Analisi Bonus'!E12)) -> 8.9090909
A13: ='Spesa Asta'!A13 -> Schalke 104 | B13: =IF(N('Analisi Bonus'!B13)=0,"n.d.",'Spesa Asta'!B13/ABS('Analisi Bonus'!B13)) -> 12.666667 | C13: =IF(N('Analisi Bonus'!C13)=0,"n.d.",'Spesa Asta'!C13/'Analisi Bonus'!C13) -> 124 | D13: =IF(N('Analisi Bonus'!D13)=0,"n.d.",'Spesa Asta'!D13/'Analisi Bonus'!D13) -> 10.173913 | E13: =IF(N('Analisi Bonus'!E13)=0,"n.d.",'Spesa Asta'!E13/'Analisi Bonus'!E13) -> 12.933333 | F13: =IF(N('Analisi Bonus'!C13)+N('Analisi Bonus'!D13)+N('Analisi Bonus'!E13)=0,"n.d.",('Spesa Asta'!C13+'Spesa Asta'!D13+'Spesa Asta'!E13)/('Analisi Bonus'!C13+'Analisi Bonus'!D13+'Analisi Bonus'!E13)) -> 13.814815
A14: ='Spesa Asta'!A14 -> SuperGregariana | B14: =IF(N('Analisi Bonus'!B14)=0,"n.d.",'Spesa Asta'!B14/ABS('Analisi Bonus'!B14)) -> 6 | C14: =IF(N('Analisi Bonus'!C14)=0,"n.d.",'Spesa Asta'!C14/'Analisi Bonus'!C14) -> -92 | D14: =IF(N('Analisi Bonus'!D14)=0,"n.d.",'Spesa Asta'!D14/'Analisi Bonus'!D14) -> 20.588235 | E14: =IF(N('Analisi Bonus'!E14)=0,"n.d.",'Spesa Asta'!E14/'Analisi Bonus'!E14) -> 6.1111111 | F14: =IF(N('Analisi Bonus'!C14)+N('Analisi Bonus'!D14)+N('Analisi Bonus'!E14)=0,"n.d.",('Spesa Asta'!C14+'Spesa Asta'!D14+'Spesa Asta'!E14)/('Analisi Bonus'!C14+'Analisi Bonus'!D14+'Analisi Bonus'!E14)) -> 14.784314
A16: Legenda
A17: Ogni cella = crediti spesi all'asta per quel reparto diviso il BonusMalus dei voti utili dello stesso reparto
A18: Difensori/Centrocampisti/Attaccanti: valore positivo = crediti spesi per ogni punto di bonus; piu' e' basso, migliore e' la resa
A19: Valore negativo (in rosso) = il reparto ha prodotto malus complessivi: i crediti spesi non hanno reso nulla
A20: PORTIERI: crediti spesi diviso il VALORE ASSOLUTO del BonusMalus. Per i Portieri piu' il valore e' ALTO, migliore e' il rapporto (i malus del portiere sono quasi inevitabili: a parita' di crediti, meno malus subiti = valore piu' alto). Per tutti gli altri ruoli vale il contrario: piu' e' BASSO, meglio e'.
A21: n.d. = BonusMalus pari a zero, il rapporto non e' calcolabile (divisione per zero)
A22: Totale: somma dei crediti di Difensori + Centrocampisti + Attaccanti diviso la somma dei rispettivi BonusMalus (Portieri esclusi)
A23: I bonus si riferiscono ai soli giocatori con Voto Utile = SI e si aggiornano a ogni nuova giornata
A24: I crediti sono fissi (asta di inizio stagione), quindi il rapporto migliora col progredire del campionato

Sheet VdM
A1: Squadra | B1: Giocatore | C1: Ruolo TM | D1: Nato il | E1: Valore di mercato | F1: Ruolo FG | G1: Mantra | H1: Attivo
A2: AC Milan | B2: Mike Maignan | C2: Portiere | D2: 34765 | E2: 20,00 mln € | F2: P | G2: Por | H2: Sì
A3: AC Milan | B3: Pietro Terracciano | C3: Portiere | D3: 33088 | E3: 900 mila € | F3: P | G3: Por | H3: Sì
A4: AC Milan | B4: Lorenzo Torriani | C4: Portiere | D4: 31/01/2005 | E4: 2,00 mln € | F4: P | G4: Por | H4: Sì
A5: AC Milan | B5: Strahinja Pavlović | C5: Difensore centrale | D5: 24/05/2001 | E5: 40,00 mln € | F5: D | G5: Dc | H5: Sì
A6: AC Milan | B6: Mario Gila | C6: Difensore centrale | D6: 29/08/2000 | E6: 30,00 mln € | F6: D | G6: Dc | H6: Sì
A7: AC Milan | B7: Koni De Winter | C7: Difensore centrale | D7: 37596 | E7: 25,00 mln € | F7: D | G7: Dd;Dc | H7: Sì
A8: AC Milan | B8: Fikayo Tomori | C8: Difensore centrale | D8: 19/12/1997 | E8: 10,00 mln € | F8: D | G8: Dc | H8: Sì
A9: AC Milan | B9: Matteo Gabbia | C9: Difensore centrale | D9: 21/10/1999 | E9: 17,00 mln € | F9: D | G9: Dc | H9: Sì
A10: AC Milan | B10: David Odogu | C10: Difensore centrale | D10: 38782 | E10: 5,00 mln € | H10: No
A11: AC Milan | B11: Filippo Terracciano | C11: Difensore centrale | D11: 37835 | E11: 4,50 mln € | H11: Sì
A12: AC Milan | B12: Sankhoun Diawara | C12: Difensore centrale | D12: 38730 | E12: 2,00 mln € | F12: D | G12: Ds;Dc | H12: Sì
A13: AC Milan | B13: Valeri Vladimirov | C13: Difensore centrale | D13: 39604 | E13: 800 mila € | H13: Sì
A14: AC Milan | B14: Davide Bartesaghi | C14: Terzino sinistro | D14: 29/12/2005 | E14: 22,00 mln € | F14: D | G14: Ds;E | H14: Sì
A15: AC Milan | B15: Pervis Estupiñán | C15: Terzino sinistro | D15: 21/01/1998 | E15: 12,00 mln € | F15: D | G15: Ds;E | H15: Sì
A16: AC Milan | B16: Zachary Athekame | C16: Terzino destro | D16: 13/12/2004 | E16: 15,00 mln € | F16: D | H16: No
A17: AC Milan | B17: Ardon Jashari | C17: Mediano | D17: 30/07/2002 | E17: 22,00 mln € | F17: C | G17: C | H17: Sì
A18: AC Milan | B18: Youssouf Fofana | C18: Mediano | D18: 36434 | E18: 23,00 mln € | F18: C | G18: M;C | H18: No
A19: AC Milan | B19: Samuele Ricci | C19: Mediano | D19: 21/08/2001 | E19: 22,00 mln € | F19: C | G19: M;C | H19: Sì
A20: AC Milan | B20: Ismaël Bennacer | C20: Mediano | D20: 35442 | E20: 8,00 mln € | H20: No
A21: AC Milan | B21: Adrien Rabiot | C21: Centrocampista | D21: 34762 | E21: 18,00 mln € | F21: C | G21: C;T | H21: Sì
A22: AC Milan | B22: Yunus Musah | C22: Centrocampista | D22: 29/11/2002 | E22: 18,00 mln € | F22: C | G22: C;W | H22: Sì
A23: AC Milan | B23: Ruben Loftus-Cheek | C23: Centrocampista | D23: 23/01/1996 | E23: 8,50 mln € | F23: C | G23: C;T | H23: Sì
A24: AC Milan | B24: Warren Bondo | C24: Centrocampista | D24: 15/09/2003 | E24: 4,00 mln € | H24: Sì
A25: AC Milan | B25: Christian Comotto | C25: Centrocampista | D25: 25/04/2008 | E25: 10,00 mln € | H25: Sì
A26: AC Milan | B26: Luka Modric | C26: Centrocampista | D26: 31299 | E26: 3,50 mln € | F26: C | G26: M;C | H26: Sì
A27: AC Milan | B27: Alexis Saelemaekers | C27: Esterno di destra | D27: 27/06/1999 | E27: 18,00 mln € | F27: C | G27: E;W | H27: Sì
A28: AC Milan | B28: Diego Moreira | C28: Esterno di sinistra | D28: 38205 | E28: 45,00 mln € | F28: C | G28: W | H28: Sì
A29: AC Milan | B29: Alphadjo Cissè | C29: Trequartista | D29: 22/10/2006 | E29: 20,00 mln € | H29: Sì
A30: AC Milan | B30: Rafael Leão | C30: Ala sinistra | D30: 36439 | E30: 50,00 mln € | F30: A | G30: A | H30: No
A31: AC Milan | B31: Christian Pulisic | C31: Ala destra | D31: 18/09/1998 | E31: 35,00 mln € | F31: C | G31: T;A | H31: Sì
A32: AC Milan | B32: Omari Hutchinson | C32: Ala destra | D32: 37924 | E32: 30,00 mln € | F32: C | G32: W;A | H32: Sì
A33: AC Milan | B33: Samuel Chukwueze | C33: Ala destra | D33: 22/05/1999 | E33: 20,00 mln € | F33: C | G33: W | H33: Sì
A34: AC Milan | B34: Gonçalo Ramos | C34: Punta centrale | D34: 20/06/2001 | E34: 50,00 mln € | F34: A | G34: Pc | H34: Sì
A35: AC Milan | B35: Christopher Nkunku | C35: Punta centrale | D35: 14/11/1997 | E35: 25,00 mln € | F35: A | G35: A | H35: No
A36: AC Milan | B36: Santiago Gimenez | C36: Punta centrale | D36: 18/04/2001 | E36: 18,00 mln € | F36: A | G36: Pc | H36: No
A37: AC Milan | B37: Francesco Camarda | C37: Punta centrale | D37: 39724 | E37: 15,00 mln € | F37: A | G37: Pc | H37: Sì
A38: AC Monza | B38: Noel Törnqvist | C38: Portiere | D38: 37288 | E38: 2,00 mln € | F38: P | G38: Por | H38: Sì
A39: AC Monza | B39: Demba Thiam | C39: Portiere | D39: 35918 | E39: 2,00 mln € | F39: P | G39: Por | H39: Sì
A40: AC Monza | B40: Semuel Pizzignacco | C40: Portiere | D40: 36900 | E40: 600 mila € | F40: P | G40: Por | H40: No
A41: AC Monza | B41: Aljaz Strajnar | C41: Portiere | D41: 16/08/2007 | E41: 200 mila € | F41: P | G41: Por | H41: Sì
A42: AC Monza | B42: Jan Ziolkowski | C42: Difensore centrale | D42: 38478 | E42: 12,00 mln € | F42: D | G42: Dc | H42: Sì
A43: AC Monza | B43: Saba Goglichidze | C43: Difensore centrale | D43: 25/06/2004 | E43: 3,50 mln € | F43: D | G43: Dd;Dc | H43: Sì
A44: AC Monza | B44: Lorenzo Lucchesi | C44: Difensore centrale | D44: 37869 | E44: 3,30 mln € | F44: D | G44: Dc | H44: Sì
A45: AC Monza | B45: Andrea Carboni | C45: Difensore centrale | D45: 36983 | E45: 3,00 mln € | F45: D | G45: Ds;Dc | H45: Sì
A46: AC Monza | B46: Eddy Kouadio | C46: Difensore centrale | D46: 38903 | E46: 6,00 mln € | F46: D | G46: Dd;Dc | H46: Sì
A47: AC Monza | B47: Luca Ravanelli | C47: Difensore centrale | D47: 35582 | E47: 1,80 mln € | H47: No
A48: AC Monza | B48: Valentin Antov | C48: Difensore centrale | D48: 36780 | E48: 1,50 mln € | F48: D | G48: Dc | H48: Sì
A49: AC Monza | B49: Filippo Delli Carri | C49: Difensore centrale | D49: 36224 | E49: 1,50 mln € | F49: D | G49: Dc | H49: No
A50: AC Monza | B50: Yvan Maye | C50: Difensore centrale | D50: 38797 | E50: 1,50 mln € | F50: D | G50: Ds;Dc | H50: Sì
A51: AC Monza | B51: Arvid Brorsson | C51: Difensore centrale | D51: 36377 | E51: 400 mila € | H51: No
A52: AC Monza | B52: Samuele Capolupo | C52: Terzino sinistro | D52: 38933 | E52: 250 mila € | H52: No
A53: AC Monza | B53: Ricardo Mangas | C53: Terzino sinistro | D53: 35873 | E53: 400 mila € | F53: D | G53: Ds;E | H53: Sì
A54: AC Monza | B54: Samuele Birindelli | C54: Terzino destro | D54: 19/07/1999 | E54: 2,50 mln € | F54: D | G54: Dd;Ds;E | H54: Sì
A55: AC Monza | B55: Adam Bakoune | C55: Terzino destro | D55: 38870 | E55: 2,00 mln € | F55: D | G55: Dd;E | H55: Sì
A56: AC Monza | B56: Leonardo Colombo | C56: Mediano | D56: 38448 | E56: 4,00 mln € | F56: C | G56: M;C | H56: Sì
A57: AC Monza | B57: Ebenezer Akinsanmiro | C57: Centrocampista | D57: 25/11/2004 | E57: 7,00 mln € | F57: C | G57: C | H57: Sì
A58: AC Monza | B58: Michael Folorunsho | C58: Centrocampista | D58: 35978 | E58: 5,00 mln € | F58: C | G58: C;T | H58: Sì
A59: AC Monza | B59: Matteo Pessina | C59: Centrocampista | D59: 21/04/1997 | E59: 5,00 mln € | F59: C | G59: M;C | H59: Sì
A60: AC Monza | B60: Alessandro Berretta | C60: Centrocampista | D60: 38724 | E60: 400 mila € | H60: No
A61: AC Monza | B61: Pedro Obiang | C61: Centrocampista | D61: 27/03/1992 | E61: 350 mila € | H61: Sì
A62: AC Monza | B62: Idrissa Touré | C62: Esterno di destra | D62: 35914 | E62: 4,00 mln € | F62: C | G62: E;M | H62: Sì
A63: AC Monza | B63: Patrick Ciurria | C63: Esterno di destra | D63: 34944 | E63: 1,00 mln € | F63: C | G63: E;W | H63: Sì
A64: AC Monza | B64: Paulo Azzi | C64: Esterno di sinistra | D64: 15/07/1994 | E64: 800 mila € | H64: No
A65: AC Monza | B65: Andrea Colpani | C65: Trequartista | D65: 36469 | E65: 4,00 mln € | F65: C | G65: T | H65: Sì
A66: AC Monza | B66: Foe Ondoa | C66: Trequartista | D66: 38698 | E66: 1,50 mln € | H66: Sì
A67: AC Monza | B67: Nicolas Galazzi | C67: Trequartista | D67: 18/12/2000 | E67: 750 mila € | H67: No
A68: AC Monza | B68: Jay Robinson | C68: Ala sinistra | D68: 39156 | E68: 8,00 mln € | F68: A | G68: A | H68: Sì
A69: AC Monza | B69: Keita Baldé | C69: Ala sinistra | D69: 34914 | E69: 800 mila € | H69: Sì
A70: AC Monza | B70: Exequiel Zeballos | C70: Ala destra | D70: 37370 | E70: 7,00 mln € | F70: A | G70: A | H70: Sì
A71: AC Monza | B71: Cyril Ngonge | C71: Ala destra | D71: 26/05/2000 | E71: 7,00 mln € | F71: A | G71: A | H71: Sì
A72: AC Monza | B72: Omari Forson | C72: Ala destra | D72: 20/07/2004 | E72: 2,50 mln € | H72: Sì
A73: AC Monza | B73: Kevin Martins | C73: Ala destra | D73: 31/01/2005 | E73: 400 mila € | H73: Sì
A74: AC Monza | B74: Patrick Cutrone | C74: Punta centrale | D74: 35855 | E74: 4,00 mln € | F74: A | G74: Pc | H74: Sì
A75: AC Monza | B75: Gustavo Varela | C75: Punta centrale | D75: 38382 | E75: 5,00 mln € | F75: A | G75: Pc | H75: Sì
A76: AC Monza | B76: Dany Mota | C76: Punta centrale | D76: 35831 | E76: 2,80 mln € | F76: A | G76: A | H76: Sì
A77: AC Monza | B77: Andrea Petagna | C77: Punta centrale | D77: 30/06/1995 | E77: 700 mila € | F77: A | G77: Pc | H77: No
A78: AC Monza | B78: Solomon Loubao | C78: Punta centrale | D78: 38423 | E78: 300 mila € | H78: No
A79: ACF Fiorentina | B79: David de Gea | C79: Portiere | D79: 33065 | E79: 3,50 mln € | F79: P | G79: Por | H79: Sì
A80: ACF Fiorentina | B80: Oliver Christensen | C80: Portiere | D80: 22/03/1999 | E80: 1,40 mln € | F80: P | G80: Por | H80: Sì
A81: ACF Fiorentina | B81: Tommaso Vannucchi | C81: Portiere | D81: 39205 | E81: 500 mila € | H81: Sì
A82: ACF Fiorentina | B82: Luca Lezzerini | C82: Portiere | D82: 24/03/1995 | E82: 350 mila € | F82: P | G82: Por | H82: Sì
A83: ACF Fiorentina | B83: Radu Drăgușin | C83: Difensore centrale | D83: 37317 | E83: 16,00 mln € | F83: D | G83: Dc | H83: Sì
A84: ACF Fiorentina | B84: Marin Pongracic | C84: Difensore centrale | D84: 35743 | E84: 6,50 mln € | F84: D | G84: Dc | H84: Sì
A85: ACF Fiorentina | B85: Viery | C85: Difensore centrale | D85: 38384 | E85: 12,00 mln € | F85: D | G85: Ds;Dc | H85: Sì
A86: ACF Fiorentina | B86: Víctor Valdepeñas | C86: Difensore centrale | D86: 39010 | E86: 12,00 mln € | F86: D | G86: Ds;Dc | H86: Sì
A87: ACF Fiorentina | B87: Matías Moreno | C87: Difensore centrale | D87: 24/09/2003 | E87: 6,00 mln € | H87: No
A88: ACF Fiorentina | B88: Luca Ranieri | C88: Difensore centrale | D88: 23/04/1999 | E88: 6,00 mln € | F88: D | G88: Ds;Dc | H88: Sì
A89: ACF Fiorentina | B89: Nicolás Valentini | C89: Difensore centrale | D89: 37046 | E89: 3,00 mln € | H89: No
A90: ACF Fiorentina | B90: Eman Košpo | C90: Difensore centrale | D90: 17/05/2007 | E90: 1,50 mln € | H90: No
A91: ACF Fiorentina | B91: Niccolò Fortini | C91: Terzino sinistro | D91: 13/02/2006 | E91: 10,00 mln € | H91: No
A92: ACF Fiorentina | B92: Fabiano Parisi | C92: Terzino sinistro | D92: 36780 | E92: 6,00 mln € | F92: D | G92: Ds;E | H92: Sì
A93: ACF Fiorentina | B93: Robin Gosens | C93: Terzino sinistro | D93: 34461 | E93: 4,00 mln € | H93: No
A94: ACF Fiorentina | B94: Luis Balbo | C94: Terzino sinistro | D94: 28/03/2006 | E94: 3,00 mln € | H94: No
A95: ACF Fiorentina | B95: Álex Jiménez | C95: Terzino destro | D95: 38480 | E95: 22,00 mln € | F95: D | G95: Dd;Ds;E | H95: Sì
A96: ACF Fiorentina | B96: Dodô | C96: Terzino destro | D96: 17/11/1998 | E96: 16,00 mln € | F96: D | G96: Dd;E | H96: Sì
A97: ACF Fiorentina | B97: João Mário | C97: Terzino destro | D97: 36528 | E97: 8,00 mln € | F97: D | G97: Dd;E | H97: Sì
A98: ACF Fiorentina | B98: Rolando Mandragora | C98: Mediano | D98: 29/06/1997 | E98: 9,00 mln € | F98: C | G98: C | H98: No
A99: ACF Fiorentina | B99: Lapo Deli | C99: Mediano | D99: 38832 | E99: 250 mila € | H99: Sì
A100: ACF Fiorentina | B100: Christ Inao Oulaï | C100: Centrocampista | D100: 38813 | E100: 28,00 mln € | F100: C | G100: M;C | H100: Sì
...

Sheet Mappatura
A1: Mappatura Giocatori Database → VdM Inizio stagione
A2: Colonna C = nome completo esatto del foglio VdM. Per nuovi giocatori aggiungi una riga in fondo alla tabella Mappa.
A4: Giocatore_DB | B4: Ruolo_DB | C4: Giocatore_VdM | D4: Stato | E4: VdM (mln €) | G4: Da mappare / problematici: | H4: =COUNTIF(Mappa[Stato],"DA MAPPARE")+COUNTIF(Mappa[Stato],"AMBIGUO")+COUNTIF(Mappa[Stato],"NOME VdM ERRATO") -> 0
A5: Adams A. | B5: A | C5: Akor Adams | D5: {=IF(Mappa[[#This Row],[Giocatore_VdM]]="","DA MAPPARE",_xlfn.LET(_xlpm.e,EXACT(VdM!$B$2:$B$834,Mappa[[#This Row],[Giocatore_VdM]]),_xlpm.tot,SUMPRODUCT(--_xlpm.e),_xlpm.att,SUMPRODUCT(--_xlpm.e,--(VdM!$H$2:$H$834="Sì")),IF(_xlpm.tot=0,"NOME VdM ERRATO",IF(_xlpm.att=1,"OK",IF(_xlpm.att>1,"AMBIGUO",IF(_xlpm.tot=1,"OK (non attivo)","AMBIGUO"))))))} -> OK | E5: {=IF(OR(Mappa[[#This Row],[Stato]]="DA MAPPARE",Mappa[[#This Row],[Stato]]="NOME VdM ERRATO",Mappa[[#This Row],[Stato]]="AMBIGUO"),Mappa[[#This Row],[Stato]],_xlfn.LET(_xlpm.e,EXACT(VdM!$B$2:$B$834,Mappa[[#This Row],[Giocatore_VdM]]),_xlpm.a,IF(SUMPRODUCT(--_xlpm.e,--(VdM!$H$2:$H$834="Sì"))=1,MATCH(TRUE,(_xlpm.e)*(VdM!$H$2:$H$834="Sì")=1,0),MATCH(TRUE,_xlpm.e,0)),_xlpm.t,INDEX(VdM!$E$2:$E$834,_xlpm.a),_xlpm.k,ISNUMBER(SEARCH("mila",_xlpm.t)),_xlpm.v,IFERROR(VALUE(TRIM(LEFT(_xlpm.t,SEARCH(IF(_xlpm.k,"mila","mln"),_xlpm.t)-1))),"X"),IFERROR(IF(_xlpm.k,_xlpm.v/1000,_xlpm.v+0),"NON TROVATO")))} -> 15
A6: Adams C. | B6: A | C6: Ché Adams | D6: {=IF(Mappa[[#This Row],[Giocatore_VdM]]="","DA MAPPARE",_xlfn.LET(_xlpm.e,EXACT(VdM!$B$2:$B$834,Mappa[[#This Row],[Giocatore_VdM]]),_xlpm.tot,SUMPRODUCT(--_xlpm.e),_xlpm.att,SUMPRODUCT(--_xlpm.e,--(VdM!$H$2:$H$834="Sì")),IF(_xlpm.tot=0,"NOME VdM ERRATO",IF(_xlpm.att=1,"OK",IF(_xlpm.att>1,"AMBIGUO",IF(_xlpm.tot=1,"OK (non attivo)","AMBIGUO"))))))} -> OK | E6: {=IF(OR(Mappa[[#This Row],[Stato]]="DA MAPPARE",Mappa[[#This Row],[Stato]]="NOME VdM ERRATO",Mappa[[#This Row],[Stato]]="AMBIGUO"),Mappa[[#This Row],[Stato]],_xlfn.LET(_xlpm.e,EXACT(VdM!$B$2:$B$834,Mappa[[#This Row],[Giocatore_VdM]]),_xlpm.a,IF(SUMPRODUCT(--_xlpm.e,--(VdM!$H$2:$H$834="Sì"))=1,MATCH(TRUE,(_xlpm.e)*(VdM!$H$2:$H$834="Sì")=1,0),MATCH(TRUE,_xlpm.e,0)),_xlpm.t,INDEX(VdM!$E$2:$E$834,_xlpm.a),_xlpm.k,ISNUMBER(SEARCH("mila",_xlpm.t)),_xlpm.v,IFERROR(VALUE(TRIM(LEFT(_xlpm.t,SEARCH(IF(_xlpm.k,"mila","mln"),_xlpm.t)-1))),"X"),IFERROR(IF(_xlpm.k,_xlpm.v/1000,_xlpm.v+0),"NON TROVATO")))} -> 5 | G6: Legenda Stato:
A7: Adzic | B7: C | C7: Vasilije Adžić | D7: {=IF(Mappa[[#This Row],[Giocatore_VdM]]="","DA MAPPARE",_xlfn.LET(_xlpm.e,EXACT(VdM!$B$2:$B$834,Mappa[[#This Row],[Giocatore_VdM]]),_xlpm.tot,SUMPRODUCT(--_xlpm.e),_xlpm.att,SUMPRODUCT(--_xlpm.e,--(VdM!$H$2:$H$834="Sì")),IF(_xlpm.tot=0,"NOME VdM ERRATO",IF(_xlpm.att=1,"OK",IF(_xlpm.att>1,"AMBIGUO",IF(_xlpm.tot=1,"OK (non attivo)","AMBIGUO"))))))} -> OK | E7: {=IF(OR(Mappa[[#This Row],[Stato]]="DA MAPPARE",Mappa[[#This Row],[Stato]]="NOME VdM ERRATO",Mappa[[#This Row],[Stato]]="AMBIGUO"),Mappa[[#This Row],[Stato]],_xlfn.LET(_xlpm.e,EXACT(VdM!$B$2:$B$834,Mappa[[#This Row],[Giocatore_VdM]]),_xlpm.a,IF(SUMPRODUCT(--_xlpm.e,--(VdM!$H$2:$H$834="Sì"))=1,MATCH(TRUE,(_xlpm.e)*(VdM!$H$2:$H$834="Sì")=1,0),MATCH(TRUE,_xlpm.e,0)),_xlpm.t,INDEX(VdM!$E$2:$E$834,_xlpm.a),_xlpm.k,ISNUMBER(SEARCH("mila",_xlpm.t)),_xlpm.v,IFERROR(VALUE(TRIM(LEFT(_xlpm.t,SEARCH(IF(_xlpm.k,"mila","mln"),_xlpm.t)-1))),"X"),IFERROR(IF(_xlpm.k,_xlpm.v/1000,_xlpm.v+0),"NON TROVATO")))} -> 15 | G7: OK = corrispondenza univoca con giocatore attivo
A8: Akanji | B8: D | C8: Manuel Akanji | D8: {=IF(Mappa[[#This Row],[Giocatore_VdM]]="","DA MAPPARE",_xlfn.LET(_xlpm.e,EXACT(VdM!$B$2:$B$834,Mappa[[#This Row],[Giocatore_VdM]]),_xlpm.tot,SUMPRODUCT(--_xlpm.e),_xlpm.att,SUMPRODUCT(--_xlpm.e,--(VdM!$H$2:$H$834="Sì")),IF(_xlpm.tot=0,"NOME VdM ERRATO",IF(_xlpm.att=1,"OK",IF(_xlpm.att>1,"AMBIGUO",IF(_xlpm.tot=1,"OK (non attivo)","AMBIGUO"))))))} -> OK | E8: {=IF(OR(Mappa[[#This Row],[Stato]]="DA MAPPARE",Mappa[[#This Row],[Stato]]="NOME VdM ERRATO",Mappa[[#This Row],[Stato]]="AMBIGUO"),Mappa[[#This Row],[Stato]],_xlfn.LET(_xlpm.e,EXACT(VdM!$B$2:$B$834,Mappa[[#This Row],[Giocatore_VdM]]),_xlpm.a,IF(SUMPRODUCT(--_xlpm.e,--(VdM!$H$2:$H$834="Sì"))=1,MATCH(TRUE,(_xlpm.e)*(VdM!$H$2:$H$834="Sì")=1,0),MATCH(TRUE,_xlpm.e,0)),_xlpm.t,INDEX(VdM!$E$2:$E$834,_xlpm.a),_xlpm.k,ISNUMBER(SEARCH("mila",_xlpm.t)),_xlpm.v,IFERROR(VALUE(TRIM(LEFT(_xlpm.t,SEARCH(IF(_xlpm.k,"mila","mln"),_xlpm.t)-1))),"X"),IFERROR(IF(_xlpm.k,_xlpm.v/1000,_xlpm.v+0),"NON TROVATO")))} -> 17 | G8: OK (non attivo) = unica corrispondenza, giocatore con Attivo = No
A9: Alajbegovic | B9: C | C9: Kerim Alajbegovic | D9: {=IF(Mappa[[#This Row],[Giocatore_VdM]]="","DA MAPPARE",_xlfn.LET(_xlpm.e,EXACT(VdM!$B$2:$B$834,Mappa[[#This Row],[Giocatore_VdM]]),_xlpm.tot,SUMPRODUCT(--_xlpm.e),_xlpm.att,SUMPRODUCT(--_xlpm.e,--(VdM!$H$2:$H$834="Sì")),IF(_xlpm.tot=0,"NOME VdM ERRATO",IF(_xlpm.att=1,"OK",IF(_xlpm.att>1,"AMBIGUO",IF(_xlpm.tot=1,"OK (non attivo)","AMBIGUO"))))))} -> OK | E9: {=IF(OR(Mappa[[#This Row],[Stato]]="DA MAPPARE",Mappa[[#This Row],[Stato]]="NOME VdM ERRATO",Mappa[[#This Row],[Stato]]="AMBIGUO"),Mappa[[#This Row],[Stato]],_xlfn.LET(_xlpm.e,EXACT(VdM!$B$2:$B$834,Mappa[[#This Row],[Giocatore_VdM]]),_xlpm.a,IF(SUMPRODUCT(--_xlpm.e,--(VdM!$H$2:$H$834="Sì"))=1,MATCH(TRUE,(_xlpm.e)*(VdM!$H$2:$H$834="Sì")=1,0),MATCH(TRUE,_xlpm.e,0)),_xlpm.t,INDEX(VdM!$E$2:$E$834,_xlpm.a),_xlpm.k,ISNUMBER(SEARCH("mila",_xlpm.t)),_xlpm.v,IFERROR(VALUE(TRIM(LEFT(_xlpm.t,SEARCH(IF(_xlpm.k,"mila","mln"),_xlpm.t)-1))),"X"),IFERROR(IF(_xlpm.k,_xlpm.v/1000,_xlpm.v+0),"NON TROVATO")))} -> 32 | G9: DA MAPPARE = colonna C vuota, inserisci il nome VdM
A10: Albarracin | B10: A | C10: Agustín Albarracín | D10: {=IF(Mappa[[#This Row],[Giocatore_VdM]]="","DA MAPPARE",_xlfn.LET(_xlpm.e,EXACT(VdM!$B$2:$B$834,Mappa[[#This Row],[Giocatore_VdM]]),_xlpm.tot,SUMPRODUCT(--_xlpm.e),_xlpm.att,SUMPRODUCT(--_xlpm.e,--(VdM!$H$2:$H$834="Sì")),IF(_xlpm.tot=0,"NOME VdM ERRATO",IF(_xlpm.att=1,"OK",IF(_xlpm.att>1,"AMBIGUO",IF(_xlpm.tot=1,"OK (non attivo)","AMBIGUO"))))))} -> OK (non attivo) | E10: {=IF(OR(Mappa[[#This Row],[Stato]]="DA MAPPARE",Mappa[[#This Row],[Stato]]="NOME VdM ERRATO",Mappa[[#This Row],[Stato]]="AMBIGUO"),Mappa[[#This Row],[Stato]],_xlfn.LET(_xlpm.e,EXACT(VdM!$B$2:$B$834,Mappa[[#This Row],[Giocatore_VdM]]),_xlpm.a,IF(SUMPRODUCT(--_xlpm.e,--(VdM!$H$2:$H$834="Sì"))=1,MATCH(TRUE,(_xlpm.e)*(VdM!$H$2:$H$834="Sì")=1,0),MATCH(TRUE,_xlpm.e,0)),_xlpm.t,INDEX(VdM!$E$2:$E$834,_xlpm.a),_xlpm.k,ISNUMBER(SEARCH("mila",_xlpm.t)),_xlpm.v,IFERROR(VALUE(TRIM(LEFT(_xlpm.t,SEARCH(IF(_xlpm.k,"mila","mln"),_xlpm.t)-1))),"X"),IFERROR(IF(_xlpm.k,_xlpm.v/1000,_xlpm.v+0),"NON TROVATO")))} -> 2.3 | G10: AMBIGUO = più giocatori attivi con lo stesso nome nel foglio VdM
A11: Atta | B11: C | C11: Arthur Atta | D11: {=IF(Mappa[[#This Row],[Giocatore_VdM]]="","DA MAPPARE",_xlfn.LET(_xlpm.e,EXACT(VdM!$B$2:$B$834,Mappa[[#This Row],[Giocatore_VdM]]),_xlpm.tot,SUMPRODUCT(--_xlpm.e),_xlpm.att,SUMPRODUCT(--_xlpm.e,--(VdM!$H$2:$H$834="Sì")),IF(_xlpm.tot=0,"NOME VdM ERRATO",IF(_xlpm.att=1,"OK",IF(_xlpm.att>1,"AMBIGUO",IF(_xlpm.tot=1,"OK (non attivo)","AMBIGUO"))))))} -> OK | E11: {=IF(OR(Mappa[[#This Row],[Stato]]="DA MAPPARE",Mappa[[#This Row],[Stato]]="NOME VdM ERRATO",Mappa[[#This Row],[Stato]]="AMBIGUO"),Mappa[[#This Row],[Stato]],_xlfn.LET(_xlpm.e,EXACT(VdM!$B$2:$B$834,Mappa[[#This Row],[Giocatore_VdM]]),_xlpm.a,IF(SUMPRODUCT(--_xlpm.e,--(VdM!$H$2:$H$834="Sì"))=1,MATCH(TRUE,(_xlpm.e)*(VdM!$H$2:$H$834="Sì")=1,0),MATCH(TRUE,_xlpm.e,0)),_xlpm.t,INDEX(VdM!$E$2:$E$834,_xlpm.a),_xlpm.k,ISNUMBER(SEARCH("mila",_xlpm.t)),_xlpm.v,IFERROR(VALUE(TRIM(LEFT(_xlpm.t,SEARCH(IF(_xlpm.k,"mila","mln"),_xlpm.t)-1))),"X"),IFERROR(IF(_xlpm.k,_xlpm.v/1000,_xlpm.v+0),"NON TROVATO")))} -> 25 | G11: NOME VdM ERRATO = il nome in colonna C non esiste nel foglio VdM
A12: Baldanzi | B12: C | C12: Tommaso Baldanzi | D12: {=IF(Mappa[[#This Row],[Giocatore_VdM]]="","DA MAPPARE",_xlfn.LET(_xlpm.e,EXACT(VdM!$B$2:$B$834,Mappa[[#This Row],[Giocatore_VdM]]),_xlpm.tot,SUMPRODUCT(--_xlpm.e),_xlpm.att,SUMPRODUCT(--_xlpm.e,--(VdM!$H$2:$H$834="Sì")),IF(_xlpm.tot=0,"NOME VdM ERRATO",IF(_xlpm.att=1,"OK",IF(_xlpm.att>1,"AMBIGUO",IF(_xlpm.tot=1,"OK (non attivo)","AMBIGUO"))))))} -> OK | E12: {=IF(OR(Mappa[[#This Row],[Stato]]="DA MAPPARE",Mappa[[#This Row],[Stato]]="NOME VdM ERRATO",Mappa[[#This Row],[Stato]]="AMBIGUO"),Mappa[[#This Row],[Stato]],_xlfn.LET(_xlpm.e,EXACT(VdM!$B$2:$B$834,Mappa[[#This Row],[Giocatore_VdM]]),_xlpm.a,IF(SUMPRODUCT(--_xlpm.e,--(VdM!$H$2:$H$834="Sì"))=1,MATCH(TRUE,(_xlpm.e)*(VdM!$H$2:$H$834="Sì")=1,0),MATCH(TRUE,_xlpm.e,0)),_xlpm.t,INDEX(VdM!$E$2:$E$834,_xlpm.a),_xlpm.k,ISNUMBER(SEARCH("mila",_xlpm.t)),_xlpm.v,IFERROR(VALUE(TRIM(LEFT(_xlpm.t,SEARCH(IF(_xlpm.k,"mila","mln"),_xlpm.t)-1))),"X"),IFERROR(IF(_xlpm.k,_xlpm.v/1000,_xlpm.v+0),"NON TROVATO")))} -> 8.5
A13: Barella | B13: C | C13: Nicolò Barella | D13: {=IF(Mappa[[#This Row],[Giocatore_VdM]]="","DA MAPPARE",_xlfn.LET(_xlpm.e,EXACT(VdM!$B$2:$B$834,Mappa[[#This Row],[Giocatore_VdM]]),_xlpm.tot,SUMPRODUCT(--_xlpm.e),_xlpm.att,SUMPRODUCT(--_xlpm.e,--(VdM!$H$2:$H$834="Sì")),IF(_xlpm.tot=0,"NOME VdM ERRATO",IF(_xlpm.att=1,"OK",IF(_xlpm.att>1,"AMBIGUO",IF(_xlpm.tot=1,"OK (non attivo)","AMBIGUO"))))))} -> OK | E13: {=IF(OR(Mappa[[#This Row],[Stato]]="DA MAPPARE",Mappa[[#This Row],[Stato]]="NOME VdM ERRATO",Mappa[[#This Row],[Stato]]="AMBIGUO"),Mappa[[#This Row],[Stato]],_xlfn.LET(_xlpm.e,EXACT(VdM!$B$2:$B$834,Mappa[[#This Row],[Giocatore_VdM]]),_xlpm.a,IF(SUMPRODUCT(--_xlpm.e,--(VdM!$H$2:$H$834="Sì"))=1,MATCH(TRUE,(_xlpm.e)*(VdM!$H$2:$H$834="Sì")=1,0),MATCH(TRUE,_xlpm.e,0)),_xlpm.t,INDEX(VdM!$E$2:$E$834,_xlpm.a),_xlpm.k,ISNUMBER(SEARCH("mila",_xlpm.t)),_xlpm.v,IFERROR(VALUE(TRIM(LEFT(_xlpm.t,SEARCH(IF(_xlpm.k,"mila","mln"),_xlpm.t)-1))),"X"),IFERROR(IF(_xlpm.k,_xlpm.v/1000,_xlpm.v+0),"NON TROVATO")))} -> 50
A14: Bartesaghi | B14: D | C14: Davide Bartesaghi | D14: {=IF(Mappa[[#This Row],[Giocatore_VdM]]="","DA MAPPARE",_xlfn.LET(_xlpm.e,EXACT(VdM!$B$2:$B$834,Mappa[[#This Row],[Giocatore_VdM]]),_xlpm.tot,SUMPRODUCT(--_xlpm.e),_xlpm.att,SUMPRODUCT(--_xlpm.e,--(VdM!$H$2:$H$834="Sì")),IF(_xlpm.tot=0,"NOME VdM ERRATO",IF(_xlpm.att=1,"OK",IF(_xlpm.att>1,"AMBIGUO",IF(_xlpm.tot=1,"OK (non attivo)","AMBIGUO"))))))} -> OK | E14: {=IF(OR(Mappa[[#This Row],[Stato]]="DA MAPPARE",Mappa[[#This Row],[Stato]]="NOME VdM ERRATO",Mappa[[#This Row],[Stato]]="AMBIGUO"),Mappa[[#This Row],[Stato]],_xlfn.LET(_xlpm.e,EXACT(VdM!$B$2:$B$834,Mappa[[#This Row],[Giocatore_VdM]]),_xlpm.a,IF(SUMPRODUCT(--_xlpm.e,--(VdM!$H$2:$H$834="Sì"))=1,MATCH(TRUE,(_xlpm.e)*(VdM!$H$2:$H$834="Sì")=1,0),MATCH(TRUE,_xlpm.e,0)),_xlpm.t,INDEX(VdM!$E$2:$E$834,_xlpm.a),_xlpm.k,ISNUMBER(SEARCH("mila",_xlpm.t)),_xlpm.v,IFERROR(VALUE(TRIM(LEFT(_xlpm.t,SEARCH(IF(_xlpm.k,"mila","mln"),_xlpm.t)-1))),"X"),IFERROR(IF(_xlpm.k,_xlpm.v/1000,_xlpm.v+0),"NON TROVATO")))} -> 22
A15: Basic | B15: C | C15: Toma Bašić | D15: {=IF(Mappa[[#This Row],[Giocatore_VdM]]="","DA MAPPARE",_xlfn.LET(_xlpm.e,EXACT(VdM!$B$2:$B$834,Mappa[[#This Row],[Giocatore_VdM]]),_xlpm.tot,SUMPRODUCT(--_xlpm.e),_xlpm.att,SUMPRODUCT(--_xlpm.e,--(VdM!$H$2:$H$834="Sì")),IF(_xlpm.tot=0,"NOME VdM ERRATO",IF(_xlpm.att=1,"OK",IF(_xlpm.att>1,"AMBIGUO",IF(_xlpm.tot=1,"OK (non attivo)","AMBIGUO"))))))} -> OK | E15: {=IF(OR(Mappa[[#This Row],[Stato]]="DA MAPPARE",Mappa[[#This Row],[Stato]]="NOME VdM ERRATO",Mappa[[#This Row],[Stato]]="AMBIGUO"),Mappa[[#This Row],[Stato]],_xlfn.LET(_xlpm.e,EXACT(VdM!$B$2:$B$834,Mappa[[#This Row],[Giocatore_VdM]]),_xlpm.a,IF(SUMPRODUCT(--_xlpm.e,--(VdM!$H$2:$H$834="Sì"))=1,MATCH(TRUE,(_xlpm.e)*(VdM!$H$2:$H$834="Sì")=1,0),MATCH(TRUE,_xlpm.e,0)),_xlpm.t,INDEX(VdM!$E$2:$E$834,_xlpm.a),_xlpm.k,ISNUMBER(SEARCH("mila",_xlpm.t)),_xlpm.v,IFERROR(VALUE(TRIM(LEFT(_xlpm.t,SEARCH(IF(_xlpm.k,"mila","mln"),_xlpm.t)-1))),"X"),IFERROR(IF(_xlpm.k,_xlpm.v/1000,_xlpm.v+0),"NON TROVATO")))} -> 3
A16: Bastoni | B16: D | C16: Alessandro Bastoni | D16: {=IF(Mappa[[#This Row],[Giocatore_VdM]]="","DA MAPPARE",_xlfn.LET(_xlpm.e,EXACT(VdM!$B$2:$B$834,Mappa[[#This Row],[Giocatore_VdM]]),_xlpm.tot,SUMPRODUCT(--_xlpm.e),_xlpm.att,SUMPRODUCT(--_xlpm.e,--(VdM!$H$2:$H$834="Sì")),IF(_xlpm.tot=0,"NOME VdM ERRATO",IF(_xlpm.att=1,"OK",IF(_xlpm.att>1,"AMBIGUO",IF(_xlpm.tot=1,"OK (non attivo)","AMBIGUO"))))))} -> OK | E16: {=IF(OR(Mappa[[#This Row],[Stato]]="DA MAPPARE",Mappa[[#This Row],[Stato]]="NOME VdM ERRATO",Mappa[[#This Row],[Stato]]="AMBIGUO"),Mappa[[#This Row],[Stato]],_xlfn.LET(_xlpm.e,EXACT(VdM!$B$2:$B$834,Mappa[[#This Row],[Giocatore_VdM]]),_xlpm.a,IF(SUMPRODUCT(--_xlpm.e,--(VdM!$H$2:$H$834="Sì"))=1,MATCH(TRUE,(_xlpm.e)*(VdM!$H$2:$H$834="Sì")=1,0),MATCH(TRUE,_xlpm.e,0)),_xlpm.t,INDEX(VdM!$E$2:$E$834,_xlpm.a),_xlpm.k,ISNUMBER(SEARCH("mila",_xlpm.t)),_xlpm.v,IFERROR(VALUE(TRIM(LEFT(_xlpm.t,SEARCH(IF(_xlpm.k,"mila","mln"),_xlpm.t)-1))),"X"),IFERROR(IF(_xlpm.k,_xlpm.v/1000,_xlpm.v+0),"NON TROVATO")))} -> 65
A17: Baturina | B17: C | C17: Martin Baturina | D17: {=IF(Mappa[[#This Row],[Giocatore_VdM]]="","DA MAPPARE",_xlfn.LET(_xlpm.e,EXACT(VdM!$B$2:$B$834,Mappa[[#This Row],[Giocatore_VdM]]),_xlpm.tot,SUMPRODUCT(--_xlpm.e),_xlpm.att,SUMPRODUCT(--_xlpm.e,--(VdM!$H$2:$H$834="Sì")),IF(_xlpm.tot=0,"NOME VdM ERRATO",IF(_xlpm.att=1,"OK",IF(_xlpm.att>1,"AMBIGUO",IF(_xlpm.tot=1,"OK (non attivo)","AMBIGUO"))))))} -> OK | E17: {=IF(OR(Mappa[[#This Row],[Stato]]="DA MAPPARE",Mappa[[#This Row],[Stato]]="NOME VdM ERRATO",Mappa[[#This Row],[Stato]]="AMBIGUO"),Mappa[[#This Row],[Stato]],_xlfn.LET(_xlpm.e,EXACT(VdM!$B$2:$B$834,Mappa[[#This Row],[Giocatore_VdM]]),_xlpm.a,IF(SUMPRODUCT(--_xlpm.e,--(VdM!$H$2:$H$834="Sì"))=1,MATCH(TRUE,(_xlpm.e)*(VdM!$H$2:$H$834="Sì")=1,0),MATCH(TRUE,_xlpm.e,0)),_xlpm.t,INDEX(VdM!$E$2:$E$834,_xlpm.a),_xlpm.k,ISNUMBER(SEARCH("mila",_xlpm.t)),_xlpm.v,IFERROR(VALUE(TRIM(LEFT(_xlpm.t,SEARCH(IF(_xlpm.k,"mila","mln"),_xlpm.t)-1))),"X"),IFERROR(IF(_xlpm.k,_xlpm.v/1000,_xlpm.v+0),"NON TROVATO")))} -> 55
A18: Bella-Kotchap | B18: D | C18: Armel Bella-Kotchap | D18: {=IF(Mappa[[#This Row],[Giocatore_VdM]]="","DA MAPPARE",_xlfn.LET(_xlpm.e,EXACT(VdM!$B$2:$B$834,Mappa[[#This Row],[Giocatore_VdM]]),_xlpm.tot,SUMPRODUCT(--_xlpm.e),_xlpm.att,SUMPRODUCT(--_xlpm.e,--(VdM!$H$2:$H$834="Sì")),IF(_xlpm.tot=0,"NOME VdM ERRATO",IF(_xlpm.att=1,"OK",IF(_xlpm.att>1,"AMBIGUO",IF(_xlpm.tot=1,"OK (non attivo)","AMBIGUO"))))))} -> OK | E18: {=IF(OR(Mappa[[#This Row],[Stato]]="DA MAPPARE",Mappa[[#This Row],[Stato]]="NOME VdM ERRATO",Mappa[[#This Row],[Stato]]="AMBIGUO"),Mappa[[#This Row],[Stato]],_xlfn.LET(_xlpm.e,EXACT(VdM!$B$2:$B$834,Mappa[[#This Row],[Giocatore_VdM]]),_xlpm.a,IF(SUMPRODUCT(--_xlpm.e,--(VdM!$H$2:$H$834="Sì"))=1,MATCH(TRUE,(_xlpm.e)*(VdM!$H$2:$H$834="Sì")=1,0),MATCH(TRUE,_xlpm.e,0)),_xlpm.t,INDEX(VdM!$E$2:$E$834,_xlpm.a),_xlpm.k,ISNUMBER(SEARCH("mila",_xlpm.t)),_xlpm.v,IFERROR(VALUE(TRIM(LEFT(_xlpm.t,SEARCH(IF(_xlpm.k,"mila","mln"),_xlpm.t)-1))),"X"),IFERROR(IF(_xlpm.k,_xlpm.v/1000,_xlpm.v+0),"NON TROVATO")))} -> 7
A19: Berardi | B19: A | C19: Domenico Berardi | D19: {=IF(Mappa[[#This Row],[Giocatore_VdM]]="","DA MAPPARE",_xlfn.LET(_xlpm.e,EXACT(VdM!$B$2:$B$834,Mappa[[#This Row],[Giocatore_VdM]]),_xlpm.tot,SUMPRODUCT(--_xlpm.e),_xlpm.att,SUMPRODUCT(--_xlpm.e,--(VdM!$H$2:$H$834="Sì")),IF(_xlpm.tot=0,"NOME VdM ERRATO",IF(_xlpm.att=1,"OK",IF(_xlpm.att>1,"AMBIGUO",IF(_xlpm.tot=1,"OK (non attivo)","AMBIGUO"))))))} -> OK | E19: {=IF(OR(Mappa[[#This Row],[Stato]]="DA MAPPARE",Mappa[[#This Row],[Stato]]="NOME VdM ERRATO",Mappa[[#This Row],[Stato]]="AMBIGUO"),Mappa[[#This Row],[Stato]],_xlfn.LET(_xlpm.e,EXACT(VdM!$B$2:$B$834,Mappa[[#This Row],[Giocatore_VdM]]),_xlpm.a,IF(SUMPRODUCT(--_xlpm.e,--(VdM!$H$2:$H$834="Sì"))=1,MATCH(TRUE,(_xlpm.e)*(VdM!$H$2:$H$834="Sì")=1,0),MATCH(TRUE,_xlpm.e,0)),_xlpm.t,INDEX(VdM!$E$2:$E$834,_xlpm.a),_xlpm.k,ISNUMBER(SEARCH("mila",_xlpm.t)),_xlpm.v,IFERROR(VALUE(TRIM(LEFT(_xlpm.t,SEARCH(IF(_xlpm.k,"mila","mln"),_xlpm.t)-1))),"X"),IFERROR(IF(_xlpm.k,_xlpm.v/1000,_xlpm.v+0),"NON TROVATO")))} -> 7
A20: Bernabè | B20: C | C20: Adrián Bernabé | D20: {=IF(Mappa[[#This Row],[Giocatore_VdM]]="","DA MAPPARE",_xlfn.LET(_xlpm.e,EXACT(VdM!$B$2:$B$834,Mappa[[#This Row],[Giocatore_VdM]]),_xlpm.tot,SUMPRODUCT(--_xlpm.e),_xlpm.att,SUMPRODUCT(--_xlpm.e,--(VdM!$H$2:$H$834="Sì")),IF(_xlpm.tot=0,"NOME VdM ERRATO",IF(_xlpm.att=1,"OK",IF(_xlpm.att>1,"AMBIGUO",IF(_xlpm.tot=1,"OK (non attivo)","AMBIGUO"))))))} -> OK | E20: {=IF(OR(Mappa[[#This Row],[Stato]]="DA MAPPARE",Mappa[[#This Row],[Stato]]="NOME VdM ERRATO",Mappa[[#This Row],[Stato]]="AMBIGUO"),Mappa[[#This Row],[Stato]],_xlfn.LET(_xlpm.e,EXACT(VdM!$B$2:$B$834,Mappa[[#This Row],[Giocatore_VdM]]),_xlpm.a,IF(SUMPRODUCT(--_xlpm.e,--(VdM!$H$2:$H$834="Sì"))=1,MATCH(TRUE,(_xlpm.e)*(VdM!$H$2:$H$834="Sì")=1,0),MATCH(TRUE,_xlpm.e,0)),_xlpm.t,INDEX(VdM!$E$2:$E$834,_xlpm.a),_xlpm.k,ISNUMBER(SEARCH("mila",_xlpm.t)),_xlpm.v,IFERROR(VALUE(TRIM(LEFT(_xlpm.t,SEARCH(IF(_xlpm.k,"mila","mln"),_xlpm.t)-1))),"X"),IFERROR(IF(_xlpm.k,_xlpm.v/1000,_xlpm.v+0),"NON TROVATO")))} -> 15
A21: Bernardeschi | B21: C | C21: Federico Bernardeschi | D21: {=IF(Mappa[[#This Row],[Giocatore_VdM]]="","DA MAPPARE",_xlfn.LET(_xlpm.e,EXACT(VdM!$B$2:$B$834,Mappa[[#This Row],[Giocatore_VdM]]),_xlpm.tot,SUMPRODUCT(--_xlpm.e),_xlpm.att,SUMPRODUCT(--_xlpm.e,--(VdM!$H$2:$H$834="Sì")),IF(_xlpm.tot=0,"NOME VdM ERRATO",IF(_xlpm.att=1,"OK",IF(_xlpm.att>1,"AMBIGUO",IF(_xlpm.tot=1,"OK (non attivo)","AMBIGUO"))))))} -> OK | E21: {=IF(OR(Mappa[[#This Row],[Stato]]="DA MAPPARE",Mappa[[#This Row],[Stato]]="NOME VdM ERRATO",Mappa[[#This Row],[Stato]]="AMBIGUO"),Mappa[[#This Row],[Stato]],_xlfn.LET(_xlpm.e,EXACT(VdM!$B$2:$B$834,Mappa[[#This Row],[Giocatore_VdM]]),_xlpm.a,IF(SUMPRODUCT(--_xlpm.e,--(VdM!$H$2:$H$834="Sì"))=1,MATCH(TRUE,(_xlpm.e)*(VdM!$H$2:$H$834="Sì")=1,0),MATCH(TRUE,_xlpm.e,0)),_xlpm.t,INDEX(VdM!$E$2:$E$834,_xlpm.a),_xlpm.k,ISNUMBER(SEARCH("mila",_xlpm.t)),_xlpm.v,IFERROR(VALUE(TRIM(LEFT(_xlpm.t,SEARCH(IF(_xlpm.k,"mila","mln"),_xlpm.t)-1))),"X"),IFERROR(IF(_xlpm.k,_xlpm.v/1000,_xlpm.v+0),"NON TROVATO")))} -> 3.5
A22: Bernasconi | B22: D | C22: Lorenzo Bernasconi | D22: {=IF(Mappa[[#This Row],[Giocatore_VdM]]="","DA MAPPARE",_xlfn.LET(_xlpm.e,EXACT(VdM!$B$2:$B$834,Mappa[[#This Row],[Giocatore_VdM]]),_xlpm.tot,SUMPRODUCT(--_xlpm.e),_xlpm.att,SUMPRODUCT(--_xlpm.e,--(VdM!$H$2:$H$834="Sì")),IF(_xlpm.tot=0,"NOME VdM ERRATO",IF(_xlpm.att=1,"OK",IF(_xlpm.att>1,"AMBIGUO",IF(_xlpm.tot=1,"OK (non attivo)","AMBIGUO"))))))} -> OK | E22: {=IF(OR(Mappa[[#This Row],[Stato]]="DA MAPPARE",Mappa[[#This Row],[Stato]]="NOME VdM ERRATO",Mappa[[#This Row],[Stato]]="AMBIGUO"),Mappa[[#This Row],[Stato]],_xlfn.LET(_xlpm.e,EXACT(VdM!$B$2:$B$834,Mappa[[#This Row],[Giocatore_VdM]]),_xlpm.a,IF(SUMPRODUCT(--_xlpm.e,--(VdM!$H$2:$H$834="Sì"))=1,MATCH(TRUE,(_xlpm.e)*(VdM!$H$2:$H$834="Sì")=1,0),MATCH(TRUE,_xlpm.e,0)),_xlpm.t,INDEX(VdM!$E$2:$E$834,_xlpm.a),_xlpm.k,ISNUMBER(SEARCH("mila",_xlpm.t)),_xlpm.v,IFERROR(VALUE(TRIM(LEFT(_xlpm.t,SEARCH(IF(_xlpm.k,"mila","mln"),_xlpm.t)-1))),"X"),IFERROR(IF(_xlpm.k,_xlpm.v/1000,_xlpm.v+0),"NON TROVATO")))} -> 20
A23: Bertola | B23: D | C23: Nicolò Bertola | D23: {=IF(Mappa[[#This Row],[Giocatore_VdM]]="","DA MAPPARE",_xlfn.LET(_xlpm.e,EXACT(VdM!$B$2:$B$834,Mappa[[#This Row],[Giocatore_VdM]]),_xlpm.tot,SUMPRODUCT(--_xlpm.e),_xlpm.att,SUMPRODUCT(--_xlpm.e,--(VdM!$H$2:$H$834="Sì")),IF(_xlpm.tot=0,"NOME VdM ERRATO",IF(_xlpm.att=1,"OK",IF(_xlpm.att>1,"AMBIGUO",IF(_xlpm.tot=1,"OK (non attivo)","AMBIGUO"))))))} -> OK | E23: {=IF(OR(Mappa[[#This Row],[Stato]]="DA MAPPARE",Mappa[[#This Row],[Stato]]="NOME VdM ERRATO",Mappa[[#This Row],[Stato]]="AMBIGUO"),Mappa[[#This Row],[Stato]],_xlfn.LET(_xlpm.e,EXACT(VdM!$B$2:$B$834,Mappa[[#This Row],[Giocatore_VdM]]),_xlpm.a,IF(SUMPRODUCT(--_xlpm.e,--(VdM!$H$2:$H$834="Sì"))=1,MATCH(TRUE,(_xlpm.e)*(VdM!$H$2:$H$834="Sì")=1,0),MATCH(TRUE,_xlpm.e,0)),_xlpm.t,INDEX(VdM!$E$2:$E$834,_xlpm.a),_xlpm.k,ISNUMBER(SEARCH("mila",_xlpm.t)),_xlpm.v,IFERROR(VALUE(TRIM(LEFT(_xlpm.t,SEARCH(IF(_xlpm.k,"mila","mln"),_xlpm.t)-1))),"X"),IFERROR(IF(_xlpm.k,_xlpm.v/1000,_xlpm.v+0),"NON TROVATO")))} -> 7
... A286: Grabara | B286: P | C286: Kamil Grabara | D286: {=IF(Mappa[[#This Row],[Giocatore_VdM]]="","DA MAPPARE",_xlfn.LET(_xlpm.e,EXACT(VdM!$B$2:$B$834,Mappa[[#This Row],[Giocatore_VdM]]),_xlpm.tot,SUMPRODUCT(--_xlpm.e),_xlpm.att,SUMPRODUCT(--_xlpm.e,--(VdM!$H$2:$H$834="Sì")),IF(_xlpm.tot=0,"NOME VdM ERRATO",IF(_xlpm.att=1,"OK",IF(_xlpm.att>1,"AMBIGUO",IF(_xlpm.tot=1,"OK (non attivo)","AMBIGUO"))))))} -> OK | E286: {=IF(OR(Mappa[[#This Row],[Stato]]="DA MAPPARE",Mappa[[#This Row],[Stato]]="NOME VdM ERRATO",Mappa[[#This Row],[Stato]]="AMBIGUO"),Mappa[[#This Row],[Stato]],_xlfn.LET(_xlpm.e,EXACT(VdM!$B$2:$B$834,Mappa[[#This Row],[Giocatore_VdM]]),_xlpm.a,IF(SUMPRODUCT(--_xlpm.e,--(VdM!$H$2:$H$834="Sì"))=1,MATCH(TRUE,(_xlpm.e)*(VdM!$H$2:$H$834="Sì")=1,0),MATCH(TRUE,_xlpm.e,0)),_xlpm.t,INDEX(VdM!$E$2:$E$834,_xlpm.a),_xlpm.k,ISNUMBER(SEARCH("mila",_xlpm.t)),_xlpm.v,IFERROR(VALUE(TRIM(LEFT(_xlpm.t,SEARCH(IF(_xlpm.k,"mila","mln"),_xlpm.t)-1))),"X"),IFERROR(IF(_xlpm.k,_xlpm.v/1000,_xlpm.v+0),"NON TROVATO")))} -> 12

Sheet Foglio Asta
A1: ⭐⭐⭐ ROBERTO | C1: ⭐⭐ DOMENICO | E1: GREG | G1: ⭐ ALE&MAX | I1: ⭐ FABIO | K1: ⭐⭐⭐⭐ SALVO | M1: ⭐⭐⭐ GIANNI | O1: ⭐ MARIO&AMEDEO | Q1: ⭐⭐ MARCO | S1: ENRICO | U1: NOME ALLENATORE | Z1: AGOSTO | AB1: Formazione realizzata il XX/XX sulla base dei prezzi dell'asta | AC1: ='[1]Quotazioni 16-08'!D3 -> SVILAR | AD1: ='[1]Quotazioni 16-08'!D62 -> PISSERI | AE1: ='[1]Quotazioni 16-08'!D238 -> ABANKWAH | AF1: ='[1]Quotazioni 16-08'!D412 -> CAMARA A.
A2: Paris Saint-Gervasoni | B2: =400-SUM(B4:B14)-SUM(B16:B23)-SUM(B25:B30)+(IF(B3<0,B3,0)) -> 4 | C2: Incontro al Capitano | D2: =400-SUM(D4:D14)-SUM(D16:D23)-SUM(D25:D30)+(IF(D3<0,D3,0)) -> 6 | E2: Super Gregariana | F2: =400-SUM(F4:F14)-SUM(F16:F23)-SUM(F25:F30)+(IF(F3<0,F3,0)) -> 2 | G2: I Bamboli | H2: =400-SUM(H4:H14)-SUM(H16:H23)-SUM(H25:H30)+(IF(H3<0,H3,0)) -> 0 | I2: Mancinix | J2: =400-SUM(J4:J14)-SUM(J16:J23)-SUM(J25:J30)+(IF(J3<0,J3,0)) -> 0 | K2: Outletico Palermo | L2: =400-SUM(L4:L14)-SUM(L16:L23)-SUM(L25:L30)+(IF(L3<0,L3,0)) -> 5 | M2: GC21 | N2: =400-SUM(N4:N14)-SUM(N16:N23)-SUM(N25:N30)+(IF(N3<0,N3,0)) -> 0 | O2: Masterchef FC | P2: =400-SUM(P4:P14)-SUM(P16:P23)-SUM(P25:P30)+(IF(P3<0,P3,0)) -> 0 | Q2: Schalke 104 | R2: =400-SUM(R4:R14)-SUM(R16:R23)-SUM(R25:R30)+(IF(R3<0,R3,0)) -> 0 | S2: Evacuo Kaka Toni | T2: =400-SUM(T4:T14)-SUM(T16:T23)-SUM(T25:T30)+(IF(T3<0,T3,0)) -> 1 | U2: NOME SQUADRA | Z2: best cost saving | AA2: =400-(SUM(AA4:AA30)) -> 400 | AB2: Strategia Base per tutti i ruoli | AC2: ='[1]Quotazioni 16-08'!D4 -> MARTINEZ JO. | AD2: ='[1]Quotazioni 16-08'!D63 -> DIMARCO | AE2: ='[1]Quotazioni 16-08'!D239 -> GOMES | AF2: ='[1]Quotazioni 16-08'!D413 -> ZARRAGA
B3: =30-B15-B24-B31 -> -22 | D3: =30-D15-D24-D31 -> 0 | F3: =30-F15-F24-F31 -> -7 | H3: =30-H15-H24-H31 -> 17 | J3: =30-J15-J24-J31 -> 2 | L3: =30-L15-L24-L31 -> -2 | N3: =30-N15-N24-N31 -> -23 | P3: =30-P15-P24-P31 -> -32 | R3: =30-R15-R24-R31 -> 0 | T3: =30-T15-T24-T31 -> 14 | AC3: ='[1]Quotazioni 16-08'!D5 -> CARNESECCHI | AD3: ='[1]Quotazioni 16-08'!D64 -> MOLINA N. | AE3: ='[1]Quotazioni 16-08'!D240 -> PAZ N. | AF3: ='[1]Quotazioni 16-08'!D414 -> DAGASSO
A4: MANDAS | B4: 16 | C4: MAIGNAN | D4: 53 | E4: BUTEZ | F4: 49 | G4: DE GEA | H4: 32 | I4: CARNESECCHI | J4: 52 | K4: SVILAR | L4: 58 | M4: DI GREGORIO | N4: 5 | O4: SKORUPSKI | P4: 6 | Q4: MERET | R4: 48 | S4: MARTINEZ JO. | T4: 57 | U4: POR | AC4: ='[1]Quotazioni 16-08'!D6 -> BUTEZ | AD4: ='[1]Quotazioni 16-08'!D65 -> WESLEY | AE4: ='[1]Quotazioni 16-08'!D241 -> MCTOMINAY | AF4: ='[1]Quotazioni 16-08'!D415 -> MARTINEZ L.
A5: OKOYE | B5: 13 | C5: PROVEDEL | D5: 11 | E5: STANKOVIC F. | F5: 1 | G5: MILINKOVIC-SAVIC V. | H5: 6 | I5: SPORTIELLO | J5: 1 | K5: GOLLINI | L5: 1 | M5: MURIC | N5: 6 | O5: BIJLOW | P5: 12 | Q5: CAPRILE | R5: 5 | S5: FALCONE | T5: 4 | U5: POR | AC5: ='[1]Quotazioni 16-08'!D7 -> MAIGNAN | AD5: ='[1]Quotazioni 16-08'!D66 -> AKANJI | AE5: ='[1]Quotazioni 16-08'!D242 -> CALHANOGLU | AF5: ='[1]Quotazioni 16-08'!D416 -> MALEN
A6: SUZUKI | B6: 5 | C6: TERRACCIANO | D6: 1 | E6: TORNQVIST | F6: 1 | G6: CHRISTENSEN O. | H6: 1 | I6: DAFFARA | J6: 1 | K6: PERIN | L6: 1 | M6: PALMISANI | N6: 4 | O6: PALEARI | P6: 1 | Q6: THIAM | R6: 4 | S6: MASCARDI | T6: 1 | U6: POR | AC6: ='[1]Quotazioni 16-08'!D8 -> DE GEA | AD6: ='[1]Quotazioni 16-08'!D67 -> BREMER | AE6: ='[1]Quotazioni 16-08'!D243 -> ORSOLINI | AF6: ='[1]Quotazioni 16-08'!D417 -> THURAM
A7: COUTO | B7: 20 | C7: SCALVINI | D7: 10 | E7: DIMARCO | F7: 63 | G7: SOLET | H7: 16 | I7: AKANJI | J7: 19 | K7: DELPRATO | L7: 2 | M7: MANCINI | N7: 21 | O7: SPENCE | P7: 30 | Q7: WESLEY | R7: 17 | S7: DOEKHI | T7: 10 | U7: DIF | AC7: ='[1]Quotazioni 16-08'!D9 -> MERET | AD7: ='[1]Quotazioni 16-08'!D68 -> MANCINI | AE7: ='[1]Quotazioni 16-08'!D244 -> PULISIC | AF7: ='[1]Quotazioni 16-08'!D418 -> HOJLUND
A8: MIRANDA J. | B8: 5 | C8: BREMER | D8: 21 | E8: KELLY L. | F8: 2 | G8: HAPS | H8: 10 | I8: BASTONI | J8: 16 | K8: KALULU | L8: 10 | M8: BISSECK | N8: 12 | O8: BELLA-KOTCHAP | P8: 1 | Q8: PAVLOVIC | R8: 17 | S8: GILA | T8: 9 | U8: DIF | AC8: ='[1]Quotazioni 16-08'!D10 -> SKORUPSKI | AD8: ='[1]Quotazioni 16-08'!D69 -> BASTONI | AE8: ='[1]Quotazioni 16-08'!D245 -> RABIOT | AF8: ='[1]Quotazioni 16-08'!D419 -> RAMOS G.
A9: BERNASCONI | B9: 4 | C9: MOLINA N. | D9: 27 | E9: LUCUMÌ | F9: 6 | G9: DI LORENZO | H9: 10 | I9: CHALOBAH T. | J9: 16 | K9: MINA | L9: 3 | M9: ZAPPACOSTA | N9: 5 | O9: OYONO A. | P9: 2 | Q9: RRAHMANI | R9: 10 | S9: DRAGUSIN | T9: 11 | U9: DIF | AC9: ='[1]Quotazioni 16-08'!D11 -> CAPRILE | AD9: ='[1]Quotazioni 16-08'!D70 -> PAVLOVIC | AE9: ='[1]Quotazioni 16-08'!D246 -> BATURINA | AF9: ='[1]Quotazioni 16-08'!D420 -> KOLO MUANI
A10: KAIKI | B10: 7 | C10: STONES | D10: 20 | E10: KRISTENSEN T. | F10: 9 | G10: CELIK | H10: 10 | I10: PAVARD | J10: 1 | K10: OSTIGARD | L10: 13 | M10: CAMBIASO | N10: 5 | O10: NORTON-CUFFY | P10: 6 | Q10: VOJVODA | R10: 7 | S10: KOULIERAKIS | T10: 4 | U10: DIF | AC10: ='[1]Quotazioni 16-08'!D12 -> DI GREGORIO | AD10: ='[1]Quotazioni 16-08'!D71 -> RRAHMANI | AE10: ='[1]Quotazioni 16-08'!D247 -> DA CUNHA | AF10: ='[1]Quotazioni 16-08'!D421 -> KEAN
A11: VALLE | B11: 2 | C11: GABBIA | D11: 2 | E11: HEGGEM | F11: 4 | G11: GASPAR K. | H11: 3 | I11: IDZES | J11: 2 | K11: N'DICKA | L11: 5 | M11: DE WINTER | N11: 1 | O11: BERTOLA | P11: 1 | Q11: SPINAZZOLA | R11: 3 | S11: ZORTEA | T11: 3 | U11: DIF | AC11: ='[1]Quotazioni 16-08'!D13 -> MANDAS | AD11: ='[1]Quotazioni 16-08'!D72 -> KALULU | AE11: ='[1]Quotazioni 16-08'!D248 -> ZANIOLO | AF11: ='[1]Quotazioni 16-08'!D422 -> YILDIZ
A12: KAMARA H. | B12: 1 | C12: OBRADOR | D12: 1 | E12: MONTERISI | F12: 1 | G12: CARLOS AUGUSTO | H12: 9 | I12: MARIN R. | J12: 1 | K12: HERMOSO | L12: 2 | M12: VASQUEZ | N12: 3 | O12: BIRINDELLI | P12: 1 | Q12: HAINAUT | R12: 2 | S12: MANGAS | T12: 1 | U12: DIF | AC12: ='[1]Quotazioni 16-08'!D14 -> OKOYE | AD12: ='[1]Quotazioni 16-08'!D73 -> N'DICKA | AE12: ='[1]Quotazioni 16-08'!D249 -> ATTA | AF12: ='[1]Quotazioni 16-08'!D423 -> DOUVIKAS
A13: TAVARES N. | B13: 2 | C13: ROMAGNOLI | D13: 1 | E13: JOAO MARIO | F13: 3 | G13: VALERI | H13: 3 | I13: KEMPF | J13: 4 | K13: PEDERSEN | L13: 1 | M13: DODÒ | N13: 3 | O13: VEIGA D. | P13: 1 | Q13: ISMAJLI | R13: 1 | S13: HELLAND | T13: 1 | U13: DIF | AC13: ='[1]Quotazioni 16-08'!D15 -> BIJLOW | AD13: ='[1]Quotazioni 16-08'!D74 -> SOLET | AE13: ='[1]Quotazioni 16-08'!D250 -> BARELLA | AF13: ='[1]Quotazioni 16-08'!D424 -> SCAMACCA
A14: PEDRAZA | B14: 1 | C14: KOLASINAC | D14: 1 | E14: TROILO | F14: 1 | G14: OBERT | H14: 1 | I14: BEUKEMA | J14: 1 | K14: TOMORI | L14: 1 | M14: BELLANOVA | N14: 2 | O14: CIRCATI | P14: 1 | Q14: COCO | R14: 3 | S14: RENSCH | T14: 1 | U14: DIF | AC14: ='[1]Quotazioni 16-08'!D16 -> FALCONE | AD14: ='[1]Quotazioni 16-08'!D75 -> STONES | AE14: ='[1]Quotazioni 16-08'!D251 -> MCKENNIE | AF14: ='[1]Quotazioni 16-08'!D425 -> DAVIS K.
A15: VALDEPENAS | B15: 15 | C15: BARTESAGHI | D15: 20 | E15: AHANOR | F15: 3 | G15: RODRIGUEZ JU. | H15: 1 | I15: VIERY | J15: 12 | K15: CUENCA A. | L15: 1 | M15: RAMON | N15: 20 | O15: TIAGO GABRIEL | P15: 7 | Q15: COMUZZO | R15: 2 | S15: JIMENEZ A. | T15: 14 | U15: DIF PRIMAVERA | AC15: ='[1]Quotazioni 16-08'!D17 -> DAFFARA | AD15: ='[1]Quotazioni 16-08'!D76 -> GILA | AE15: ='[1]Quotazioni 16-08'!D252 -> ZACCAGNI | AF15: ='[1]Quotazioni 16-08'!D426 -> KRSTOVIC
... A31: ALBARRACIN | B31: 1 | C31: CAMARDA | D31: 8 | E31: TREPY | F31: 1 | G31: VARELA G. | H31: 6 | I31: MENDY P. | J31: 4 | K31: DIAO | L31: 28 | M31: ROBINSON J. | N31: 1 | O31: EKHATOR | P31: 3 | Q31: GUEYE | R31: 3 | S31: VAZ | T31: 1 | U31: ATT PRIMAVERA | AC31: ='[1]Quotazioni 16-08'!D33 -> CHRISTENSEN O. | AD31: ='[1]Quotazioni 16-08'!D92 -> MINA | AE31: ='[1]Quotazioni 16-08'!D268 -> ZIELINSKI | AF31: ='[1]Quotazioni 16-08'!D442 -> KEVIN CARLOS
AC32: ='[1]Quotazioni 16-08'!D34 -> LEZZERINI | AD32: ='[1]Quotazioni 16-08'!D93 -> DRAGUSIN | AE32: ='[1]Quotazioni 16-08'!D269 -> THURAM K. | AF32: ='[1]Quotazioni 16-08'!D443 -> SOULÈ
B33: =B2 -> 4 | D33: =D2 -> 6 | F33: =F2 -> 2 | H33: =H2 -> 0 | J33: =J2 -> 0 | L33: =L2 -> 5 | N33: =N2 -> 0 | P33: =P2 -> 0 | R33: =R2 -> 0 | T33: =T2 -> 1 | U33: BUDGET PRIMA SQUADRA | AC33: ='[1]Quotazioni 16-08'!D35 -> LOLIC | AD33: ='[1]Quotazioni 16-08'!D94 -> JIMENEZ A. | AE33: ='[1]Quotazioni 16-08'!D270 -> SAELEMAEKERS | AF33: ='[1]Quotazioni 16-08'!D444 -> ADAMS A.
B34: =B3 -> -22 | D34: =D3 -> 0 | F34: =F3 -> -7 | H34: =H3 -> 17 | J34: =J3 -> 2 | L34: =L3 -> -2 | N34: =N3 -> -23 | P34: =P3 -> -32 | R34: =R3 -> 0 | T34: =T3 -> 14 | U34: BUDGET PRIMAVERA | AC34: ='[1]Quotazioni 16-08'!D36 -> SOMMARIVA | AD34: ='[1]Quotazioni 16-08'!D95 -> NORTON-CUFFY | AE34: ='[1]Quotazioni 16-08'!D271 -> POLITANO | AF34: ='[1]Quotazioni 16-08'!D445 -> DIAO
AC35: ='[1]Quotazioni 16-08'!D37 -> STOLZ | AD35: ='[1]Quotazioni 16-08'!D96 -> CELIK | AE35: ='[1]Quotazioni 16-08'!D272 -> KONÈ M. | AF35: ='[1]Quotazioni 16-08'!D446 -> COLOMBO
A36: DELTA | B36: =$N$33-B33 -> -4 | D36: =$N$33-D33 -> -6 | F36: =$N$33-F33 -> -2 | H36: =$N$33-H33 -> 0 | J36: =$N$33-J33 -> 0 | L36: =$N$33-L33 -> -5 | P36: =$N$33-P33 -> 0 | R36: =$N$33-R33 -> 0 | T36: =$N$33-T33 -> -1 | AC36: ='[1]Quotazioni 16-08'!D38 -> DI GENNARO | AD36: ='[1]Quotazioni 16-08'!D97 -> BARTESAGHI | AE36: ='[1]Quotazioni 16-08'!D273 -> THORSTVEDT | AF36: ='[1]Quotazioni 16-08'!D447 -> TOURÈ E.
V37: Media (esclusi Max e Min) | Y37: Budget | AC37: ='[1]Quotazioni 16-08'!D39 -> PINSOGLIO | AD37: ='[1]Quotazioni 16-08'!D98 -> SPINAZZOLA | AE37: ='[1]Quotazioni 16-08'!D274 -> CASADEI | AF37: ='[1]Quotazioni 16-08'!D448 -> DIA
A38: =SUM(B4:B6)/400 -> 0.085 | C38: =SUM(D4:D6)/400 -> 0.1625 | E38: =SUM(F4:F6)/400 -> 0.1275 | G38: =SUM(H4:H6)/400 -> 0.0975 | I38: =SUM(J4:J6)/400 -> 0.135 | K38: =SUM(L4:L6)/400 -> 0.15 | M38: =SUM(N4:N6)/400 -> 0.0375 | O38: =SUM(P4:P6)/400 -> 0.0475 | Q38: =SUM(R4:R6)/400 -> 0.1425 | S38: =SUM(T4:T6)/400 -> 0.155 | U38: % Spesa Portieri | V38: =AVERAGE(C38,G38,I38,K38,M38,O38,Q38,S38) -> 0.1159375 | Y38: =ROUND(400*V38,0) -> 46 | AC38: ='[1]Quotazioni 16-08'!D40 -> MOTTA | AD38: ='[1]Quotazioni 16-08'!D99 -> DELPRATO | AE38: ='[1]Quotazioni 16-08'!D275 -> EKKELENKAMP | AF38: ='[1]Quotazioni 16-08'!D449 -> RATKOV
A39: =SUM(B7:B14)/400 -> 0.105 | C39: =SUM(D7:D14)/400 -> 0.2075 | E39: =SUM(F7:F14)/400 -> 0.2225 | G39: =SUM(H7:H14)/400 -> 0.155 | I39: =SUM(J7:J14)/400 -> 0.15 | K39: =SUM(L7:L14)/400 -> 0.0925 | M39: =SUM(N7:N14)/400 -> 0.13 | O39: =SUM(P7:P14)/400 -> 0.1075 | Q39: =SUM(R7:R14)/400 -> 0.15 | S39: =SUM(T7:T14)/400 -> 0.1 | U39: % Spesa Difensori | V39: =AVERAGE(A39,C39,G39,I39,K39,M39,O39,S39) -> 0.1309375 | Y39: =ROUND(400*V39,0) -> 52 | AC39: ='[1]Quotazioni 16-08'!D41 -> RENZETTI | AD39: ='[1]Quotazioni 16-08'!D100 -> VALERI | AE39: ='[1]Quotazioni 16-08'!D276 -> PELLEGRINI LO. | AF39: ='[1]Quotazioni 16-08'!D450 -> BOWIE
A40: =SUM(B16:B23)/400 -> 0.325 | C40: =SUM(D16:D23)/400 -> 0.355 | E40: =SUM(F16:F23)/400 -> 0.355 | G40: =SUM(H16:H23)/400 -> 0.3075 | I40: =SUM(J16:J23)/400 -> 0.3425 | K40: =SUM(L16:L23)/400 -> 0.28 | M40: =SUM(N16:N23)/400 -> 0.32 | O40: =SUM(P16:P23)/400 -> 0.205 | Q40: =SUM(R16:R23)/400 -> 0.23 | S40: =SUM(T16:T23)/400 -> 0.3975 | U40: % Spesa Centrocampo | V40: =AVERAGE(A40,C40,E40,I40,K40,M40,O40,S40) -> 0.3225 | Y40: =ROUND(400*V40,0) -> 129 | AC40: ='[1]Quotazioni 16-08'!D42 -> TERRACCIANO | AD40: ='[1]Quotazioni 16-08'!D101 -> KOULIERAKIS | AE40: ='[1]Quotazioni 16-08'!D277 -> PASALIC | AF40: ='[1]Quotazioni 16-08'!D451 -> ROMERO D.
A41: =SUM(B25:B30)/400 -> 0.42 | C41: =SUM(D25:D30)/400 -> 0.26 | E41: =SUM(F25:F30)/400 -> 0.2725 | G41: =SUM(H25:H30)/400 -> 0.44 | I41: =SUM(J25:J30)/400 -> 0.3725 | K41: =SUM(L25:L30)/400 -> 0.46 | M41: =SUM(N25:N30)/400 -> 0.455 | O41: =SUM(P25:P30)/400 -> 0.56 | Q41: =SUM(R25:R30)/400 -> 0.4775 | S41: =SUM(T25:T30)/400 -> 0.345 | U41: % Spesa Attacco | V41: =AVERAGE(C41,G41,I41,K41,M41,O41,Q41,S41) -> 0.42125 | Y41: =ROUND(400*V41,0) -> 169 | AC41: ='[1]Quotazioni 16-08'!D43 -> TORRIANI | AD41: ='[1]Quotazioni 16-08'!D102 -> VOJVODA | AE41: ='[1]Quotazioni 16-08'!D278 -> BERNARDESCHI | AF41: ='[1]Quotazioni 16-08'!D452 -> GHEDJEMIS
AC42: ='[1]Quotazioni 16-08'!D44 -> PIZZIGNACCO | AD42: ='[1]Quotazioni 16-08'!D103 -> COUTO | AE42: ='[1]Quotazioni 16-08'!D279 -> MANDRAGORA | AF42: ='[1]Quotazioni 16-08'!D453 -> DAVID
AC43: ='[1]Quotazioni 16-08'!D45 -> STRAJNAR | AD43: ='[1]Quotazioni 16-08'!D104 -> OBERT | AE43: ='[1]Quotazioni 16-08'!D280 -> CANCELLIERI | AF43: ='[1]Quotazioni 16-08'!D454 -> GEUBBELS
AC44: ='[1]Quotazioni 16-08'!D46 -> CONTINI | AD44: ='[1]Quotazioni 16-08'!D105 -> KAIKI | AE44: ='[1]Quotazioni 16-08'!D281 -> ISAKSEN | AF44: ='[1]Quotazioni 16-08'!D455 -> CUTRONE
AC45: ='[1]Quotazioni 16-08'!D47 -> CORVI | AD45: ='[1]Quotazioni 16-08'!D106 -> CARLOS AUGUSTO | AE45: ='[1]Quotazioni 16-08'!D282 -> KONÈ I. | AF45: ='[1]Quotazioni 16-08'!D456 -> ADAMS C.
AC46: ='[1]Quotazioni 16-08'!D48 -> DE MARZI | AD46: ='[1]Quotazioni 16-08'!D107 -> DOEKHI | AE46: ='[1]Quotazioni 16-08'!D283 -> ODGAARD | AF46: ='[1]Quotazioni 16-08'!D457 -> DALLINGA
AC47: ='[1]Quotazioni 16-08'!D49 -> GOLLINI | AD47: ='[1]Quotazioni 16-08'!D108 -> ROMAGNOLI | AE47: ='[1]Quotazioni 16-08'!D284 -> CAMBIAGHI | AF47: ='[1]Quotazioni 16-08'!D458 -> PICCOLI
AC48: ='[1]Quotazioni 16-08'!D50 -> RUSSO A. | AD48: ='[1]Quotazioni 16-08'!D109 -> TIAGO GABRIEL | AE48: ='[1]Quotazioni 16-08'!D285 -> FAGIOLI | AF48: ='[1]Quotazioni 16-08'!D459 -> VITINHA O.
AC49: ='[1]Quotazioni 16-08'!D51 -> TURATI | AD49: ='[1]Quotazioni 16-08'!D110 -> GABBIA | AE49: ='[1]Quotazioni 16-08'!D286 -> NDOUR | AF49: ='[1]Quotazioni 16-08'!D460 -> YEBOAH J.
AC50: ='[1]Quotazioni 16-08'!D52 -> MASCARDI | AD50: ='[1]Quotazioni 16-08'!D111 -> TOMORI | AE50: ='[1]Quotazioni 16-08'!D287 -> DIOUF | AF50: ='[1]Quotazioni 16-08'!D461 -> RRAHMANI AL.
AC51: ='[1]Quotazioni 16-08'!D53 -> PALEARI | AD51: ='[1]Quotazioni 16-08'!D112 -> BUONGIORNO | AE51: ='[1]Quotazioni 16-08'!D288 -> SUCIC P. | AF51: ='[1]Quotazioni 16-08'!D462 -> RAIMONDO
AC52: ='[1]Quotazioni 16-08'!D54 -> SIVIERO | AD52: ='[1]Quotazioni 16-08'!D113 -> IDZES | AE52: ='[1]Quotazioni 16-08'!D289 -> LOCATELLI | AF52: ='[1]Quotazioni 16-08'!D463 -> BONNY
AC53: ='[1]Quotazioni 16-08'!D55 -> PADELLI | AD53: ='[1]Quotazioni 16-08'!D114 -> COCO | AE53: ='[1]Quotazioni 16-08'!D290 -> COLPANI | AF53: ='[1]Quotazioni 16-08'!D464 -> STULIC
... AC59: ='[1]Quotazioni 16-08'!D61 -> PENEV | AD59: ='[1]Quotazioni 16-08'!D120 -> HEGGEM | AE59: ='[1]Quotazioni 16-08'!D296 -> FAZZINI | AF59: ='[1]Quotazioni 16-08'!D470 -> GIMENEZ
AD60: ='[1]Quotazioni 16-08'!D121 -> ZORTEA | AE60: ='[1]Quotazioni 16-08'!D297 -> CALÒ | AF60: ='[1]Quotazioni 16-08'!D471 -> NERES
AD61: ='[1]Quotazioni 16-08'!D122 -> VALLE | AE61: ='[1]Quotazioni 16-08'!D298 -> FRENDRUP | AF61: ='[1]Quotazioni 16-08'!D472 -> MALDINI
AD62: ='[1]Quotazioni 16-08'!D123 -> VALDEPENAS | AE62: ='[1]Quotazioni 16-08'!D299 -> FRATTESI | AF62: ='[1]Quotazioni 16-08'!D473 -> CAMARDA
AD63: ='[1]Quotazioni 16-08'!D124 -> VIERY | AE63: ='[1]Quotazioni 16-08'!D300 -> PESSINA | AF63: ='[1]Quotazioni 16-08'!D474 -> MOTA
AD64: ='[1]Quotazioni 16-08'!D125 -> MONTERISI | AE64: ='[1]Quotazioni 16-08'!D301 -> LOBOTKA | AF64: ='[1]Quotazioni 16-08'!D475 -> FRIGAN
AD65: ='[1]Quotazioni 16-08'!D126 -> MARCANDALLI | AE65: ='[1]Quotazioni 16-08'!D302 -> BERNABÈ | AF65: ='[1]Quotazioni 16-08'!D476 -> ADORANTE
AD66: ='[1]Quotazioni 16-08'!D127 -> PAVARD | AE66: ='[1]Quotazioni 16-08'!D303 -> VOLPATO | AF66: ='[1]Quotazioni 16-08'!D477 -> BORRELLI
AD67: ='[1]Quotazioni 16-08'!D128 -> TAVARES N. | AE67: ='[1]Quotazioni 16-08'!D304 -> ORISTANIO | AF67: ='[1]Quotazioni 16-08'!D478 -> MENDY P.
AD68: ='[1]Quotazioni 16-08'!D129 -> MARUSIC | AE68: ='[1]Quotazioni 16-08'!D305 -> UNAI GOMEZ | AF68: ='[1]Quotazioni 16-08'!D479 -> MORATA
AD69: ='[1]Quotazioni 16-08'!D130 -> GALLO | AE69: ='[1]Quotazioni 16-08'!D306 -> SOW | AF69: ='[1]Quotazioni 16-08'!D480 -> KVERNADZE
AD70: ='[1]Quotazioni 16-08'!D131 -> MANGAS | AE70: ='[1]Quotazioni 16-08'!D307 -> ZALEWSKI | AF70: ='[1]Quotazioni 16-08'!D481 -> HAVEL
AD71: ='[1]Quotazioni 16-08'!D132 -> BEUKEMA | AE71: ='[1]Quotazioni 16-08'!D308 -> POBEGA | AF71: ='[1]Quotazioni 16-08'!D482 -> GIOVANE
... AD88: ='[1]Quotazioni 16-08'!D149 -> PEDRAZA | AE88: ='[1]Quotazioni 16-08'!D325 -> ROMANO | AF88: ='[1]Quotazioni 16-08'!D499 -> MORO L.
AD89: ='[1]Quotazioni 16-08'!D150 -> GASPAR K. | AE89: ='[1]Quotazioni 16-08'!D326 -> FELICI
AD90: ='[1]Quotazioni 16-08'!D151 -> VEIGA D. | AE90: ='[1]Quotazioni 16-08'!D327 -> MILLA
AD91: ='[1]Quotazioni 16-08'!D152 -> OLIVERA | AE91: ='[1]Quotazioni 16-08'!D328 -> ADDAI
AD92: ='[1]Quotazioni 16-08'!D153 -> RENSCH | AE92: ='[1]Quotazioni 16-08'!D329 -> ZERBIN
AD93: ='[1]Quotazioni 16-08'!D154 -> PEDERSEN | AE93: ='[1]Quotazioni 16-08'!D330 -> MEICHTRY
AD94: ='[1]Quotazioni 16-08'!D155 -> MORENO M. | AE94: ='[1]Quotazioni 16-08'!D331 -> TRAORÈ HJ.
AD95: ='[1]Quotazioni 16-08'!D156 -> HAPS | AE95: ='[1]Quotazioni 16-08'!D332 -> MKHITARYAN
AD96: ='[1]Quotazioni 16-08'!D157 -> ZAPPA | AE96: ='[1]Quotazioni 16-08'!D333 -> KOOPMEINERS
AD97: ='[1]Quotazioni 16-08'!D158 -> SMOLCIC I. | AE97: ='[1]Quotazioni 16-08'!D334 -> DELE-BASHIRU
AD98: ='[1]Quotazioni 16-08'!D159 -> PONGRACIC | AE98: ='[1]Quotazioni 16-08'!D335 -> BERISHA M.
AD99: ='[1]Quotazioni 16-08'!D160 -> CALVANI | AE99: ='[1]Quotazioni 16-08'!D336 -> GANDELMAN
AD100: ='[1]Quotazioni 16-08'!D161 -> MITAJ | AE100: ='[1]Quotazioni 16-08'!D337 -> FOFANA Y.
... AD174: ='[1]Quotazioni 16-08'!D235 -> MISSORI | AE174: ='[1]Quotazioni 16-08'!D411 -> ANJORIN
AD175: ='[1]Quotazioni 16-08'!D236 -> PIERAGNOLO
AD176: ='[1]Quotazioni 16-08'!D237 -> MLACIC

Sheet Spesa Asta
A1: Analisi Spesa Asta per Squadra e Ruolo
A2: Crediti spesi all'asta, suddivisi per reparto. Dati dal foglio Foglio Asta.
A4: Squadra | B4: Portieri | C4: Difensori | D4: Centrocampisti | E4: Attaccanti | F4: Totale Speso
A5: Evacuo Kaka Toni | B5: =SUM('Foglio Asta'!T4:T6) -> 62 | C5: =SUM('Foglio Asta'!T7:T15) -> 54 | D5: =SUM('Foglio Asta'!T16:T24) -> 160 | E5: =SUM('Foglio Asta'!T25:T31) -> 139 | F5: =SUM(B5:E5) -> 415
A6: GC21 | B6: =SUM('Foglio Asta'!N4:N6) -> 15 | C6: =SUM('Foglio Asta'!N7:N15) -> 72 | D6: =SUM('Foglio Asta'!N16:N24) -> 160 | E6: =SUM('Foglio Asta'!N25:N31) -> 183 | F6: =SUM(B6:E6) -> 430
A7: I Bamboli | B7: =SUM('Foglio Asta'!H4:H6) -> 39 | C7: =SUM('Foglio Asta'!H7:H15) -> 63 | D7: =SUM('Foglio Asta'!H16:H24) -> 129 | E7: =SUM('Foglio Asta'!H25:H31) -> 182 | F7: =SUM(B7:E7) -> 413
A8: Incontro al capitano | B8: =SUM('Foglio Asta'!D4:D6) -> 65 | C8: =SUM('Foglio Asta'!D7:D15) -> 103 | D8: =SUM('Foglio Asta'!D16:D24) -> 144 | E8: =SUM('Foglio Asta'!D25:D31) -> 112 | F8: =SUM(B8:E8) -> 424
A9: Mancinix | B9: =SUM('Foglio Asta'!J4:J6) -> 54 | C9: =SUM('Foglio Asta'!J7:J15) -> 72 | D9: =SUM('Foglio Asta'!J16:J24) -> 149 | E9: =SUM('Foglio Asta'!J25:J31) -> 153 | F9: =SUM(B9:E9) -> 428
A10: Masterchef FC | B10: =SUM('Foglio Asta'!P4:P6) -> 19 | C10: =SUM('Foglio Asta'!P7:P15) -> 50 | D10: =SUM('Foglio Asta'!P16:P24) -> 134 | E10: =SUM('Foglio Asta'!P25:P31) -> 227 | F10: =SUM(B10:E10) -> 430
A11: Outletico Palermo | B11: =SUM('Foglio Asta'!L4:L6) -> 60 | C11: =SUM('Foglio Asta'!L7:L15) -> 38 | D11: =SUM('Foglio Asta'!L16:L24) -> 115 | E11: =SUM('Foglio Asta'!L25:L31) -> 212 | F11: =SUM(B11:E11) -> 425
A12: Paris Saint-Gervasoni | B12: =SUM('Foglio Asta'!B4:B6) -> 34 | C12: =SUM('Foglio Asta'!B7:B15) -> 57 | D12: =SUM('Foglio Asta'!B16:B24) -> 166 | E12: =SUM('Foglio Asta'!B25:B31) -> 169 | F12: =SUM(B12:E12) -> 426
A13: Schalke 104 | B13: =SUM('Foglio Asta'!R4:R6) -> 57 | C13: =SUM('Foglio Asta'!R7:R15) -> 62 | D13: =SUM('Foglio Asta'!R16:R24) -> 117 | E13: =SUM('Foglio Asta'!R25:R31) -> 194 | F13: =SUM(B13:E13) -> 430
A14: SuperGregariana | B14: =SUM('Foglio Asta'!F4:F6) -> 51 | C14: =SUM('Foglio Asta'!F7:F15) -> 92 | D14: =SUM('Foglio Asta'!F16:F24) -> 175 | E14: =SUM('Foglio Asta'!F25:F31) -> 110 | F14: =SUM(B14:E14) -> 428
A16: Legenda
A17: Portieri: somma dei crediti delle 3 righe portiere di ogni squadra (Foglio Asta righe 4-6)
A18: Difensori: somma dei crediti dei 9 difensori (Foglio Asta righe 7-15, inclusa la riga DIF PRIMAVERA)
A19: Centrocampisti: somma dei crediti dei 9 centrocampisti (Foglio Asta righe 16-24, inclusa la riga CEN PRIMAVERA)
A20: Attaccanti: somma dei crediti dei 7 attaccanti (Foglio Asta righe 25-31, inclusa la riga ATT PRIMAVERA)
A21: Totale Speso: somma dei 4 reparti. I nomi squadra sono normalizzati come nel foglio Database.

Sheet Squadra
A1: Scheda Squadra
A3: Squadra: | B3: GC21
A4: Seleziona la squadra dal menu a tendina in B3: tutta la scheda si aggiorna automaticamente.
A6: BonusMalus (voti utili) | D6: Media Voto (voti utili)
A7: ='Analisi Bonus'!B$4 -> Portieri (VU) | B7: =IFERROR(INDEX('Analisi Bonus'!$B$5:$B$14,MATCH($B$3,'Analisi Bonus'!$A$5:$A$14,0)),"n.d.") -> -9 | D7: ='Analisi Voto'!B$4 -> Portieri (VU) | E7: =IFERROR(INDEX('Analisi Voto'!$B$5:$B$14,MATCH($B$3,'Analisi Voto'!$A$5:$A$14,0)),"n.d.") -> 5.8333333
A8: ='Analisi Bonus'!C$4 -> Difensori (VU) | B8: =IFERROR(INDEX('Analisi Bonus'!$C$5:$C$14,MATCH($B$3,'Analisi Bonus'!$A$5:$A$14,0)),"n.d.") -> 7.5 | D8: ='Analisi Voto'!C$4 -> Difensori (VU) | E8: =IFERROR(INDEX('Analisi Voto'!$C$5:$C$14,MATCH($B$3,'Analisi Voto'!$A$5:$A$14,0)),"n.d.") -> 6.2142857
A9: ='Analisi Bonus'!D$4 -> Centrocampisti (VU) | B9: =IFERROR(INDEX('Analisi Bonus'!$D$5:$D$14,MATCH($B$3,'Analisi Bonus'!$A$5:$A$14,0)),"n.d.") -> 11.5 | D9: ='Analisi Voto'!D$4 -> Centrocampisti (VU) | E9: =IFERROR(INDEX('Analisi Voto'!$D$5:$D$14,MATCH($B$3,'Analisi Voto'!$A$5:$A$14,0)),"n.d.") -> 6.0217391
A10: ='Analisi Bonus'!E$4 -> Attaccanti (VU) | B10: =IFERROR(INDEX('Analisi Bonus'!$E$5:$E$14,MATCH($B$3,'Analisi Bonus'!$A$5:$A$14,0)),"n.d.") -> 16.5 | D10: ='Analisi Voto'!E$4 -> Attaccanti (VU) | E10: =IFERROR(INDEX('Analisi Voto'!$E$5:$E$14,MATCH($B$3,'Analisi Voto'!$A$5:$A$14,0)),"n.d.") -> 6.09375
A11: ='Analisi Bonus'!F$4 -> Totale Voti Utili | B11: =IFERROR(INDEX('Analisi Bonus'!$F$5:$F$14,MATCH($B$3,'Analisi Bonus'!$A$5:$A$14,0)),"n.d.") -> 26.5 | D11: ='Analisi Voto'!F$4 -> Media Voti Utili | E11: =IFERROR(INDEX('Analisi Voto'!$F$5:$F$14,MATCH($B$3,'Analisi Voto'!$A$5:$A$14,0)),"n.d.") -> 6.0833333
A12: ='Analisi Bonus'!G$4 -> Subentrati | B12: =IFERROR(INDEX('Analisi Bonus'!$G$5:$G$14,MATCH($B$3,'Analisi Bonus'!$A$5:$A$14,0)),"n.d.") -> 2 | D12: ='Analisi Voto'!G$4 -> Subentrati | E12: =IFERROR(INDEX('Analisi Voto'!$G$5:$G$14,MATCH($B$3,'Analisi Voto'!$A$5:$A$14,0)),"n.d.") -> 6
A13: ='Analisi Bonus'!H$4 -> Panchinari (no P) | B13: =IFERROR(INDEX('Analisi Bonus'!$H$5:$H$14,MATCH($B$3,'Analisi Bonus'!$A$5:$A$14,0)),"n.d.") -> 12 | D13: ='Analisi Voto'!H$4 -> Panchinari (no P) | E13: =IFERROR(INDEX('Analisi Voto'!$H$5:$H$14,MATCH($B$3,'Analisi Voto'!$A$5:$A$14,0)),"n.d.") -> 6.0729167
A16: Valore di Mercato (VdM) dei voti utili, per giornata
A17: Media VdM | B17: =IFERROR(INDEX('Analisi VdM'!$B$5:$B$14,MATCH($B$3,'Analisi VdM'!$A$5:$A$14,0)),"n.d.") -> 300.83333
A18: VdM max | B18: =IFERROR(MAX($B$22:$AM$22),"n.d.") -> 383
A19: VdM min | B19: =IFERROR(MIN($B$22:$AM$22),"n.d.") -> 255
A20: Ultima giornata | B20: =IFERROR(LOOKUP(9.99E+307,$B$22:$AM$22),"n.d.") -> 322.5
A21: Giornata | B21: {=_xlfn.ANCHORARRAY('Analisi VdM'!C4)} -> 1 | C21: 2 | D21: 3 | E21: 4 | F21: 5 | G21: 6 | H21: 7 | I21: 8 | J21: 9 | K21: 10 | L21: 11 | M21: 12 | N21: 13 | O21: 14 | P21: 15 | Q21: 16 | R21: 17 | S21: 18 | T21: 19 | U21: 20 | V21: 21 | W21: 22 | X21: 23 | Y21: 24 | Z21: 25 | AA21: 26 | AB21: 27 | AC21: 28 | AD21: 29 | AE21: 30 | AF21: 31 | AG21: 32 | AH21: 33 | AI21: 34 | AJ21: 35 | AK21: 36 | AL21: 37 | AM21: 38
A22: VdM | B22: {=IFERROR(INDEX('Analisi VdM'!$C$5:$AN$14,MATCH($B$3,'Analisi VdM'!$A$5:$A$14,0),0),"")} -> 383 | C22: 306 | D22: 255 | E22: 262 | F22: 276.5 | G22: 322.5 | BB22: Giornate chiuse | BC22: =MAX(Fantacalcio[Giornata]) -> 6
BB23: Presenze minime (1/4, arrotondato) | BC23: =MAX(1,ROUND($BC$22/4,0)) -> 2
A25: Top 11
A26: Modulo 3-4-3: 1 portiere, 3 difensori, 4 centrocampisti, 3 attaccanti. Selezione per media Fantavoto piu' alta sulle sole giornate con Voto Utile = SI. | BB26: Area di calcolo (elenco giocatori con Voto Utile = SI della squadra selezionata)
A27: Ruolo | B27: Giocatore | C27: Fantavoto | D27: BonusMalus | E27: VdM | F27: Partite | BB27: Giocatore | BC27: Ruolo | BD27: MediaFantavoto | BE27: SommaBonusMalus | BF27: VdM inizio | BG27: Partite
A28: P | B28: {=IFERROR(INDEX(_xlfn._xlws.SORT(_xlfn._xlws.FILTER($BB$28:$BD$127,($BC$28:$BC$127=$A28)*($BB$28:$BB$127<>"")*($BG$28:$BG$127>=$BC$23)),3,-1),1,1),"n.d.")} -> Palmisani | C28: =IF($B28="n.d.","n.d.",IFERROR(INDEX($BD$28:$BD$127,MATCH($B28,$BB$28:$BB$127,0)),"n.d.")) -> 5 | D28: =IF($B28="n.d.","n.d.",IFERROR(INDEX($BE$28:$BE$127,MATCH($B28,$BB$28:$BB$127,0)),"n.d.")) -> -4 | E28: =IF($B28="n.d.","n.d.",IFERROR(INDEX($BF$28:$BF$127,MATCH($B28,$BB$28:$BB$127,0)),"n.d.")) -> 6 | F28: =IF($B28="n.d.","n.d.",COUNTIFS(Fantacalcio[Squadra],$B$3,Fantacalcio[Giocatore],$B28,Fantacalcio[VotoUtile],"SI")) -> 3 | BB28: {=IFERROR(_xlfn._xlws.SORT(_xlfn.UNIQUE(_xlfn._xlws.FILTER(Fantacalcio[Giocatore],(Fantacalcio[Squadra]=$B$3)*(Fantacalcio[VotoUtile]="SI")))),"")} -> Bellanova | BC28: {=IF($BB28="","",INDEX(Fantacalcio[Ruolo],MATCH(1,(Fantacalcio[Squadra]=$B$3)*(Fantacalcio[Giocatore]=$BB28),0)))} -> D | BD28: =IF($BB28="","",AVERAGEIFS(Fantacalcio[Fantavoto],Fantacalcio[Squadra],$B$3,Fantacalcio[Giocatore],$BB28,Fantacalcio[VotoUtile],"SI")) -> 6.1666667 | BE28: =IF($BB28="","",SUMIFS(Fantacalcio[BonusMalus],Fantacalcio[Squadra],$B$3,Fantacalcio[Giocatore],$BB28,Fantacalcio[VotoUtile],"SI")) -> -0.5 | BF28: {=IF($BB28="","",IFERROR(INDEX(Mappa[VdM (mln €)],MATCH(1,(Mappa[Giocatore_DB]=$BB28)*(Mappa[Ruolo_DB]=$BC28),0)),"n.d."))} -> 15 | BG28: =IF($BB28="","",COUNTIFS(Fantacalcio[Squadra],$B$3,Fantacalcio[Giocatore],$BB28,Fantacalcio[VotoUtile],"SI")) -> 3
A29: D | B29: {=IFERROR(INDEX(_xlfn._xlws.SORT(_xlfn._xlws.FILTER($BB$28:$BD$127,($BC$28:$BC$127=$A29)*($BB$28:$BB$127<>"")*($BG$28:$BG$127>=$BC$23)),3,-1),1,1),"n.d.")} -> Bisseck | C29: =IF($B29="n.d.","n.d.",IFERROR(INDEX($BD$28:$BD$127,MATCH($B29,$BB$28:$BB$127,0)),"n.d.")) -> 7.25 | D29: =IF($B29="n.d.","n.d.",IFERROR(INDEX($BE$28:$BE$127,MATCH($B29,$BB$28:$BB$127,0)),"n.d.")) -> 3 | E29: =IF($B29="n.d.","n.d.",IFERROR(INDEX($BF$28:$BF$127,MATCH($B29,$BB$28:$BB$127,0)),"n.d.")) -> 50 | F29: =IF($B29="n.d.","n.d.",COUNTIFS(Fantacalcio[Squadra],$B$3,Fantacalcio[Giocatore],$B29,Fantacalcio[VotoUtile],"SI")) -> 4 | BB29: Bisseck | BC29: {=IF($BB29="","",INDEX(Fantacalcio[Ruolo],MATCH(1,(Fantacalcio[Squadra]=$B$3)*(Fantacalcio[Giocatore]=$BB29),0)))} -> D | BD29: =IF($BB29="","",AVERAGEIFS(Fantacalcio[Fantavoto],Fantacalcio[Squadra],$B$3,Fantacalcio[Giocatore],$BB29,Fantacalcio[VotoUtile],"SI")) -> 7.25 | BE29: =IF($BB29="","",SUMIFS(Fantacalcio[BonusMalus],Fantacalcio[Squadra],$B$3,Fantacalcio[Giocatore],$BB29,Fantacalcio[VotoUtile],"SI")) -> 3 | BF29: {=IF($BB29="","",IFERROR(INDEX(Mappa[VdM (mln €)],MATCH(1,(Mappa[Giocatore_DB]=$BB29)*(Mappa[Ruolo_DB]=$BC29),0)),"n.d."))} -> 50 | BG29: =IF($BB29="","",COUNTIFS(Fantacalcio[Squadra],$B$3,Fantacalcio[Giocatore],$BB29,Fantacalcio[VotoUtile],"SI")) -> 4
A30: D | B30: {=IFERROR(INDEX(_xlfn._xlws.SORT(_xlfn._xlws.FILTER($BB$28:$BD$127,($BC$28:$BC$127=$A30)*($BB$28:$BB$127<>"")*($BG$28:$BG$127>=$BC$23)),3,-1),2,1),"n.d.")} -> Ramon | C30: =IF($B30="n.d.","n.d.",IFERROR(INDEX($BD$28:$BD$127,MATCH($B30,$BB$28:$BB$127,0)),"n.d.")) -> 7.125 | D30: =IF($B30="n.d.","n.d.",IFERROR(INDEX($BE$28:$BE$127,MATCH($B30,$BB$28:$BB$127,0)),"n.d.")) -> 3 | E30: =IF($B30="n.d.","n.d.",IFERROR(INDEX($BF$28:$BF$127,MATCH($B30,$BB$28:$BB$127,0)),"n.d.")) -> 45 | F30: =IF($B30="n.d.","n.d.",COUNTIFS(Fantacalcio[Squadra],$B$3,Fantacalcio[Giocatore],$B30,Fantacalcio[VotoUtile],"SI")) -> 4 | BB30: Cambiaso | BC30: {=IF($BB30="","",INDEX(Fantacalcio[Ruolo],MATCH(1,(Fantacalcio[Squadra]=$B$3)*(Fantacalcio[Giocatore]=$BB30),0)))} -> D | BD30: =IF($BB30="","",AVERAGEIFS(Fantacalcio[Fantavoto],Fantacalcio[Squadra],$B$3,Fantacalcio[Giocatore],$BB30,Fantacalcio[VotoUtile],"SI")) -> 5.25 | BE30: =IF($BB30="","",SUMIFS(Fantacalcio[BonusMalus],Fantacalcio[Squadra],$B$3,Fantacalcio[Giocatore],$BB30,Fantacalcio[VotoUtile],"SI")) -> -0.5 | BF30: {=IF($BB30="","",IFERROR(INDEX(Mappa[VdM (mln €)],MATCH(1,(Mappa[Giocatore_DB]=$BB30)*(Mappa[Ruolo_DB]=$BC30),0)),"n.d."))} -> 15 | BG30: =IF($BB30="","",COUNTIFS(Fantacalcio[Squadra],$B$3,Fantacalcio[Giocatore],$BB30,Fantacalcio[VotoUtile],"SI")) -> 2
A31: D | B31: {=IFERROR(INDEX(_xlfn._xlws.SORT(_xlfn._xlws.FILTER($BB$28:$BD$127,($BC$28:$BC$127=$A31)*($BB$28:$BB$127<>"")*($BG$28:$BG$127>=$BC$23)),3,-1),3,1),"n.d.")} -> Mancini | C31: =IF($B31="n.d.","n.d.",IFERROR(INDEX($BD$28:$BD$127,MATCH($B31,$BB$28:$BB$127,0)),"n.d.")) -> 6.5 | D31: =IF($B31="n.d.","n.d.",IFERROR(INDEX($BE$28:$BE$127,MATCH($B31,$BB$28:$BB$127,0)),"n.d.")) -> 1 | E31: =IF($B31="n.d.","n.d.",IFERROR(INDEX($BF$28:$BF$127,MATCH($B31,$BB$28:$BB$127,0)),"n.d.")) -> 15 | F31: =IF($B31="n.d.","n.d.",COUNTIFS(Fantacalcio[Squadra],$B$3,Fantacalcio[Giocatore],$B31,Fantacalcio[VotoUtile],"SI")) -> 4 | BB31: Colombo | BC31: {=IF($BB31="","",INDEX(Fantacalcio[Ruolo],MATCH(1,(Fantacalcio[Squadra]=$B$3)*(Fantacalcio[Giocatore]=$BB31),0)))} -> A | BD31: =IF($BB31="","",AVERAGEIFS(Fantacalcio[Fantavoto],Fantacalcio[Squadra],$B$3,Fantacalcio[Giocatore],$BB31,Fantacalcio[VotoUtile],"SI")) -> 2 | BE31: =IF($BB31="","",SUMIFS(Fantacalcio[BonusMalus],Fantacalcio[Squadra],$B$3,Fantacalcio[Giocatore],$BB31,Fantacalcio[VotoUtile],"SI")) -> -3 | BF31: {=IF($BB31="","",IFERROR(INDEX(Mappa[VdM (mln €)],MATCH(1,(Mappa[Giocatore_DB]=$BB31)*(Mappa[Ruolo_DB]=$BC31),0)),"n.d."))} -> 10 | BG31: =IF($BB31="","",COUNTIFS(Fantacalcio[Squadra],$B$3,Fantacalcio[Giocatore],$BB31,Fantacalcio[VotoUtile],"SI")) -> 1
A32: C | B32: {=IFERROR(INDEX(_xlfn._xlws.SORT(_xlfn._xlws.FILTER($BB$28:$BD$127,($BC$28:$BC$127=$A32)*($BB$28:$BB$127<>"")*($BG$28:$BG$127>=$BC$23)),3,-1),1,1),"n.d.")} -> Mastantuono | C32: =IF($B32="n.d.","n.d.",IFERROR(INDEX($BD$28:$BD$127,MATCH($B32,$BB$28:$BB$127,0)),"n.d.")) -> 7.4166667 | D32: =IF($B32="n.d.","n.d.",IFERROR(INDEX($BE$28:$BE$127,MATCH($B32,$BB$28:$BB$127,0)),"n.d.")) -> 8.5 | E32: =IF($B32="n.d.","n.d.",IFERROR(INDEX($BF$28:$BF$127,MATCH($B32,$BB$28:$BB$127,0)),"n.d.")) -> 45 | F32: =IF($B32="n.d.","n.d.",COUNTIFS(Fantacalcio[Squadra],$B$3,Fantacalcio[Giocatore],$B32,Fantacalcio[VotoUtile],"SI")) -> 6 | BB32: Cristante | BC32: {=IF($BB32="","",INDEX(Fantacalcio[Ruolo],MATCH(1,(Fantacalcio[Squadra]=$B$3)*(Fantacalcio[Giocatore]=$BB32),0)))} -> C | BD32: =IF($BB32="","",AVERAGEIFS(Fantacalcio[Fantavoto],Fantacalcio[Squadra],$B$3,Fantacalcio[Giocatore],$BB32,Fantacalcio[VotoUtile],"SI")) -> 6.5 | BE32: =IF($BB32="","",SUMIFS(Fantacalcio[BonusMalus],Fantacalcio[Squadra],$B$3,Fantacalcio[Giocatore],$BB32,Fantacalcio[VotoUtile],"SI")) -> 0 | BF32: {=IF($BB32="","",IFERROR(INDEX(Mappa[VdM (mln €)],MATCH(1,(Mappa[Giocatore_DB]=$BB32)*(Mappa[Ruolo_DB]=$BC32),0)),"n.d."))} -> 7 | BG32: =IF($BB32="","",COUNTIFS(Fantacalcio[Squadra],$B$3,Fantacalcio[Giocatore],$BB32,Fantacalcio[VotoUtile],"SI")) -> 1
A33: C | B33: {=IFERROR(INDEX(_xlfn._xlws.SORT(_xlfn._xlws.FILTER($BB$28:$BD$127,($BC$28:$BC$127=$A33)*($BB$28:$BB$127<>"")*($BG$28:$BG$127>=$BC$23)),3,-1),2,1),"n.d.")} -> Mandragora | C33: =IF($B33="n.d.","n.d.",IFERROR(INDEX($BD$28:$BD$127,MATCH($B33,$BB$28:$BB$127,0)),"n.d.")) -> 6.6666667 | D33: =IF($B33="n.d.","n.d.",IFERROR(INDEX($BE$28:$BE$127,MATCH($B33,$BB$28:$BB$127,0)),"n.d.")) -> 1 | E33: =IF($B33="n.d.","n.d.",IFERROR(INDEX($BF$28:$BF$127,MATCH($B33,$BB$28:$BB$127,0)),"n.d.")) -> 7.5 | F33: =IF($B33="n.d.","n.d.",COUNTIFS(Fantacalcio[Squadra],$B$3,Fantacalcio[Giocatore],$B33,Fantacalcio[VotoUtile],"SI")) -> 3 | BB33: De Winter | BC33: {=IF($BB33="","",INDEX(Fantacalcio[Ruolo],MATCH(1,(Fantacalcio[Squadra]=$B$3)*(Fantacalcio[Giocatore]=$BB33),0)))} -> D | BD33: =IF($BB33="","",AVERAGEIFS(Fantacalcio[Fantavoto],Fantacalcio[Squadra],$B$3,Fantacalcio[Giocatore],$BB33,Fantacalcio[VotoUtile],"SI")) -> 5.75 | BE33: =IF($BB33="","",SUMIFS(Fantacalcio[BonusMalus],Fantacalcio[Squadra],$B$3,Fantacalcio[Giocatore],$BB33,Fantacalcio[VotoUtile],"SI")) -> -0.5 | BF33: {=IF($BB33="","",IFERROR(INDEX(Mappa[VdM (mln €)],MATCH(1,(Mappa[Giocatore_DB]=$BB33)*(Mappa[Ruolo_DB]=$BC33),0)),"n.d."))} -> 25 | BG33: =IF($BB33="","",COUNTIFS(Fantacalcio[Squadra],$B$3,Fantacalcio[Giocatore],$BB33,Fantacalcio[VotoUtile],"SI")) -> 2
A34: C | B34: {=IFERROR(INDEX(_xlfn._xlws.SORT(_xlfn._xlws.FILTER($BB$28:$BD$127,($BC$28:$BC$127=$A34)*($BB$28:$BB$127<>"")*($BG$28:$BG$127>=$BC$23)),3,-1),3,1),"n.d.")} -> Ferguson | C34: =IF($B34="n.d.","n.d.",IFERROR(INDEX($BD$28:$BD$127,MATCH($B34,$BB$28:$BB$127,0)),"n.d.")) -> 6 | D34: =IF($B34="n.d.","n.d.",IFERROR(INDEX($BE$28:$BE$127,MATCH($B34,$BB$28:$BB$127,0)),"n.d.")) -> 0 | E34: =IF($B34="n.d.","n.d.",IFERROR(INDEX($BF$28:$BF$127,MATCH($B34,$BB$28:$BB$127,0)),"n.d.")) -> 14 | F34: =IF($B34="n.d.","n.d.",COUNTIFS(Fantacalcio[Squadra],$B$3,Fantacalcio[Giocatore],$B34,Fantacalcio[VotoUtile],"SI")) -> 3 | BB34: Ederson D.S. | BC34: {=IF($BB34="","",INDEX(Fantacalcio[Ruolo],MATCH(1,(Fantacalcio[Squadra]=$B$3)*(Fantacalcio[Giocatore]=$BB34),0)))} -> C | BD34: =IF($BB34="","",AVERAGEIFS(Fantacalcio[Fantavoto],Fantacalcio[Squadra],$B$3,Fantacalcio[Giocatore],$BB34,Fantacalcio[VotoUtile],"SI")) -> 5.8 | BE34: =IF($BB34="","",SUMIFS(Fantacalcio[BonusMalus],Fantacalcio[Squadra],$B$3,Fantacalcio[Giocatore],$BB34,Fantacalcio[VotoUtile],"SI")) -> 0 | BF34: {=IF($BB34="","",IFERROR(INDEX(Mappa[VdM (mln €)],MATCH(1,(Mappa[Giocatore_DB]=$BB34)*(Mappa[Ruolo_DB]=$BC34),0)),"n.d."))} -> 40 | BG34: =IF($BB34="","",COUNTIFS(Fantacalcio[Squadra],$B$3,Fantacalcio[Giocatore],$BB34,Fantacalcio[VotoUtile],"SI")) -> 5
A35: C | B35: {=IFERROR(INDEX(_xlfn._xlws.SORT(_xlfn._xlws.FILTER($BB$28:$BD$127,($BC$28:$BC$127=$A35)*($BB$28:$BB$127<>"")*($BG$28:$BG$127>=$BC$23)),3,-1),4,1),"n.d.")} -> Ederson D.S. | C35: =IF($B35="n.d.","n.d.",IFERROR(INDEX($BD$28:$BD$127,MATCH($B35,$BB$28:$BB$127,0)),"n.d.")) -> 5.8 | D35: =IF($B35="n.d.","n.d.",IFERROR(INDEX($BE$28:$BE$127,MATCH($B35,$BB$28:$BB$127,0)),"n.d.")) -> 0 | E35: =IF($B35="n.d.","n.d.",IFERROR(INDEX($BF$28:$BF$127,MATCH($B35,$BB$28:$BB$127,0)),"n.d.")) -> 40 | F35: =IF($B35="n.d.","n.d.",COUNTIFS(Fantacalcio[Squadra],$B$3,Fantacalcio[Giocatore],$B35,Fantacalcio[VotoUtile],"SI")) -> 5 | BB35: Esposito F.P. | BC35: {=IF($BB35="","",INDEX(Fantacalcio[Ruolo],MATCH(1,(Fantacalcio[Squadra]=$B$3)*(Fantacalcio[Giocatore]=$BB35),0)))} -> A | BD35: =IF($BB35="","",AVERAGEIFS(Fantacalcio[Fantavoto],Fantacalcio[Squadra],$B$3,Fantacalcio[Giocatore],$BB35,Fantacalcio[VotoUtile],"SI")) -> 7.9 | BE35: =IF($BB35="","",SUMIFS(Fantacalcio[BonusMalus],Fantacalcio[Squadra],$B$3,Fantacalcio[Giocatore],$BB35,Fantacalcio[VotoUtile],"SI")) -> 7 | BF35: {=IF($BB35="","",IFERROR(INDEX(Mappa[VdM (mln €)],MATCH(1,(Mappa[Giocatore_DB]=$BB35)*(Mappa[Ruolo_DB]=$BC35),0)),"n.d."))} -> 50 | BG35: =IF($BB35="","",COUNTIFS(Fantacalcio[Squadra],$B$3,Fantacalcio[Giocatore],$BB35,Fantacalcio[VotoUtile],"SI")) -> 5
A36: A | B36: {=IFERROR(INDEX(_xlfn._xlws.SORT(_xlfn._xlws.FILTER($BB$28:$BD$127,($BC$28:$BC$127=$A36)*($BB$28:$BB$127<>"")*($BG$28:$BG$127>=$BC$23)),3,-1),1,1),"n.d.")} -> Krstovic | C36: =IF($B36="n.d.","n.d.",IFERROR(INDEX($BD$28:$BD$127,MATCH($B36,$BB$28:$BB$127,0)),"n.d.")) -> 8.2 | D36: =IF($B36="n.d.","n.d.",IFERROR(INDEX($BE$28:$BE$127,MATCH($B36,$BB$28:$BB$127,0)),"n.d.")) -> 9.5 | E36: =IF($B36="n.d.","n.d.",IFERROR(INDEX($BF$28:$BF$127,MATCH($B36,$BB$28:$BB$127,0)),"n.d.")) -> 30 | F36: =IF($B36="n.d.","n.d.",COUNTIFS(Fantacalcio[Squadra],$B$3,Fantacalcio[Giocatore],$B36,Fantacalcio[VotoUtile],"SI")) -> 5 | BB36: Ferguson | BC36: {=IF($BB36="","",INDEX(Fantacalcio[Ruolo],MATCH(1,(Fantacalcio[Squadra]=$B$3)*(Fantacalcio[Giocatore]=$BB36),0)))} -> C | BD36: =IF($BB36="","",AVERAGEIFS(Fantacalcio[Fantavoto],Fantacalcio[Squadra],$B$3,Fantacalcio[Giocatore],$BB36,Fantacalcio[VotoUtile],"SI")) -> 6 | BE36: =IF($BB36="","",SUMIFS(Fantacalcio[BonusMalus],Fantacalcio[Squadra],$B$3,Fantacalcio[Giocatore],$BB36,Fantacalcio[VotoUtile],"SI")) -> 0 | BF36: {=IF($BB36="","",IFERROR(INDEX(Mappa[VdM (mln €)],MATCH(1,(Mappa[Giocatore_DB]=$BB36)*(Mappa[Ruolo_DB]=$BC36),0)),"n.d."))} -> 14 | BG36: =IF($BB36="","",COUNTIFS(Fantacalcio[Squadra],$B$3,Fantacalcio[Giocatore],$BB36,Fantacalcio[VotoUtile],"SI")) -> 3
A37: A | B37: {=IFERROR(INDEX(_xlfn._xlws.SORT(_xlfn._xlws.FILTER($BB$28:$BD$127,($BC$28:$BC$127=$A37)*($BB$28:$BB$127<>"")*($BG$28:$BG$127>=$BC$23)),3,-1),2,1),"n.d.")} -> Esposito F.P. | C37: =IF($B37="n.d.","n.d.",IFERROR(INDEX($BD$28:$BD$127,MATCH($B37,$BB$28:$BB$127,0)),"n.d.")) -> 7.9 | D37: =IF($B37="n.d.","n.d.",IFERROR(INDEX($BE$28:$BE$127,MATCH($B37,$BB$28:$BB$127,0)),"n.d.")) -> 7 | E37: =IF($B37="n.d.","n.d.",IFERROR(INDEX($BF$28:$BF$127,MATCH($B37,$BB$28:$BB$127,0)),"n.d.")) -> 50 | F37: =IF($B37="n.d.","n.d.",COUNTIFS(Fantacalcio[Squadra],$B$3,Fantacalcio[Giocatore],$B37,Fantacalcio[VotoUtile],"SI")) -> 5 | BB37: Krstovic | BC37: {=IF($BB37="","",INDEX(Fantacalcio[Ruolo],MATCH(1,(Fantacalcio[Squadra]=$B$3)*(Fantacalcio[Giocatore]=$BB37),0)))} -> A | BD37: =IF($BB37="","",AVERAGEIFS(Fantacalcio[Fantavoto],Fantacalcio[Squadra],$B$3,Fantacalcio[Giocatore],$BB37,Fantacalcio[VotoUtile],"SI")) -> 8.2 | BE37: =IF($BB37="","",SUMIFS(Fantacalcio[BonusMalus],Fantacalcio[Squadra],$B$3,Fantacalcio[Giocatore],$BB37,Fantacalcio[VotoUtile],"SI")) -> 9.5 | BF37: {=IF($BB37="","",IFERROR(INDEX(Mappa[VdM (mln €)],MATCH(1,(Mappa[Giocatore_DB]=$BB37)*(Mappa[Ruolo_DB]=$BC37),0)),"n.d."))} -> 30 | BG37: =IF($BB37="","",COUNTIFS(Fantacalcio[Squadra],$B$3,Fantacalcio[Giocatore],$BB37,Fantacalcio[VotoUtile],"SI")) -> 5
A38: A | B38: {=IFERROR(INDEX(_xlfn._xlws.SORT(_xlfn._xlws.FILTER($BB$28:$BD$127,($BC$28:$BC$127=$A38)*($BB$28:$BB$127<>"")*($BG$28:$BG$127>=$BC$23)),3,-1),3,1),"n.d.")} -> Pellegrino M. | C38: =IF($B38="n.d.","n.d.",IFERROR(INDEX($BD$28:$BD$127,MATCH($B38,$BB$28:$BB$127,0)),"n.d.")) -> 6.5 | D38: =IF($B38="n.d.","n.d.",IFERROR(INDEX($BE$28:$BE$127,MATCH($B38,$BB$28:$BB$127,0)),"n.d.")) -> 3 | E38: =IF($B38="n.d.","n.d.",IFERROR(INDEX($BF$28:$BF$127,MATCH($B38,$BB$28:$BB$127,0)),"n.d.")) -> 22 | F38: =IF($B38="n.d.","n.d.",COUNTIFS(Fantacalcio[Squadra],$B$3,Fantacalcio[Giocatore],$B38,Fantacalcio[VotoUtile],"SI")) -> 3 | BB38: Mancini | BC38: {=IF($BB38="","",INDEX(Fantacalcio[Ruolo],MATCH(1,(Fantacalcio[Squadra]=$B$3)*(Fantacalcio[Giocatore]=$BB38),0)))} -> D | BD38: =IF($BB38="","",AVERAGEIFS(Fantacalcio[Fantavoto],Fantacalcio[Squadra],$B$3,Fantacalcio[Giocatore],$BB38,Fantacalcio[VotoUtile],"SI")) -> 6.5 | BE38: =IF($BB38="","",SUMIFS(Fantacalcio[BonusMalus],Fantacalcio[Squadra],$B$3,Fantacalcio[Giocatore],$BB38,Fantacalcio[VotoUtile],"SI")) -> 1 | BF38: {=IF($BB38="","",IFERROR(INDEX(Mappa[VdM (mln €)],MATCH(1,(Mappa[Giocatore_DB]=$BB38)*(Mappa[Ruolo_DB]=$BC38),0)),"n.d."))} -> 15 | BG38: =IF($BB38="","",COUNTIFS(Fantacalcio[Squadra],$B$3,Fantacalcio[Giocatore],$BB38,Fantacalcio[VotoUtile],"SI")) -> 4
A39: Totale | B39: Media FV / Somma BM / Somma VdM | C39: =IFERROR(AVERAGE(C28:C38),"n.d.") -> 6.7598485 | D39: =IFERROR(SUM(D28:D38),"n.d.") -> 32 | E39: =IFERROR(SUM(E28:E38),"n.d.") -> 324.5 | F39: =IFERROR(SUM(F28:F38),"n.d.") -> 45 | BB39: Mandragora | BC39: {=IF($BB39="","",INDEX(Fantacalcio[Ruolo],MATCH(1,(Fantacalcio[Squadra]=$B$3)*(Fantacalcio[Giocatore]=$BB39),0)))} -> C | BD39: =IF($BB39="","",AVERAGEIFS(Fantacalcio[Fantavoto],Fantacalcio[Squadra],$B$3,Fantacalcio[Giocatore],$BB39,Fantacalcio[VotoUtile],"SI")) -> 6.6666667 | BE39: =IF($BB39="","",SUMIFS(Fantacalcio[BonusMalus],Fantacalcio[Squadra],$B$3,Fantacalcio[Giocatore],$BB39,Fantacalcio[VotoUtile],"SI")) -> 1 | BF39: {=IF($BB39="","",IFERROR(INDEX(Mappa[VdM (mln €)],MATCH(1,(Mappa[Giocatore_DB]=$BB39)*(Mappa[Ruolo_DB]=$BC39),0)),"n.d."))} -> 7.5 | BG39: =IF($BB39="","",COUNTIFS(Fantacalcio[Squadra],$B$3,Fantacalcio[Giocatore],$BB39,Fantacalcio[VotoUtile],"SI")) -> 3
BB40: Mastantuono | BC40: {=IF($BB40="","",INDEX(Fantacalcio[Ruolo],MATCH(1,(Fantacalcio[Squadra]=$B$3)*(Fantacalcio[Giocatore]=$BB40),0)))} -> C | BD40: =IF($BB40="","",AVERAGEIFS(Fantacalcio[Fantavoto],Fantacalcio[Squadra],$B$3,Fantacalcio[Giocatore],$BB40,Fantacalcio[VotoUtile],"SI")) -> 7.4166667 | BE40: =IF($BB40="","",SUMIFS(Fantacalcio[BonusMalus],Fantacalcio[Squadra],$B$3,Fantacalcio[Giocatore],$BB40,Fantacalcio[VotoUtile],"SI")) -> 8.5 | BF40: {=IF($BB40="","",IFERROR(INDEX(Mappa[VdM (mln €)],MATCH(1,(Mappa[Giocatore_DB]=$BB40)*(Mappa[Ruolo_DB]=$BC40),0)),"n.d."))} -> 45 | BG40: =IF($BB40="","",COUNTIFS(Fantacalcio[Squadra],$B$3,Fantacalcio[Giocatore],$BB40,Fantacalcio[VotoUtile],"SI")) -> 6
A41: Legenda | BB41: McTominay | BC41: {=IF($BB41="","",INDEX(Fantacalcio[Ruolo],MATCH(1,(Fantacalcio[Squadra]=$B$3)*(Fantacalcio[Giocatore]=$BB41),0)))} -> C | BD41: =IF($BB41="","",AVERAGEIFS(Fantacalcio[Fantavoto],Fantacalcio[Squadra],$B$3,Fantacalcio[Giocatore],$BB41,Fantacalcio[VotoUtile],"SI")) -> 5.6666667 | BE41: =IF($BB41="","",SUMIFS(Fantacalcio[BonusMalus],Fantacalcio[Squadra],$B$3,Fantacalcio[Giocatore],$BB41,Fantacalcio[VotoUtile],"SI")) -> 0 | BF41: {=IF($BB41="","",IFERROR(INDEX(Mappa[VdM (mln €)],MATCH(1,(Mappa[Giocatore_DB]=$BB41)*(Mappa[Ruolo_DB]=$BC41),0)),"n.d."))} -> 40 | BG41: =IF($BB41="","",COUNTIFS(Fantacalcio[Squadra],$B$3,Fantacalcio[Giocatore],$BB41,Fantacalcio[VotoUtile],"SI")) -> 3
A42: La scheda e' parametrica: cambia la squadra in B3 (menu a tendina) e dashboard, grafico e Top 11 si ricalcolano. | BB42: Muric | BC42: {=IF($BB42="","",INDEX(Fantacalcio[Ruolo],MATCH(1,(Fantacalcio[Squadra]=$B$3)*(Fantacalcio[Giocatore]=$BB42),0)))} -> P | BD42: =IF($BB42="","",AVERAGEIFS(Fantacalcio[Fantavoto],Fantacalcio[Squadra],$B$3,Fantacalcio[Giocatore],$BB42,Fantacalcio[VotoUtile],"SI")) -> 4.25 | BE42: =IF($BB42="","",SUMIFS(Fantacalcio[BonusMalus],Fantacalcio[Squadra],$B$3,Fantacalcio[Giocatore],$BB42,Fantacalcio[VotoUtile],"SI")) -> -3 | BF42: {=IF($BB42="","",IFERROR(INDEX(Mappa[VdM (mln €)],MATCH(1,(Mappa[Giocatore_DB]=$BB42)*(Mappa[Ruolo_DB]=$BC42),0)),"n.d."))} -> 7.5 | BG42: =IF($BB42="","",COUNTIFS(Fantacalcio[Squadra],$B$3,Fantacalcio[Giocatore],$BB42,Fantacalcio[VotoUtile],"SI")) -> 2
A43: BonusMalus e Media Voto: valori ripresi dai fogli Analisi Bonus e Analisi Voto per la squadra selezionata. | BB43: Okoye | BC43: {=IF($BB43="","",INDEX(Fantacalcio[Ruolo],MATCH(1,(Fantacalcio[Squadra]=$B$3)*(Fantacalcio[Giocatore]=$BB43),0)))} -> P | BD43: =IF($BB43="","",AVERAGEIFS(Fantacalcio[Fantavoto],Fantacalcio[Squadra],$B$3,Fantacalcio[Giocatore],$BB43,Fantacalcio[VotoUtile],"SI")) -> 2.5 | BE43: =IF($BB43="","",SUMIFS(Fantacalcio[BonusMalus],Fantacalcio[Squadra],$B$3,Fantacalcio[Giocatore],$BB43,Fantacalcio[VotoUtile],"SI")) -> -2 | BF43: {=IF($BB43="","",IFERROR(INDEX(Mappa[VdM (mln €)],MATCH(1,(Mappa[Giocatore_DB]=$BB43)*(Mappa[Ruolo_DB]=$BC43),0)),"n.d."))} -> 10 | BG43: =IF($BB43="","",COUNTIFS(Fantacalcio[Squadra],$B$3,Fantacalcio[Giocatore],$BB43,Fantacalcio[VotoUtile],"SI")) -> 1
A44: VdM per giornata: somma dei valori di mercato dei giocatori con Voto Utile = SI, dal foglio Analisi VdM. Le giornate non ancora giocate restano vuote. | BB44: Palmisani | BC44: {=IF($BB44="","",INDEX(Fantacalcio[Ruolo],MATCH(1,(Fantacalcio[Squadra]=$B$3)*(Fantacalcio[Giocatore]=$BB44),0)))} -> P | BD44: =IF($BB44="","",AVERAGEIFS(Fantacalcio[Fantavoto],Fantacalcio[Squadra],$B$3,Fantacalcio[Giocatore],$BB44,Fantacalcio[VotoUtile],"SI")) -> 5 | BE44: =IF($BB44="","",SUMIFS(Fantacalcio[BonusMalus],Fantacalcio[Squadra],$B$3,Fantacalcio[Giocatore],$BB44,Fantacalcio[VotoUtile],"SI")) -> -4 | BF44: {=IF($BB44="","",IFERROR(INDEX(Mappa[VdM (mln €)],MATCH(1,(Mappa[Giocatore_DB]=$BB44)*(Mappa[Ruolo_DB]=$BC44),0)),"n.d."))} -> 6 | BG44: =IF($BB44="","",COUNTIFS(Fantacalcio[Squadra],$B$3,Fantacalcio[Giocatore],$BB44,Fantacalcio[VotoUtile],"SI")) -> 3
A45: Top 11 - selezione: tra i giocatori della squadra con almeno il numero minimo di presenze richiesto, si prendono 1 P, 3 D, 4 C e 3 A con la media Fantavoto piu' alta (modulo 3-4-3). | BB45: Pellegrino M. | BC45: {=IF($BB45="","",INDEX(Fantacalcio[Ruolo],MATCH(1,(Fantacalcio[Squadra]=$B$3)*(Fantacalcio[Giocatore]=$BB45),0)))} -> A | BD45: =IF($BB45="","",AVERAGEIFS(Fantacalcio[Fantavoto],Fantacalcio[Squadra],$B$3,Fantacalcio[Giocatore],$BB45,Fantacalcio[VotoUtile],"SI")) -> 6.5 | BE45: =IF($BB45="","",SUMIFS(Fantacalcio[BonusMalus],Fantacalcio[Squadra],$B$3,Fantacalcio[Giocatore],$BB45,Fantacalcio[VotoUtile],"SI")) -> 3 | BF45: {=IF($BB45="","",IFERROR(INDEX(Mappa[VdM (mln €)],MATCH(1,(Mappa[Giocatore_DB]=$BB45)*(Mappa[Ruolo_DB]=$BC45),0)),"n.d."))} -> 22 | BG45: =IF($BB45="","",COUNTIFS(Fantacalcio[Squadra],$B$3,Fantacalcio[Giocatore],$BB45,Fantacalcio[VotoUtile],"SI")) -> 3
A46: Presenze minime: per entrare in Top 11 il giocatore deve avere almeno 1/4 delle giornate chiuse con Voto Utile = SI, arrotondato (minimo 1). Es. 4 giornate -> 1 presenza; 7 giornate -> 2 presenze. | BB46: Ramon | BC46: {=IF($BB46="","",INDEX(Fantacalcio[Ruolo],MATCH(1,(Fantacalcio[Squadra]=$B$3)*(Fantacalcio[Giocatore]=$BB46),0)))} -> D | BD46: =IF($BB46="","",AVERAGEIFS(Fantacalcio[Fantavoto],Fantacalcio[Squadra],$B$3,Fantacalcio[Giocatore],$BB46,Fantacalcio[VotoUtile],"SI")) -> 7.125 | BE46: =IF($BB46="","",SUMIFS(Fantacalcio[BonusMalus],Fantacalcio[Squadra],$B$3,Fantacalcio[Giocatore],$BB46,Fantacalcio[VotoUtile],"SI")) -> 3 | BF46: {=IF($BB46="","",IFERROR(INDEX(Mappa[VdM (mln €)],MATCH(1,(Mappa[Giocatore_DB]=$BB46)*(Mappa[Ruolo_DB]=$BC46),0)),"n.d."))} -> 45 | BG46: =IF($BB46="","",COUNTIFS(Fantacalcio[Squadra],$B$3,Fantacalcio[Giocatore],$BB46,Fantacalcio[VotoUtile],"SI")) -> 4
A47: VdM: valore di mercato di inizio stagione (mln €), ripreso dalla tabella Mappa del foglio Mappatura. | BB47: Robinson J. | BC47: {=IF($BB47="","",INDEX(Fantacalcio[Ruolo],MATCH(1,(Fantacalcio[Squadra]=$B$3)*(Fantacalcio[Giocatore]=$BB47),0)))} -> A | BD47: =IF($BB47="","",AVERAGEIFS(Fantacalcio[Fantavoto],Fantacalcio[Squadra],$B$3,Fantacalcio[Giocatore],$BB47,Fantacalcio[VotoUtile],"SI")) -> 6.5 | BE47: =IF($BB47="","",SUMIFS(Fantacalcio[BonusMalus],Fantacalcio[Squadra],$B$3,Fantacalcio[Giocatore],$BB47,Fantacalcio[VotoUtile],"SI")) -> 0 | BF47: {=IF($BB47="","",IFERROR(INDEX(Mappa[VdM (mln €)],MATCH(1,(Mappa[Giocatore_DB]=$BB47)*(Mappa[Ruolo_DB]=$BC47),0)),"n.d."))} -> 8 | BG47: =IF($BB47="","",COUNTIFS(Fantacalcio[Squadra],$B$3,Fantacalcio[Giocatore],$BB47,Fantacalcio[VotoUtile],"SI")) -> 1
A48: Partite: numero di giornate in cui il giocatore ha avuto Voto Utile = SI (nella riga Totale, somma delle presenze utili degli 11). | BB48: Schmid | BC48: {=IF($BB48="","",INDEX(Fantacalcio[Ruolo],MATCH(1,(Fantacalcio[Squadra]=$B$3)*(Fantacalcio[Giocatore]=$BB48),0)))} -> C | BD48: =IF($BB48="","",AVERAGEIFS(Fantacalcio[Fantavoto],Fantacalcio[Squadra],$B$3,Fantacalcio[Giocatore],$BB48,Fantacalcio[VotoUtile],"SI")) -> 5.5 | BE48: =IF($BB48="","",SUMIFS(Fantacalcio[BonusMalus],Fantacalcio[Squadra],$B$3,Fantacalcio[Giocatore],$BB48,Fantacalcio[VotoUtile],"SI")) -> -0.5 | BF48: {=IF($BB48="","",IFERROR(INDEX(Mappa[VdM (mln €)],MATCH(1,(Mappa[Giocatore_DB]=$BB48)*(Mappa[Ruolo_DB]=$BC48),0)),"n.d."))} -> 15 | BG48: =IF($BB48="","",COUNTIFS(Fantacalcio[Squadra],$B$3,Fantacalcio[Giocatore],$BB48,Fantacalcio[VotoUtile],"SI")) -> 1
A49: Riga Totale: media dei Fantavoto degli 11, somma dei BonusMalus, somma dei VdM e somma delle Partite. | BB49: Vasquez | BC49: {=IF($BB49="","",INDEX(Fantacalcio[Ruolo],MATCH(1,(Fantacalcio[Squadra]=$B$3)*(Fantacalcio[Giocatore]=$BB49),0)))} -> D | BD49: =IF($BB49="","",AVERAGEIFS(Fantacalcio[Fantavoto],Fantacalcio[Squadra],$B$3,Fantacalcio[Giocatore],$BB49,Fantacalcio[VotoUtile],"SI")) -> 8 | BE49: =IF($BB49="","",SUMIFS(Fantacalcio[BonusMalus],Fantacalcio[Squadra],$B$3,Fantacalcio[Giocatore],$BB49,Fantacalcio[VotoUtile],"SI")) -> 2 | BF49: {=IF($BB49="","",IFERROR(INDEX(Mappa[VdM (mln €)],MATCH(1,(Mappa[Giocatore_DB]=$BB49)*(Mappa[Ruolo_DB]=$BC49),0)),"n.d."))} -> 14 | BG49: =IF($BB49="","",COUNTIFS(Fantacalcio[Squadra],$B$3,Fantacalcio[Giocatore],$BB49,Fantacalcio[VotoUtile],"SI")) -> 1
A50: Celle BB30:BC31 = giornate chiuse e soglia presenze minime, calcolate automaticamente dal Database. | BB50: Volpato | BC50: {=IF($BB50="","",INDEX(Fantacalcio[Ruolo],MATCH(1,(Fantacalcio[Squadra]=$B$3)*(Fantacalcio[Giocatore]=$BB50),0)))} -> C | BD50: =IF($BB50="","",AVERAGEIFS(Fantacalcio[Fantavoto],Fantacalcio[Squadra],$B$3,Fantacalcio[Giocatore],$BB50,Fantacalcio[VotoUtile],"SI")) -> 9.5 | BE50: =IF($BB50="","",SUMIFS(Fantacalcio[BonusMalus],Fantacalcio[Squadra],$B$3,Fantacalcio[Giocatore],$BB50,Fantacalcio[VotoUtile],"SI")) -> 2.5 | BF50: {=IF($BB50="","",IFERROR(INDEX(Mappa[VdM (mln €)],MATCH(1,(Mappa[Giocatore_DB]=$BB50)*(Mappa[Ruolo_DB]=$BC50),0)),"n.d."))} -> 10 | BG50: =IF($BB50="","",COUNTIFS(Fantacalcio[Squadra],$B$3,Fantacalcio[Giocatore],$BB50,Fantacalcio[VotoUtile],"SI")) -> 1
BB51: Yildiz | BC51: {=IF($BB51="","",INDEX(Fantacalcio[Ruolo],MATCH(1,(Fantacalcio[Squadra]=$B$3)*(Fantacalcio[Giocatore]=$BB51),0)))} -> A | BD51: =IF($BB51="","",AVERAGEIFS(Fantacalcio[Fantavoto],Fantacalcio[Squadra],$B$3,Fantacalcio[Giocatore],$BB51,Fantacalcio[VotoUtile],"SI")) -> 5.5 | BE51: =IF($BB51="","",SUMIFS(Fantacalcio[BonusMalus],Fantacalcio[Squadra],$B$3,Fantacalcio[Giocatore],$BB51,Fantacalcio[VotoUtile],"SI")) -> 0 | BF51: {=IF($BB51="","",IFERROR(INDEX(Mappa[VdM (mln €)],MATCH(1,(Mappa[Giocatore_DB]=$BB51)*(Mappa[Ruolo_DB]=$BC51),0)),"n.d."))} -> 75 | BG51: =IF($BB51="","",COUNTIFS(Fantacalcio[Squadra],$B$3,Fantacalcio[Giocatore],$BB51,Fantacalcio[VotoUtile],"SI")) -> 1
BB52: Zappacosta | BC52: {=IF($BB52="","",INDEX(Fantacalcio[Ruolo],MATCH(1,(Fantacalcio[Squadra]=$B$3)*(Fantacalcio[Giocatore]=$BB52),0)))} -> D | BD52: =IF($BB52="","",AVERAGEIFS(Fantacalcio[Fantavoto],Fantacalcio[Squadra],$B$3,Fantacalcio[Giocatore],$BB52,Fantacalcio[VotoUtile],"SI")) -> 6 | BE52: =IF($BB52="","",SUMIFS(Fantacalcio[BonusMalus],Fantacalcio[Squadra],$B$3,Fantacalcio[Giocatore],$BB52,Fantacalcio[VotoUtile],"SI")) -> 0 | BF52: {=IF($BB52="","",IFERROR(INDEX(Mappa[VdM (mln €)],MATCH(1,(Mappa[Giocatore_DB]=$BB52)*(Mappa[Ruolo_DB]=$BC52),0)),"n.d."))} -> 3.5 | BG52: =IF($BB52="","",COUNTIFS(Fantacalcio[Squadra],$B$3,Fantacalcio[Giocatore],$BB52,Fantacalcio[VotoUtile],"SI")) -> 1
BC53: {=IF($BB53="","",INDEX(Fantacalcio[Ruolo],MATCH(1,(Fantacalcio[Squadra]=$B$3)*(Fantacalcio[Giocatore]=$BB53),0)))} | BD53: =IF($BB53="","",AVERAGEIFS(Fantacalcio[Fantavoto],Fantacalcio[Squadra],$B$3,Fantacalcio[Giocatore],$BB53,Fantacalcio[VotoUtile],"SI")) | BE53: =IF($BB53="","",SUMIFS(Fantacalcio[BonusMalus],Fantacalcio[Squadra],$B$3,Fantacalcio[Giocatore],$BB53,Fantacalcio[VotoUtile],"SI")) | BF53: {=IF($BB53="","",IFERROR(INDEX(Mappa[VdM (mln €)],MATCH(1,(Mappa[Giocatore_DB]=$BB53)*(Mappa[Ruolo_DB]=$BC53),0)),"n.d."))} | BG53: =IF($BB53="","",COUNTIFS(Fantacalcio[Squadra],$B$3,Fantacalcio[Giocatore],$BB53,Fantacalcio[VotoUtile],"SI"))
BC54: {=IF($BB54="","",INDEX(Fantacalcio[Ruolo],MATCH(1,(Fantacalcio[Squadra]=$B$3)*(Fantacalcio[Giocatore]=$BB54),0)))} | BD54: =IF($BB54="","",AVERAGEIFS(Fantacalcio[Fantavoto],Fantacalcio[Squadra],$B$3,Fantacalcio[Giocatore],$BB54,Fantacalcio[VotoUtile],"SI")) | BE54: =IF($BB54="","",SUMIFS(Fantacalcio[BonusMalus],Fantacalcio[Squadra],$B$3,Fantacalcio[Giocatore],$BB54,Fantacalcio[VotoUtile],"SI")) | BF54: {=IF($BB54="","",IFERROR(INDEX(Mappa[VdM (mln €)],MATCH(1,(Mappa[Giocatore_DB]=$BB54)*(Mappa[Ruolo_DB]=$BC54),0)),"n.d."))} | BG54: =IF($BB54="","",COUNTIFS(Fantacalcio[Squadra],$B$3,Fantacalcio[Giocatore],$BB54,Fantacalcio[VotoUtile],"SI"))
BC55: {=IF($BB55="","",INDEX(Fantacalcio[Ruolo],MATCH(1,(Fantacalcio[Squadra]=$B$3)*(Fantacalcio[Giocatore]=$BB55),0)))} | BD55: =IF($BB55="","",AVERAGEIFS(Fantacalcio[Fantavoto],Fantacalcio[Squadra],$B$3,Fantacalcio[Giocatore],$BB55,Fantacalcio[VotoUtile],"SI")) | BE55: =IF($BB55="","",SUMIFS(Fantacalcio[BonusMalus],Fantacalcio[Squadra],$B$3,Fantacalcio[Giocatore],$BB55,Fantacalcio[VotoUtile],"SI")) | BF55: {=IF($BB55="","",IFERROR(INDEX(Mappa[VdM (mln €)],MATCH(1,(Mappa[Giocatore_DB]=$BB55)*(Mappa[Ruolo_DB]=$BC55),0)),"n.d."))} | BG55: =IF($BB55="","",COUNTIFS(Fantacalcio[Squadra],$B$3,Fantacalcio[Giocatore],$BB55,Fantacalcio[VotoUtile],"SI"))
BC56: {=IF($BB56="","",INDEX(Fantacalcio[Ruolo],MATCH(1,(Fantacalcio[Squadra]=$B$3)*(Fantacalcio[Giocatore]=$BB56),0)))} | BD56: =IF($BB56="","",AVERAGEIFS(Fantacalcio[Fantavoto],Fantacalcio[Squadra],$B$3,Fantacalcio[Giocatore],$BB56,Fantacalcio[VotoUtile],"SI")) | BE56: =IF($BB56="","",SUMIFS(Fantacalcio[BonusMalus],Fantacalcio[Squadra],$B$3,Fantacalcio[Giocatore],$BB56,Fantacalcio[VotoUtile],"SI")) | BF56: {=IF($BB56="","",IFERROR(INDEX(Mappa[VdM (mln €)],MATCH(1,(Mappa[Giocatore_DB]=$BB56)*(Mappa[Ruolo_DB]=$BC56),0)),"n.d."))} | BG56: =IF($BB56="","",COUNTIFS(Fantacalcio[Squadra],$B$3,Fantacalcio[Giocatore],$BB56,Fantacalcio[VotoUtile],"SI"))
BC57: {=IF($BB57="","",INDEX(Fantacalcio[Ruolo],MATCH(1,(Fantacalcio[Squadra]=$B$3)*(Fantacalcio[Giocatore]=$BB57),0)))} | BD57: =IF($BB57="","",AVERAGEIFS(Fantacalcio[Fantavoto],Fantacalcio[Squadra],$B$3,Fantacalcio[Giocatore],$BB57,Fantacalcio[VotoUtile],"SI")) | BE57: =IF($BB57="","",SUMIFS(Fantacalcio[BonusMalus],Fantacalcio[Squadra],$B$3,Fantacalcio[Giocatore],$BB57,Fantacalcio[VotoUtile],"SI")) | BF57: {=IF($BB57="","",IFERROR(INDEX(Mappa[VdM (mln €)],MATCH(1,(Mappa[Giocatore_DB]=$BB57)*(Mappa[Ruolo_DB]=$BC57),0)),"n.d."))} | BG57: =IF($BB57="","",COUNTIFS(Fantacalcio[Squadra],$B$3,Fantacalcio[Giocatore],$BB57,Fantacalcio[VotoUtile],"SI"))
BC58: {=IF($BB58="","",INDEX(Fantacalcio[Ruolo],MATCH(1,(Fantacalcio[Squadra]=$B$3)*(Fantacalcio[Giocatore]=$BB58),0)))} | BD58: =IF($BB58="","",AVERAGEIFS(Fantacalcio[Fantavoto],Fantacalcio[Squadra],$B$3,Fantacalcio[Giocatore],$BB58,Fantacalcio[VotoUtile],"SI")) | BE58: =IF($BB58="","",SUMIFS(Fantacalcio[BonusMalus],Fantacalcio[Squadra],$B$3,Fantacalcio[Giocatore],$BB58,Fantacalcio[VotoUtile],"SI")) | BF58: {=IF($BB58="","",IFERROR(INDEX(Mappa[VdM (mln €)],MATCH(1,(Mappa[Giocatore_DB]=$BB58)*(Mappa[Ruolo_DB]=$BC58),0)),"n.d."))} | BG58: =IF($BB58="","",COUNTIFS(Fantacalcio[Squadra],$B$3,Fantacalcio[Giocatore],$BB58,Fantacalcio[VotoUtile],"SI"))
BC59: {=IF($BB59="","",INDEX(Fantacalcio[Ruolo],MATCH(1,(Fantacalcio[Squadra]=$B$3)*(Fantacalcio[Giocatore]=$BB59),0)))} | BD59: =IF($BB59="","",AVERAGEIFS(Fantacalcio[Fantavoto],Fantacalcio[Squadra],$B$3,Fantacalcio[Giocatore],$BB59,Fantacalcio[VotoUtile],"SI")) | BE59: =IF($BB59="","",SUMIFS(Fantacalcio[BonusMalus],Fantacalcio[Squadra],$B$3,Fantacalcio[Giocatore],$BB59,Fantacalcio[VotoUtile],"SI")) | BF59: {=IF($BB59="","",IFERROR(INDEX(Mappa[VdM (mln €)],MATCH(1,(Mappa[Giocatore_DB]=$BB59)*(Mappa[Ruolo_DB]=$BC59),0)),"n.d."))} | BG59: =IF($BB59="","",COUNTIFS(Fantacalcio[Squadra],$B$3,Fantacalcio[Giocatore],$BB59,Fantacalcio[VotoUtile],"SI"))
BC60: {=IF($BB60="","",INDEX(Fantacalcio[Ruolo],MATCH(1,(Fantacalcio[Squadra]=$B$3)*(Fantacalcio[Giocatore]=$BB60),0)))} | BD60: =IF($BB60="","",AVERAGEIFS(Fantacalcio[Fantavoto],Fantacalcio[Squadra],$B$3,Fantacalcio[Giocatore],$BB60,Fantacalcio[VotoUtile],"SI")) | BE60: =IF($BB60="","",SUMIFS(Fantacalcio[BonusMalus],Fantacalcio[Squadra],$B$3,Fantacalcio[Giocatore],$BB60,Fantacalcio[VotoUtile],"SI")) | BF60: {=IF($BB60="","",IFERROR(INDEX(Mappa[VdM (mln €)],MATCH(1,(Mappa[Giocatore_DB]=$BB60)*(Mappa[Ruolo_DB]=$BC60),0)),"n.d."))} | BG60: =IF($BB60="","",COUNTIFS(Fantacalcio[Squadra],$B$3,Fantacalcio[Giocatore],$BB60,Fantacalcio[VotoUtile],"SI"))
BC61: {=IF($BB61="","",INDEX(Fantacalcio[Ruolo],MATCH(1,(Fantacalcio[Squadra]=$B$3)*(Fantacalcio[Giocatore]=$BB61),0)))} | BD61: =IF($BB61="","",AVERAGEIFS(Fantacalcio[Fantavoto],Fantacalcio[Squadra],$B$3,Fantacalcio[Giocatore],$BB61,Fantacalcio[VotoUtile],"SI")) | BE61: =IF($BB61="","",SUMIFS(Fantacalcio[BonusMalus],Fantacalcio[Squadra],$B$3,Fantacalcio[Giocatore],$BB61,Fantacalcio[VotoUtile],"SI")) | BF61: {=IF($BB61="","",IFERROR(INDEX(Mappa[VdM (mln €)],MATCH(1,(Mappa[Giocatore_DB]=$BB61)*(Mappa[Ruolo_DB]=$BC61),0)),"n.d."))} | BG61: =IF($BB61="","",COUNTIFS(Fantacalcio[Squadra],$B$3,Fantacalcio[Giocatore],$BB61,Fantacalcio[VotoUtile],"SI"))
BC62: {=IF($BB62="","",INDEX(Fantacalcio[Ruolo],MATCH(1,(Fantacalcio[Squadra]=$B$3)*(Fantacalcio[Giocatore]=$BB62),0)))} | BD62: =IF($BB62="","",AVERAGEIFS(Fantacalcio[Fantavoto],Fantacalcio[Squadra],$B$3,Fantacalcio[Giocatore],$BB62,Fantacalcio[VotoUtile],"SI")) | BE62: =IF($BB62="","",SUMIFS(Fantacalcio[BonusMalus],Fantacalcio[Squadra],$B$3,Fantacalcio[Giocatore],$BB62,Fantacalcio[VotoUtile],"SI")) | BF62: {=IF($BB62="","",IFERROR(INDEX(Mappa[VdM (mln €)],MATCH(1,(Mappa[Giocatore_DB]=$BB62)*(Mappa[Ruolo_DB]=$BC62),0)),"n.d."))} | BG62: =IF($BB62="","",COUNTIFS(Fantacalcio[Squadra],$B$3,Fantacalcio[Giocatore],$BB62,Fantacalcio[VotoUtile],"SI"))
BC63: {=IF($BB63="","",INDEX(Fantacalcio[Ruolo],MATCH(1,(Fantacalcio[Squadra]=$B$3)*(Fantacalcio[Giocatore]=$BB63),0)))} | BD63: =IF($BB63="","",AVERAGEIFS(Fantacalcio[Fantavoto],Fantacalcio[Squadra],$B$3,Fantacalcio[Giocatore],$BB63,Fantacalcio[VotoUtile],"SI")) | BE63: =IF($BB63="","",SUMIFS(Fantacalcio[BonusMalus],Fantacalcio[Squadra],$B$3,Fantacalcio[Giocatore],$BB63,Fantacalcio[VotoUtile],"SI")) | BF63: {=IF($BB63="","",IFERROR(INDEX(Mappa[VdM (mln €)],MATCH(1,(Mappa[Giocatore_DB]=$BB63)*(Mappa[Ruolo_DB]=$BC63),0)),"n.d."))} | BG63: =IF($BB63="","",COUNTIFS(Fantacalcio[Squadra],$B$3,Fantacalcio[Giocatore],$BB63,Fantacalcio[VotoUtile],"SI"))
BC64: {=IF($BB64="","",INDEX(Fantacalcio[Ruolo],MATCH(1,(Fantacalcio[Squadra]=$B$3)*(Fantacalcio[Giocatore]=$BB64),0)))} | BD64: =IF($BB64="","",AVERAGEIFS(Fantacalcio[Fantavoto],Fantacalcio[Squadra],$B$3,Fantacalcio[Giocatore],$BB64,Fantacalcio[VotoUtile],"SI")) | BE64: =IF($BB64="","",SUMIFS(Fantacalcio[BonusMalus],Fantacalcio[Squadra],$B$3,Fantacalcio[Giocatore],$BB64,Fantacalcio[VotoUtile],"SI")) | BF64: {=IF($BB64="","",IFERROR(INDEX(Mappa[VdM (mln €)],MATCH(1,(Mappa[Giocatore_DB]=$BB64)*(Mappa[Ruolo_DB]=$BC64),0)),"n.d."))} | BG64: =IF($BB64="","",COUNTIFS(Fantacalcio[Squadra],$B$3,Fantacalcio[Giocatore],$BB64,Fantacalcio[VotoUtile],"SI"))
... BC127: {=IF($BB127="","",INDEX(Fantacalcio[Ruolo],MATCH(1,(Fantacalcio[Squadra]=$B$3)*(Fantacalcio[Giocatore]=$BB127),0)))} | BD127: =IF($BB127="","",AVERAGEIFS(Fantacalcio[Fantavoto],Fantacalcio[Squadra],$B$3,Fantacalcio[Giocatore],$BB127,Fantacalcio[VotoUtile],"SI")) | BE127: =IF($BB127="","",SUMIFS(Fantacalcio[BonusMalus],Fantacalcio[Squadra],$B$3,Fantacalcio[Giocatore],$BB127,Fantacalcio[VotoUtile],"SI")) | BF127: {=IF($BB127="","",IFERROR(INDEX(Mappa[VdM (mln €)],MATCH(1,(Mappa[Giocatore_DB]=$BB127)*(Mappa[Ruolo_DB]=$BC127),0)),"n.d."))} | BG127: =IF($BB127="","",COUNTIFS(Fantacalcio[Squadra],$B$3,Fantacalcio[Giocatore],$BB127,Fantacalcio[VotoUtile],"SI"))

Sheet Giocatore
A1: Scheda Giocatore | Z1: Elenco giocatori | AA1: Squadre del giocatore
A2: Seleziona il giocatore in B3, poi la squadra in B4 (elenco delle sole squadre in cui il giocatore compare nel Database). | Z2: {=_xlfn._xlws.SORT(_xlfn.UNIQUE(_xlfn._xlws.FILTER(Fantacalcio[Giocatore],Fantacalcio[Giocatore]<>"")))} -> Adams A. | AA2: {=IF($B$3="","",_xlfn._xlws.SORT(_xlfn.UNIQUE(_xlfn._xlws.FILTER(Fantacalcio[Squadra],Fantacalcio[Giocatore]=$B$3,""))))} -> Masterchef FC
A3: Giocatore: | B3: Osmajic | C3: =IF($B$3="","",IFERROR("Ruolo: "&INDEX(Fantacalcio[Ruolo],MATCH($B$3,Fantacalcio[Giocatore],0)),"Giocatore non trovato")) -> Ruolo: A | Z3: Adams C.
A4: =IF($B$3="","","Squadra:") -> Squadra: | B4: Masterchef FC | C4: {=IF($B$3="","",_xlfn.LET(_xlpm.n,ROWS(_xlfn.UNIQUE(_xlfn._xlws.FILTER(Fantacalcio[Squadra],Fantacalcio[Giocatore]=$B$3,""))),IF($B$5="","⚠ Seleziona una squadra ("&_xlpm.n&" disponibili)",IF($B$5<>$B$4,"Squadra in B4 non valida: uso l'unica squadra disponibile",_xlpm.n&IF(_xlpm.n=1," squadra"," squadre")&" in carriera"))))} -> 1 squadra in carriera | Z4: Adzic
A5: Squadra in analisi: | B5: {=IF($B$3="","",_xlfn.LET(_xlpm.sq,_xlfn.UNIQUE(_xlfn._xlws.FILTER(Fantacalcio[Squadra],Fantacalcio[Giocatore]=$B$3,"")),IF(COUNTIFS(Fantacalcio[Giocatore],$B$3,Fantacalcio[Squadra],$B$4)>0,$B$4,IF(ROWS(_xlpm.sq)=1,INDEX(_xlpm.sq,1),""))))} -> Masterchef FC | Z5: Akanji
Z6: Alajbegovic
A7: Voti Utili | Z7: Albarracin
A8: Indicatore | B8: Valore | Z8: Atta
A9: Giornate disputate dalla squadra | B9: {=IF($B$5="",0,ROWS(_xlfn.UNIQUE(_xlfn._xlws.FILTER(Fantacalcio[Giornata],Fantacalcio[Squadra]=$B$5))))} -> 6 | Z9: Baldanzi
A10: Voti Utili (SI) | B10: =COUNTIFS(Fantacalcio[Giocatore],$B$3,Fantacalcio[Squadra],$B$5,Fantacalcio[VotoUtile],"SI") -> 2 | Z10: Barella
A11: % Voti Utili sulle giornate | B11: =IFERROR(B10/B9,0) -> 0.33333333 | Z11: Bartesaghi
A12: Media Voto (solo VU) | B12: =IFERROR(AVERAGEIFS(Fantacalcio[Voto],Fantacalcio[Giocatore],$B$3,Fantacalcio[Squadra],$B$5,Fantacalcio[VotoUtile],"SI"),"n.d.") -> 6.5 | Z12: Basic
A13: Media Fantavoto (solo VU) | B13: =IFERROR(AVERAGEIFS(Fantacalcio[Fantavoto],Fantacalcio[Giocatore],$B$3,Fantacalcio[Squadra],$B$5,Fantacalcio[VotoUtile],"SI"),"n.d.") -> 8.5 | Z13: Bastoni
Z14: Baturina
A15: Utilizzo | Z15: Bella-Kotchap
A16: Stato | B16: Giornate | C16: % (escl. N.D.) | Z16: Bellanova
A17: Titolare | B17: =COUNTIFS(Fantacalcio[Giocatore],$B$3,Fantacalcio[Squadra],$B$5,Fantacalcio[Titolare],"SI") -> 1 | C17: =IFERROR(B17/($B$17+$B$18),0) -> 0.25 | Z17: Berardi
A18: Panchina | B18: =COUNTIFS(Fantacalcio[Giocatore],$B$3,Fantacalcio[Squadra],$B$5,Fantacalcio[Titolare],"NO") -> 3 | C18: =IFERROR(B18/($B$17+$B$18),0) -> 0.75 | Z18: Berisha M.
A19: Non disponibile | B19: =MAX(0,B20-B17-B18) -> 2 | C19: esclusa | Z19: Bernabè
A20: Totale giornate | B20: =B9 -> 6 | C20: =SUM(C17:C18) -> 1 | Z20: Bernardeschi
Z21: Bernasconi
A22: Bonus | Z22: Bertola
A23: Tipo | B23: BonusMalus | Z23: Beukema
A24: Bonus con Voto Utile (SI) | B24: =SUMIFS(Fantacalcio[BonusMalus],Fantacalcio[Giocatore],$B$3,Fantacalcio[Squadra],$B$5,Fantacalcio[VotoUtile],"SI") -> 4 | Z24: Bijlow
A25: Bonus da Subentrato (Tit. NO, VU SI) | B25: =SUMIFS(Fantacalcio[BonusMalus],Fantacalcio[Giocatore],$B$3,Fantacalcio[Squadra],$B$5,Fantacalcio[Titolare],"NO",Fantacalcio[VotoUtile],"SI") -> 4 | Z25: Birindelli
A26: Bonus Persi (Voto Utile NO) | B26: =SUMIFS(Fantacalcio[BonusMalus],Fantacalcio[Giocatore],$B$3,Fantacalcio[Squadra],$B$5,Fantacalcio[VotoUtile],"NO") -> 6 | Z26: Birligea
Z27: Bisseck
A28: Giornate con BonusMalus diverso da 0 | Z28: Bobcek
A29: Giornata | B29: Squadra | C29: Bonus | D29: Titolare | E29: Voto Utile | Z29: Boga
A30: {=IF($B$5="","",_xlfn._xlws.SORT(_xlfn._xlws.FILTER(_xlfn.CHOOSECOLS(Fantacalcio[[Giornata]:[VotoUtile]],1,2,8,9,10),(Fantacalcio[Giocatore]=$B$3)*(Fantacalcio[Squadra]=$B$5)*ISNUMBER(Fantacalcio[BonusMalus])*(Fantacalcio[BonusMalus]<>0),"Nessuna giornata con bonus/malus"),1,1))} -> 3 | B30: Masterchef FC | C30: 3 | D30: NO | E30: NO | Z30: Bonny
A31: 5 | B31: Masterchef FC | C31: 3 | D31: NO | E31: NO | Z31: Borrelli
A32: 6 | B32: Masterchef FC | C32: 4 | D32: NO | E32: SI | Z32: Bowie
Z33: Bracaglia
Z34: Bremer
Z35: Busio
Z36: Butez
Z37: Cacciamani
Z38: Calhanoglu
Z39: Calò
Z40: Camarda
Z41: Cambiaghi
Z42: Cambiaso
Z43: Cancellieri
Z44: Caprile
... Z283: Zortea
